Workbook

Sheet Messages
A1: Messages Draft
A3: =IF('Profit & Loss'!A6>=TODAY(),"Looking for friendly players to join the following game: " & CHAR(10) & CHAR(10) & "Date: " & TEXT('Profit & Loss'!A6,"dd mmm yyy") & ", " & 'Profit & Loss'!B6 & CHAR(10) & "Time: " & TEXT('Profit & Loss'!C6, "hh:mm AM/PM") & " - " & TEXT('Profit & Loss'!D6, "hh:mm AM/PM") & CHAR(10) & "Venue: " & 'Profit & Loss'!E6 & CHAR(10) & "Level: HB - LI" & CHAR(10) & "Cost: $" & 'Profit & Loss'!O6 & " per pax" & CHAR(10) & "Max " & 'Profit & Loss'!I6*6 & " pax," & " (" & 'Profit & Loss'!I6 & " courts)" & CHAR(10) & CHAR(10) & "RSL Ultimate shuttles provided" & CHAR(10) & CHAR(10) & "PM if interested, thank you!"," ")
A4: =IF('Profit & Loss'!A7>=TODAY(),"Looking for friendly players to join the following game: " & CHAR(10) & CHAR(10) & "Date: " & TEXT('Profit & Loss'!A7,"dd mmm yyy") & ", " & 'Profit & Loss'!B7 & CHAR(10) & "Time: " & TEXT('Profit & Loss'!C7, "hh:mm AM/PM") & " - " & TEXT('Profit & Loss'!D7, "hh:mm AM/PM") & CHAR(10) & "Venue: " & 'Profit & Loss'!E7 & CHAR(10) & "Level: HB - LI" & CHAR(10) & "Cost: $" & 'Profit & Loss'!O7 & " per pax" & CHAR(10) & "Max " & 'Profit & Loss'!I7*6 & " pax," & " (" & 'Profit & Loss'!I7 & " courts)" & CHAR(10) & CHAR(10) & "RSL Ultimate shuttles provided" & CHAR(10) & CHAR(10) & "PM if interested, thank you!"," ")
A5: =IF('Profit & Loss'!A8>=TODAY(),"Looking for friendly players to join the following game: " & CHAR(10) & CHAR(10) & "Date: " & TEXT('Profit & Loss'!A8,"dd mmm yyy") & ", " & 'Profit & Loss'!B8 & CHAR(10) & "Time: " & TEXT('Profit & Loss'!C8, "hh:mm AM/PM") & " - " & TEXT('Profit & Loss'!D8, "hh:mm AM/PM") & CHAR(10) & "Venue: " & 'Profit & Loss'!E8 & CHAR(10) & "Level: HB - LI" & CHAR(10) & "Cost: $" & 'Profit & Loss'!O8 & " per pax" & CHAR(10) & "Max " & 'Profit & Loss'!I8*6 & " pax," & " (" & 'Profit & Loss'!I8 & " courts)" & CHAR(10) & CHAR(10) & "RSL Ultimate shuttles provided" & CHAR(10) & CHAR(10) & "PM if interested, thank you!"," ")
A6: =IF('Profit & Loss'!A9>=TODAY(),"Looking for friendly players to join the following game: " & CHAR(10) & CHAR(10) & "Date: " & TEXT('Profit & Loss'!A9,"dd mmm yyy") & ", " & 'Profit & Loss'!B9 & CHAR(10) & "Time: " & TEXT('Profit & Loss'!C9, "hh:mm AM/PM") & " - " & TEXT('Profit & Loss'!D9, "hh:mm AM/PM") & CHAR(10) & "Venue: " & 'Profit & Loss'!E9 & CHAR(10) & "Level: HB - LI" & CHAR(10) & "Cost: $" & 'Profit & Loss'!O9 & " per pax" & CHAR(10) & "Max " & 'Profit & Loss'!I9*6 & " pax," & " (" & 'Profit & Loss'!I9 & " courts)" & CHAR(10) & CHAR(10) & "RSL Ultimate shuttles provided" & CHAR(10) & CHAR(10) & "PM if interested, thank you!"," ")
A7: =IF('Profit & Loss'!A10>=TODAY(),"Looking for friendly players to join the following game: " & CHAR(10) & CHAR(10) & "Date: " & TEXT('Profit & Loss'!A10,"dd mmm yyy") & ", " & 'Profit & Loss'!B10 & CHAR(10) & "Time: " & TEXT('Profit & Loss'!C10, "hh:mm AM/PM") & " - " & TEXT('Profit & Loss'!D10, "hh:mm AM/PM") & CHAR(10) & "Venue: " & 'Profit & Loss'!E10 & CHAR(10) & "Level: HB - LI" & CHAR(10) & "Cost: $" & 'Profit & Loss'!O10 & " per pax" & CHAR(10) & "Max " & 'Profit & Loss'!I10*6 & " pax," & " (" & 'Profit & Loss'!I10 & " courts)" & CHAR(10) & CHAR(10) & "RSL Ultimate shuttles provided" & CHAR(10) & CHAR(10) & "PM if interested, thank you!"," ")
A8: =IF('Profit & Loss'!A11>=TODAY(),"Looking for friendly players to join the following game: " & CHAR(10) & CHAR(10) & "Date: " & TEXT('Profit & Loss'!A11,"dd mmm yyy") & ", " & 'Profit & Loss'!B11 & CHAR(10) & "Time: " & TEXT('Profit & Loss'!C11, "hh:mm AM/PM") & " - " & TEXT('Profit & Loss'!D11, "hh:mm AM/PM") & CHAR(10) & "Venue: " & 'Profit & Loss'!E11 & CHAR(10) & "Level: HB - LI" & CHAR(10) & "Cost: $" & 'Profit & Loss'!O11 & " per pax" & CHAR(10) & "Max " & 'Profit & Loss'!I11*6 & " pax," & " (" & 'Profit & Loss'!I11 & " courts)" & CHAR(10) & CHAR(10) & "RSL Ultimate shuttles provided" & CHAR(10) & CHAR(10) & "PM if interested, thank you!"," ")
A9: =IF('Profit & Loss'!A12>=TODAY(),"Looking for friendly players to join the following game: " & CHAR(10) & CHAR(10) & "Date: " & TEXT('Profit & Loss'!A12,"dd mmm yyy") & ", " & 'Profit & Loss'!B12 & CHAR(10) & "Time: " & TEXT('Profit & Loss'!C12, "hh:mm AM/PM") & " - " & TEXT('Profit & Loss'!D12, "hh:mm AM/PM") & CHAR(10) & "Venue: " & 'Profit & Loss'!E12 & CHAR(10) & "Level: HB - LI" & CHAR(10) & "Cost: $" & 'Profit & Loss'!O12 & " per pax" & CHAR(10) & "Max " & 'Profit & Loss'!I12*6 & " pax," & " (" & 'Profit & Loss'!I12 & " courts)" & CHAR(10) & CHAR(10) & "RSL Ultimate shuttles provided" & CHAR(10) & CHAR(10) & "PM if interested, thank you!"," ")
A10: =IF('Profit & Loss'!A13>=TODAY(),"Looking for friendly players to join the following game: " & CHAR(10) & CHAR(10) & "Date: " & TEXT('Profit & Loss'!A13,"dd mmm yyy") & ", " & 'Profit & Loss'!B13 & CHAR(10) & "Time: " & TEXT('Profit & Loss'!C13, "hh:mm AM/PM") & " - " & TEXT('Profit & Loss'!D13, "hh:mm AM/PM") & CHAR(10) & "Venue: " & 'Profit & Loss'!E13 & CHAR(10) & "Level: HB - LI" & CHAR(10) & "Cost: $" & 'Profit & Loss'!O13 & " per pax" & CHAR(10) & "Max " & 'Profit & Loss'!I13*6 & " pax," & " (" & 'Profit & Loss'!I13 & " courts)" & CHAR(10) & CHAR(10) & "RSL Ultimate shuttles provided" & CHAR(10) & CHAR(10) & "PM if interested, thank you!"," ")
A11: =IF('Profit & Loss'!A14>=TODAY(),"Looking for friendly players to join the following game: " & CHAR(10) & CHAR(10) & "Date: " & TEXT('Profit & Loss'!A14,"dd mmm yyy") & ", " & 'Profit & Loss'!B14 & CHAR(10) & "Time: " & TEXT('Profit & Loss'!C14, "hh:mm AM/PM") & " - " & TEXT('Profit & Loss'!D14, "hh:mm AM/PM") & CHAR(10) & "Venue: " & 'Profit & Loss'!E14 & CHAR(10) & "Level: HB - LI" & CHAR(10) & "Cost: $" & 'Profit & Loss'!O14 & " per pax" & CHAR(10) & "Max " & 'Profit & Loss'!I14*6 & " pax," & " (" & 'Profit & Loss'!I14 & " courts)" & CHAR(10) & CHAR(10) & "RSL Ultimate shuttles provided" & CHAR(10) & CHAR(10) & "PM if interested, thank you!"," ")
A12: =IF('Profit & Loss'!A15>=TODAY(),"Looking for friendly players to join the following game: " & CHAR(10) & CHAR(10) & "Date: " & TEXT('Profit & Loss'!A15,"dd mmm yyy") & ", " & 'Profit & Loss'!B15 & CHAR(10) & "Time: " & TEXT('Profit & Loss'!C15, "hh:mm AM/PM") & " - " & TEXT('Profit & Loss'!D15, "hh:mm AM/PM") & CHAR(10) & "Venue: " & 'Profit & Loss'!E15 & CHAR(10) & "Level: HB - LI" & CHAR(10) & "Cost: $" & 'Profit & Loss'!O15 & " per pax" & CHAR(10) & "Max " & 'Profit & Loss'!I15*6 & " pax," & " (" & 'Profit & Loss'!I15 & " courts)" & CHAR(10) & CHAR(10) & "RSL Ultimate shuttles provided" & CHAR(10) & CHAR(10) & "PM if interested, thank you!"," ")
A13: =IF('Profit & Loss'!A16>=TODAY(),"Looking for friendly players to join the following game: " & CHAR(10) & CHAR(10) & "Date: " & TEXT('Profit & Loss'!A16,"dd mmm yyy") & ", " & 'Profit & Loss'!B16 & CHAR(10) & "Time: " & TEXT('Profit & Loss'!C16, "hh:mm AM/PM") & " - " & TEXT('Profit & Loss'!D16, "hh:mm AM/PM") & CHAR(10) & "Venue: " & 'Profit & Loss'!E16 & CHAR(10) & "Level: HB - LI" & CHAR(10) & "Cost: $" & 'Profit & Loss'!O16 & " per pax" & CHAR(10) & "Max " & 'Profit & Loss'!I16*6 & " pax," & " (" & 'Profit & Loss'!I16 & " courts)" & CHAR(10) & CHAR(10) & "RSL Ultimate shuttles provided" & CHAR(10) & CHAR(10) & "PM if interested, thank you!"," ")
A14: =IF('Profit & Loss'!A17>=TODAY(),"Looking for friendly players to join the following game: " & CHAR(10) & CHAR(10) & "Date: " & TEXT('Profit & Loss'!A17,"dd mmm yyy") & ", " & 'Profit & Loss'!B17 & CHAR(10) & "Time: " & TEXT('Profit & Loss'!C17, "hh:mm AM/PM") & " - " & TEXT('Profit & Loss'!D17, "hh:mm AM/PM") & CHAR(10) & "Venue: " & 'Profit & Loss'!E17 & CHAR(10) & "Level: HB - LI" & CHAR(10) & "Cost: $" & 'Profit & Loss'!O17 & " per pax" & CHAR(10) & "Max " & 'Profit & Loss'!I17*6 & " pax," & " (" & 'Profit & Loss'!I17 & " courts)" & CHAR(10) & CHAR(10) & "RSL Ultimate shuttles provided" & CHAR(10) & CHAR(10) & "PM if interested, thank you!"," ")
A15: =IF('Profit & Loss'!A19>=TODAY(),"Looking for friendly players to join the following game: " & CHAR(10) & CHAR(10) & "Date: " & TEXT('Profit & Loss'!A19,"dd mmm yyy") & ", " & 'Profit & Loss'!B19 & CHAR(10) & "Time: " & TEXT('Profit & Loss'!C19, "hh:mm AM/PM") & " - " & TEXT('Profit & Loss'!D19, "hh:mm AM/PM") & CHAR(10) & "Venue: " & 'Profit & Loss'!E19 & CHAR(10) & "Level: HB - LI" & CHAR(10) & "Cost: $" & 'Profit & Loss'!O19 & " per pax" & CHAR(10) & "Max " & 'Profit & Loss'!I19*6 & " pax," & " (" & 'Profit & Loss'!I19 & " courts)" & CHAR(10) & CHAR(10) & "RSL Ultimate shuttles provided" & CHAR(10) & CHAR(10) & "PM if interested, thank you!"," ")
A16: =IF('Profit & Loss'!A18>=TODAY(),"Looking for friendly players to join the following game: " & CHAR(10) & CHAR(10) & "Date: " & TEXT('Profit & Loss'!A18,"dd mmm yyy") & ", " & 'Profit & Loss'!B18 & CHAR(10) & "Time: " & TEXT('Profit & Loss'!C18, "hh:mm AM/PM") & " - " & TEXT('Profit & Loss'!D18, "hh:mm AM/PM") & CHAR(10) & "Venue: " & 'Profit & Loss'!E18 & CHAR(10) & "Level: HB - LI" & CHAR(10) & "Cost: $" & 'Profit & Loss'!O18 & " per pax" & CHAR(10) & "Max " & 'Profit & Loss'!I18*6 & " pax," & " (" & 'Profit & Loss'!I18 & " courts)" & CHAR(10) & CHAR(10) & "RSL Ultimate shuttles provided" & CHAR(10) & CHAR(10) & "PM if interested, thank you!"," ")
A17: =IF('Profit & Loss'!A20>=TODAY(),"Looking for friendly players to join the following game: " & CHAR(10) & CHAR(10) & "Date: " & TEXT('Profit & Loss'!A20,"dd mmm yyy") & ", " & 'Profit & Loss'!B20 & CHAR(10) & "Time: " & TEXT('Profit & Loss'!C20, "hh:mm AM/PM") & " - " & TEXT('Profit & Loss'!D20, "hh:mm AM/PM") & CHAR(10) & "Venue: " & 'Profit & Loss'!E20 & CHAR(10) & "Level: HB - LI" & CHAR(10) & "Cost: $" & 'Profit & Loss'!O20 & " per pax" & CHAR(10) & "Max " & 'Profit & Loss'!I20*6 & " pax," & " (" & 'Profit & Loss'!I20 & " courts)" & CHAR(10) & CHAR(10) & "RSL Ultimate shuttles provided" & CHAR(10) & CHAR(10) & "PM if interested, thank you!"," ") | B17: =IF('Profit & Loss'!A20>=TODAY(), "Date: " & TEXT('Profit & Loss'!A20,"dd mmm yyy") & ", " & 'Profit & Loss'!B20 & CHAR(10) & "Time: " & TEXT('Profit & Loss'!C20, "hh:mm AM/PM") & " - " & TEXT('Profit & Loss'!D20, "hh:mm AM/PM") & CHAR(10) & "Venue: " & 'Profit & Loss'!E20 & CHAR(10) & "Court No.: " & 'Profit & Loss'!F20 & CHAR(10) & "Level: HB - LI" & CHAR(10) & "Please transfer $" & 'Profit & Loss'!O20 & " per pax to Belle (83396501)" & CHAR(10) & CHAR(10) & IF('Profit & Loss'!I20=1, "1." & CHAR(10) & "2." & CHAR(10) & "3." & CHAR(10) & "4." & CHAR(10) & "5." & CHAR(10) & "6." & CHAR(10), IF('Profit & Loss'!I20=2, "1." & CHAR(10) & "2." & CHAR(10) & "3." & CHAR(10) & "4." & CHAR(10) & "5." & CHAR(10) & "6." & CHAR(10) & "7." & CHAR(10) & "8." & CHAR(10) & "9." & CHAR(10) & "10." & CHAR(10) & "11." & CHAR(10) & "12." & CHAR(10), IF('Profit & Loss'!I20=3, "1." & CHAR(10) & "2." & CHAR(10) & "3." & CHAR(10) & "4." & CHAR(10) & "5." & CHAR(10) & "6." & CHAR(10) & "7." & CHAR(10) & "8." & CHAR(10) & "9." & CHAR(10) & "10." & CHAR(10) & "11." & CHAR(10) & "12." & CHAR(10) & "13." & CHAR(10) & "14." & CHAR(10) & "15." & CHAR(10) & "16." & CHAR(10) & "17." & CHAR(10) & "18." & CHAR(10), " ")))," ")
A18: =IF('Profit & Loss'!A21>=TODAY(),"Looking for friendly players to join the following game: " & CHAR(10) & CHAR(10) & "Date: " & TEXT('Profit & Loss'!A21,"dd mmm yyy") & ", " & 'Profit & Loss'!B21 & CHAR(10) & "Time: " & TEXT('Profit & Loss'!C21, "hh:mm AM/PM") & " - " & TEXT('Profit & Loss'!D21, "hh:mm AM/PM") & CHAR(10) & "Venue: " & 'Profit & Loss'!E21 & CHAR(10) & "Level: HB - LI" & CHAR(10) & "Cost: $" & 'Profit & Loss'!O21 & " per pax" & CHAR(10) & "Max " & 'Profit & Loss'!I21*6 & " pax," & " (" & 'Profit & Loss'!I21 & " courts)" & CHAR(10) & CHAR(10) & "RSL Ultimate shuttles provided" & CHAR(10) & CHAR(10) & "PM if interested, thank you!"," ") | B18: =IF('Profit & Loss'!A21>=TODAY(), "Date: " & TEXT('Profit & Loss'!A21,"dd mmm yyy") & ", " & 'Profit & Loss'!B21 & CHAR(10) & "Time: " & TEXT('Profit & Loss'!C21, "hh:mm AM/PM") & " - " & TEXT('Profit & Loss'!D21, "hh:mm AM/PM") & CHAR(10) & "Venue: " & 'Profit & Loss'!E21 & CHAR(10) & "Court No.: " & 'Profit & Loss'!F21 & CHAR(10) & "Level: HB - LI" & CHAR(10) & "Please transfer $" & 'Profit & Loss'!O21 & " per pax to Belle (83396501)" & CHAR(10) & CHAR(10) & IF('Profit & Loss'!I21=1, "1." & CHAR(10) & "2." & CHAR(10) & "3." & CHAR(10) & "4." & CHAR(10) & "5." & CHAR(10) & "6." & CHAR(10), IF('Profit & Loss'!I21=2, "1." & CHAR(10) & "2." & CHAR(10) & "3." & CHAR(10) & "4." & CHAR(10) & "5." & CHAR(10) & "6." & CHAR(10) & "7." & CHAR(10) & "8." & CHAR(10) & "9." & CHAR(10) & "10." & CHAR(10) & "11." & CHAR(10) & "12." & CHAR(10), IF('Profit & Loss'!I21=3, "1." & CHAR(10) & "2." & CHAR(10) & "3." & CHAR(10) & "4." & CHAR(10) & "5." & CHAR(10) & "6." & CHAR(10) & "7." & CHAR(10) & "8." & CHAR(10) & "9." & CHAR(10) & "10." & CHAR(10) & "11." & CHAR(10) & "12." & CHAR(10) & "13." & CHAR(10) & "14." & CHAR(10) & "15." & CHAR(10) & "16." & CHAR(10) & "17." & CHAR(10) & "18." & CHAR(10), " ")))," ")
A19: =IF('Profit & Loss'!A22>=TODAY(),"Looking for friendly players to join the following game: " & CHAR(10) & CHAR(10) & "Date: " & TEXT('Profit & Loss'!A22,"dd mmm yyy") & ", " & 'Profit & Loss'!B22 & CHAR(10) & "Time: " & TEXT('Profit & Loss'!C22, "hh:mm AM/PM") & " - " & TEXT('Profit & Loss'!D22, "hh:mm AM/PM") & CHAR(10) & "Venue: " & 'Profit & Loss'!E22 & CHAR(10) & "Level: HB - LI" & CHAR(10) & "Cost: $" & 'Profit & Loss'!O22 & " per pax" & CHAR(10) & "Max " & 'Profit & Loss'!I22*6 & " pax," & " (" & 'Profit & Loss'!I22 & " courts)" & CHAR(10) & CHAR(10) & "RSL Ultimate shuttles provided" & CHAR(10) & CHAR(10) & "PM if interested, thank you!"," ") | B19: =IF('Profit & Loss'!A22>=TODAY(), "Date: " & TEXT('Profit & Loss'!A22,"dd mmm yyy") & ", " & 'Profit & Loss'!B22 & CHAR(10) & "Time: " & TEXT('Profit & Loss'!C22, "hh:mm AM/PM") & " - " & TEXT('Profit & Loss'!D22, "hh:mm AM/PM") & CHAR(10) & "Venue: " & 'Profit & Loss'!E22 & CHAR(10) & "Court No.: " & 'Profit & Loss'!F22 & CHAR(10) & "Level: HB - LI" & CHAR(10) & "Please transfer $" & 'Profit & Loss'!O22 & " per pax to Belle (83396501)" & CHAR(10) & CHAR(10) & IF('Profit & Loss'!I22=1, "1." & CHAR(10) & "2." & CHAR(10) & "3." & CHAR(10) & "4." & CHAR(10) & "5." & CHAR(10) & "6." & CHAR(10), IF('Profit & Loss'!I22=2, "1." & CHAR(10) & "2." & CHAR(10) & "3." & CHAR(10) & "4." & CHAR(10) & "5." & CHAR(10) & "6." & CHAR(10) & "7." & CHAR(10) & "8." & CHAR(10) & "9." & CHAR(10) & "10." & CHAR(10) & "11." & CHAR(10) & "12." & CHAR(10), IF('Profit & Loss'!I22=3, "1." & CHAR(10) & "2." & CHAR(10) & "3." & CHAR(10) & "4." & CHAR(10) & "5." & CHAR(10) & "6." & CHAR(10) & "7." & CHAR(10) & "8." & CHAR(10) & "9." & CHAR(10) & "10." & CHAR(10) & "11." & CHAR(10) & "12." & CHAR(10) & "13." & CHAR(10) & "14." & CHAR(10) & "15." & CHAR(10) & "16." & CHAR(10) & "17." & CHAR(10) & "18." & CHAR(10), " ")))," ")
A20: =IF('Profit & Loss'!A23>=TODAY(),"Looking for friendly players to join the following game: " & CHAR(10) & CHAR(10) & "Date: " & TEXT('Profit & Loss'!A23,"dd mmm yyy") & ", " & 'Profit & Loss'!B23 & CHAR(10) & "Time: " & TEXT('Profit & Loss'!C23, "hh:mm AM/PM") & " - " & TEXT('Profit & Loss'!D23, "hh:mm AM/PM") & CHAR(10) & "Venue: " & 'Profit & Loss'!E23 & CHAR(10) & "Level: HB - LI" & CHAR(10) & "Cost: $" & 'Profit & Loss'!O23 & " per pax" & CHAR(10) & "Max " & 'Profit & Loss'!I23*6 & " pax," & " (" & 'Profit & Loss'!I23 & " courts)" & CHAR(10) & CHAR(10) & "RSL Ultimate shuttles provided" & CHAR(10) & CHAR(10) & "PM if interested, thank you!"," ") | B20: =IF('Profit & Loss'!A23>=TODAY(), "Date: " & TEXT('Profit & Loss'!A23,"dd mmm yyy") & ", " & 'Profit & Loss'!B23 & CHAR(10) & "Time: " & TEXT('Profit & Loss'!C23, "hh:mm AM/PM") & " - " & TEXT('Profit & Loss'!D23, "hh:mm AM/PM") & CHAR(10) & "Venue: " & 'Profit & Loss'!E23 & CHAR(10) & "Court No.: " & 'Profit & Loss'!F23 & CHAR(10) & "Level: HB - LI" & CHAR(10) & "Please transfer $" & 'Profit & Loss'!O23 & " per pax to Belle (83396501)" & CHAR(10) & CHAR(10) & IF('Profit & Loss'!I23=1, "1." & CHAR(10) & "2." & CHAR(10) & "3." & CHAR(10) & "4." & CHAR(10) & "5." & CHAR(10) & "6." & CHAR(10), IF('Profit & Loss'!I23=2, "1." & CHAR(10) & "2." & CHAR(10) & "3." & CHAR(10) & "4." & CHAR(10) & "5." & CHAR(10) & "6." & CHAR(10) & "7." & CHAR(10) & "8." & CHAR(10) & "9." & CHAR(10) & "10." & CHAR(10) & "11." & CHAR(10) & "12." & CHAR(10), IF('Profit & Loss'!I23=3, "1." & CHAR(10) & "2." & CHAR(10) & "3." & CHAR(10) & "4." & CHAR(10) & "5." & CHAR(10) & "6." & CHAR(10) & "7." & CHAR(10) & "8." & CHAR(10) & "9." & CHAR(10) & "10." & CHAR(10) & "11." & CHAR(10) & "12." & CHAR(10) & "13." & CHAR(10) & "14." & CHAR(10) & "15." & CHAR(10) & "16." & CHAR(10) & "17." & CHAR(10) & "18." & CHAR(10), " ")))," ")
A21: =IF('Profit & Loss'!A24>=TODAY(),"Looking for friendly players to join the following game: " & CHAR(10) & CHAR(10) & "Date: " & TEXT('Profit & Loss'!A24,"dd mmm yyy") & ", " & 'Profit & Loss'!B24 & CHAR(10) & "Time: " & TEXT('Profit & Loss'!C24, "hh:mm AM/PM") & " - " & TEXT('Profit & Loss'!D24, "hh:mm AM/PM") & CHAR(10) & "Venue: " & 'Profit & Loss'!E24 & CHAR(10) & "Level: HB - LI" & CHAR(10) & "Cost: $" & 'Profit & Loss'!O24 & " per pax" & CHAR(10) & "Max " & 'Profit & Loss'!I24*6 & " pax," & " (" & 'Profit & Loss'!I24 & " courts)" & CHAR(10) & CHAR(10) & "RSL Ultimate shuttles provided" & CHAR(10) & CHAR(10) & "PM if interested, thank you!"," ") | B21: =IF('Profit & Loss'!A24>=TODAY(), "Date: " & TEXT('Profit & Loss'!A24,"dd mmm yyy") & ", " & 'Profit & Loss'!B24 & CHAR(10) & "Time: " & TEXT('Profit & Loss'!C24, "hh:mm AM/PM") & " - " & TEXT('Profit & Loss'!D24, "hh:mm AM/PM") & CHAR(10) & "Venue: " & 'Profit & Loss'!E24 & CHAR(10) & "Court No.: " & 'Profit & Loss'!F24 & CHAR(10) & "Level: HB - LI" & CHAR(10) & "Please transfer $" & 'Profit & Loss'!O24 & " per pax to Belle (83396501)" & CHAR(10) & CHAR(10) & IF('Profit & Loss'!I24=1, "1." & CHAR(10) & "2." & CHAR(10) & "3." & CHAR(10) & "4." & CHAR(10) & "5." & CHAR(10) & "6." & CHAR(10), IF('Profit & Loss'!I24=2, "1." & CHAR(10) & "2." & CHAR(10) & "3." & CHAR(10) & "4." & CHAR(10) & "5." & CHAR(10) & "6." & CHAR(10) & "7." & CHAR(10) & "8." & CHAR(10) & "9." & CHAR(10) & "10." & CHAR(10) & "11." & CHAR(10) & "12." & CHAR(10), IF('Profit & Loss'!I24=3, "1." & CHAR(10) & "2." & CHAR(10) & "3." & CHAR(10) & "4." & CHAR(10) & "5." & CHAR(10) & "6." & CHAR(10) & "7." & CHAR(10) & "8." & CHAR(10) & "9." & CHAR(10) & "10." & CHAR(10) & "11." & CHAR(10) & "12." & CHAR(10) & "13." & CHAR(10) & "14." & CHAR(10) & "15." & CHAR(10) & "16." & CHAR(10) & "17." & CHAR(10) & "18." & CHAR(10), " ")))," ")
A22: =IF('Profit & Loss'!A25>=TODAY(),"Looking for friendly players to join the following game: " & CHAR(10) & CHAR(10) & "Date: " & TEXT('Profit & Loss'!A25,"dd mmm yyy") & ", " & 'Profit & Loss'!B25 & CHAR(10) & "Time: " & TEXT('Profit & Loss'!C25, "hh:mm AM/PM") & " - " & TEXT('Profit & Loss'!D25, "hh:mm AM/PM") & CHAR(10) & "Venue: " & 'Profit & Loss'!E25 & CHAR(10) & "Level: HB - LI" & CHAR(10) & "Cost: $" & 'Profit & Loss'!O25 & " per pax" & CHAR(10) & "Max " & 'Profit & Loss'!I25*6 & " pax," & " (" & 'Profit & Loss'!I25 & " courts)" & CHAR(10) & CHAR(10) & "RSL Ultimate shuttles provided" & CHAR(10) & CHAR(10) & "PM if interested, thank you!"," ") | B22: =IF('Profit & Loss'!A25>=TODAY(), "Date: " & TEXT('Profit & Loss'!A25,"dd mmm yyy") & ", " & 'Profit & Loss'!B25 & CHAR(10) & "Time: " & TEXT('Profit & Loss'!C25, "hh:mm AM/PM") & " - " & TEXT('Profit & Loss'!D25, "hh:mm AM/PM") & CHAR(10) & "Venue: " & 'Profit & Loss'!E25 & CHAR(10) & "Court No.: " & 'Profit & Loss'!F25 & CHAR(10) & "Level: HB - LI" & CHAR(10) & "Please transfer $" & 'Profit & Loss'!O25 & " per pax to Belle (83396501)" & CHAR(10) & CHAR(10) & IF('Profit & Loss'!I25=1, "1." & CHAR(10) & "2." & CHAR(10) & "3." & CHAR(10) & "4." & CHAR(10) & "5." & CHAR(10) & "6." & CHAR(10), IF('Profit & Loss'!I25=2, "1." & CHAR(10) & "2." & CHAR(10) & "3." & CHAR(10) & "4." & CHAR(10) & "5." & CHAR(10) & "6." & CHAR(10) & "7." & CHAR(10) & "8." & CHAR(10) & "9." & CHAR(10) & "10." & CHAR(10) & "11." & CHAR(10) & "12." & CHAR(10), IF('Profit & Loss'!I25=3, "1." & CHAR(10) & "2." & CHAR(10) & "3." & CHAR(10) & "4." & CHAR(10) & "5." & CHAR(10) & "6." & CHAR(10) & "7." & CHAR(10) & "8." & CHAR(10) & "9." & CHAR(10) & "10." & CHAR(10) & "11." & CHAR(10) & "12." & CHAR(10) & "13." & CHAR(10) & "14." & CHAR(10) & "15." & CHAR(10) & "16." & CHAR(10) & "17." & CHAR(10) & "18." & CHAR(10), " ")))," ")
A23: =IF('Profit & Loss'!A26>=TODAY(),"Looking for friendly players to join the following game: " & CHAR(10) & CHAR(10) & "Date: " & TEXT('Profit & Loss'!A26,"dd mmm yyy") & ", " & 'Profit & Loss'!B26 & CHAR(10) & "Time: " & TEXT('Profit & Loss'!C26, "hh:mm AM/PM") & " - " & TEXT('Profit & Loss'!D26, "hh:mm AM/PM") & CHAR(10) & "Venue: " & 'Profit & Loss'!E26 & CHAR(10) & "Level: HB - LI" & CHAR(10) & "Cost: $" & 'Profit & Loss'!O26 & " per pax" & CHAR(10) & "Max " & 'Profit & Loss'!I26*6 & " pax," & " (" & 'Profit & Loss'!I26 & " courts)" & CHAR(10) & CHAR(10) & "RSL Ultimate shuttles provided" & CHAR(10) & CHAR(10) & "PM if interested, thank you!"," ") | B23: =IF('Profit & Loss'!A26>=TODAY(), "Date: " & TEXT('Profit & Loss'!A26,"dd mmm yyy") & ", " & 'Profit & Loss'!B26 & CHAR(10) & "Time: " & TEXT('Profit & Loss'!C26, "hh:mm AM/PM") & " - " & TEXT('Profit & Loss'!D26, "hh:mm AM/PM") & CHAR(10) & "Venue: " & 'Profit & Loss'!E26 & CHAR(10) & "Court No.: " & 'Profit & Loss'!F26 & CHAR(10) & "Level: HB - LI" & CHAR(10) & "Please transfer $" & 'Profit & Loss'!O26 & " per pax to Belle (83396501)" & CHAR(10) & CHAR(10) & IF('Profit & Loss'!I26=1, "1." & CHAR(10) & "2." & CHAR(10) & "3." & CHAR(10) & "4." & CHAR(10) & "5." & CHAR(10) & "6." & CHAR(10), IF('Profit & Loss'!I26=2, "1." & CHAR(10) & "2." & CHAR(10) & "3." & CHAR(10) & "4." & CHAR(10) & "5." & CHAR(10) & "6." & CHAR(10) & "7." & CHAR(10) & "8." & CHAR(10) & "9." & CHAR(10) & "10." & CHAR(10) & "11." & CHAR(10) & "12." & CHAR(10), IF('Profit & Loss'!I26=3, "1." & CHAR(10) & "2." & CHAR(10) & "3." & CHAR(10) & "4." & CHAR(10) & "5." & CHAR(10) & "6." & CHAR(10) & "7." & CHAR(10) & "8." & CHAR(10) & "9." & CHAR(10) & "10." & CHAR(10) & "11." & CHAR(10) & "12." & CHAR(10) & "13." & CHAR(10) & "14." & CHAR(10) & "15." & CHAR(10) & "16." & CHAR(10) & "17." & CHAR(10) & "18." & CHAR(10), " ")))," ")
A24: =IF('Profit & Loss'!A27>=TODAY(),"Looking for friendly players to join the following game: " & CHAR(10) & CHAR(10) & "Date: " & TEXT('Profit & Loss'!A27,"dd mmm yyy") & ", " & 'Profit & Loss'!B27 & CHAR(10) & "Time: " & TEXT('Profit & Loss'!C27, "hh:mm AM/PM") & " - " & TEXT('Profit & Loss'!D27, "hh:mm AM/PM") & CHAR(10) & "Venue: " & 'Profit & Loss'!E27 & CHAR(10) & "Level: HB - LI" & CHAR(10) & "Cost: $" & 'Profit & Loss'!O27 & " per pax" & CHAR(10) & "Max " & 'Profit & Loss'!I27*6 & " pax," & " (" & 'Profit & Loss'!I27 & " courts)" & CHAR(10) & CHAR(10) & "RSL Ultimate shuttles provided" & CHAR(10) & CHAR(10) & "PM if interested, thank you!"," ") | B24: =IF('Profit & Loss'!A27>=TODAY(), "Date: " & TEXT('Profit & Loss'!A27,"dd mmm yyy") & ", " & 'Profit & Loss'!B27 & CHAR(10) & "Time: " & TEXT('Profit & Loss'!C27, "hh:mm AM/PM") & " - " & TEXT('Profit & Loss'!D27, "hh:mm AM/PM") & CHAR(10) & "Venue: " & 'Profit & Loss'!E27 & CHAR(10) & "Court No.: " & 'Profit & Loss'!F27 & CHAR(10) & "Level: HB - LI" & CHAR(10) & "Please transfer $" & 'Profit & Loss'!O27 & " per pax to Belle (83396501)" & CHAR(10) & CHAR(10) & IF('Profit & Loss'!I27=1, "1." & CHAR(10) & "2." & CHAR(10) & "3." & CHAR(10) & "4." & CHAR(10) & "5." & CHAR(10) & "6." & CHAR(10), IF('Profit & Loss'!I27=2, "1." & CHAR(10) & "2." & CHAR(10) & "3." & CHAR(10) & "4." & CHAR(10) & "5." & CHAR(10) & "6." & CHAR(10) & "7." & CHAR(10) & "8." & CHAR(10) & "9." & CHAR(10) & "10." & CHAR(10) & "11." & CHAR(10) & "12." & CHAR(10), IF('Profit & Loss'!I27=3, "1." & CHAR(10) & "2." & CHAR(10) & "3." & CHAR(10) & "4." & CHAR(10) & "5." & CHAR(10) & "6." & CHAR(10) & "7." & CHAR(10) & "8." & CHAR(10) & "9." & CHAR(10) & "10." & CHAR(10) & "11." & CHAR(10) & "12." & CHAR(10) & "13." & CHAR(10) & "14." & CHAR(10) & "15." & CHAR(10) & "16." & CHAR(10) & "17." & CHAR(10) & "18." & CHAR(10), " ")))," ")
A25: =IF('Profit & Loss'!A28>=TODAY(),"Looking for friendly players to join the following game: " & CHAR(10) & CHAR(10) & "Date: " & TEXT('Profit & Loss'!A28,"dd mmm yyy") & ", " & 'Profit & Loss'!B28 & CHAR(10) & "Time: " & TEXT('Profit & Loss'!C28, "hh:mm AM/PM") & " - " & TEXT('Profit & Loss'!D28, "hh:mm AM/PM") & CHAR(10) & "Venue: " & 'Profit & Loss'!E28 & CHAR(10) & "Level: HB - LI" & CHAR(10) & "Cost: $" & 'Profit & Loss'!O28 & " per pax" & CHAR(10) & "Max " & 'Profit & Loss'!I28*6 & " pax," & " (" & 'Profit & Loss'!I28 & " courts)" & CHAR(10) & CHAR(10) & "RSL Ultimate shuttles provided" & CHAR(10) & CHAR(10) & "PM if interested, thank you!"," ") | B25: =IF('Profit & Loss'!A28>=TODAY(), "Date: " & TEXT('Profit & Loss'!A28,"dd mmm yyy") & ", " & 'Profit & Loss'!B28 & CHAR(10) & "Time: " & TEXT('Profit & Loss'!C28, "hh:mm AM/PM") & " - " & TEXT('Profit & Loss'!D28, "hh:mm AM/PM") & CHAR(10) & "Venue: " & 'Profit & Loss'!E28 & CHAR(10) & "Court No.: " & 'Profit & Loss'!F28 & CHAR(10) & "Level: HB - LI" & CHAR(10) & "Please transfer $" & 'Profit & Loss'!O28 & " per pax to Belle (83396501)" & CHAR(10) & CHAR(10) & IF('Profit & Loss'!I28=1, "1." & CHAR(10) & "2." & CHAR(10) & "3." & CHAR(10) & "4." & CHAR(10) & "5." & CHAR(10) & "6." & CHAR(10), IF('Profit & Loss'!I28=2, "1." & CHAR(10) & "2." & CHAR(10) & "3." & CHAR(10) & "4." & CHAR(10) & "5." & CHAR(10) & "6." & CHAR(10) & "7." & CHAR(10) & "8." & CHAR(10) & "9." & CHAR(10) & "10." & CHAR(10) & "11." & CHAR(10) & "12." & CHAR(10), IF('Profit & Loss'!I28=3, "1." & CHAR(10) & "2." & CHAR(10) & "3." & CHAR(10) & "4." & CHAR(10) & "5." & CHAR(10) & "6." & CHAR(10) & "7." & CHAR(10) & "8." & CHAR(10) & "9." & CHAR(10) & "10." & CHAR(10) & "11." & CHAR(10) & "12." & CHAR(10) & "13." & CHAR(10) & "14." & CHAR(10) & "15." & CHAR(10) & "16." & CHAR(10) & "17." & CHAR(10) & "18." & CHAR(10), " ")))," ")
A26: =IF('Profit & Loss'!A29>=TODAY(),"Looking for friendly players to join the following game: " & CHAR(10) & CHAR(10) & "Date: " & TEXT('Profit & Loss'!A29,"dd mmm yyy") & ", " & 'Profit & Loss'!B29 & CHAR(10) & "Time: " & TEXT('Profit & Loss'!C29, "hh:mm AM/PM") & " - " & TEXT('Profit & Loss'!D29, "hh:mm AM/PM") & CHAR(10) & "Venue: " & 'Profit & Loss'!E29 & CHAR(10) & "Level: HB - LI" & CHAR(10) & "Cost: $" & 'Profit & Loss'!O29 & " per pax" & CHAR(10) & "Max " & 'Profit & Loss'!I29*6 & " pax," & " (" & 'Profit & Loss'!I29 & " courts)" & CHAR(10) & CHAR(10) & "RSL Ultimate shuttles provided" & CHAR(10) & CHAR(10) & "PM if interested, thank you!"," ") | B26: =IF('Profit & Loss'!A29>=TODAY(), "Date: " & TEXT('Profit & Loss'!A29,"dd mmm yyy") & ", " & 'Profit & Loss'!B29 & CHAR(10) & "Time: " & TEXT('Profit & Loss'!C29, "hh:mm AM/PM") & " - " & TEXT('Profit & Loss'!D29, "hh:mm AM/PM") & CHAR(10) & "Venue: " & 'Profit & Loss'!E29 & CHAR(10) & "Court No.: " & 'Profit & Loss'!F29 & CHAR(10) & "Level: HB - LI" & CHAR(10) & "Please transfer $" & 'Profit & Loss'!O29 & " per pax to Belle (83396501)" & CHAR(10) & CHAR(10) & IF('Profit & Loss'!I29=1, "1." & CHAR(10) & "2." & CHAR(10) & "3." & CHAR(10) & "4." & CHAR(10) & "5." & CHAR(10) & "6." & CHAR(10), IF('Profit & Loss'!I29=2, "1." & CHAR(10) & "2." & CHAR(10) & "3." & CHAR(10) & "4." & CHAR(10) & "5." & CHAR(10) & "6." & CHAR(10) & "7." & CHAR(10) & "8." & CHAR(10) & "9." & CHAR(10) & "10." & CHAR(10) & "11." & CHAR(10) & "12." & CHAR(10), IF('Profit & Loss'!I29=3, "1." & CHAR(10) & "2." & CHAR(10) & "3." & CHAR(10) & "4." & CHAR(10) & "5." & CHAR(10) & "6." & CHAR(10) & "7." & CHAR(10) & "8." & CHAR(10) & "9." & CHAR(10) & "10." & CHAR(10) & "11." & CHAR(10) & "12." & CHAR(10) & "13." & CHAR(10) & "14." & CHAR(10) & "15." & CHAR(10) & "16." & CHAR(10) & "17." & CHAR(10) & "18." & CHAR(10), " ")))," ")
A27: =IF('Profit & Loss'!A30>=TODAY(),"Looking for friendly players to join the following game: " & CHAR(10) & CHAR(10) & "Date: " & TEXT('Profit & Loss'!A30,"dd mmm yyy") & ", " & 'Profit & Loss'!B30 & CHAR(10) & "Time: " & TEXT('Profit & Loss'!C30, "hh:mm AM/PM") & " - " & TEXT('Profit & Loss'!D30, "hh:mm AM/PM") & CHAR(10) & "Venue: " & 'Profit & Loss'!E30 & CHAR(10) & "Level: HB - LI" & CHAR(10) & "Cost: $" & 'Profit & Loss'!O30 & " per pax" & CHAR(10) & "Max " & 'Profit & Loss'!I30*6 & " pax," & " (" & 'Profit & Loss'!I30 & " courts)" & CHAR(10) & CHAR(10) & "RSL Ultimate shuttles provided" & CHAR(10) & CHAR(10) & "PM if interested, thank you!"," ") | B27: =IF('Profit & Loss'!A30>=TODAY(), "Date: " & TEXT('Profit & Loss'!A30,"dd mmm yyy") & ", " & 'Profit & Loss'!B30 & CHAR(10) & "Time: " & TEXT('Profit & Loss'!C30, "hh:mm AM/PM") & " - " & TEXT('Profit & Loss'!D30, "hh:mm AM/PM") & CHAR(10) & "Venue: " & 'Profit & Loss'!E30 & CHAR(10) & "Court No.: " & 'Profit & Loss'!F30 & CHAR(10) & "Level: HB - LI" & CHAR(10) & "Please transfer $" & 'Profit & Loss'!O30 & " per pax to Belle (83396501)" & CHAR(10) & CHAR(10) & IF('Profit & Loss'!I30=1, "1." & CHAR(10) & "2." & CHAR(10) & "3." & CHAR(10) & "4." & CHAR(10) & "5." & CHAR(10) & "6." & CHAR(10), IF('Profit & Loss'!I30=2, "1." & CHAR(10) & "2." & CHAR(10) & "3." & CHAR(10) & "4." & CHAR(10) & "5." & CHAR(10) & "6." & CHAR(10) & "7." & CHAR(10) & "8." & CHAR(10) & "9." & CHAR(10) & "10." & CHAR(10) & "11." & CHAR(10) & "12." & CHAR(10), IF('Profit & Loss'!I30=3, "1." & CHAR(10) & "2." & CHAR(10) & "3." & CHAR(10) & "4." & CHAR(10) & "5." & CHAR(10) & "6." & CHAR(10) & "7." & CHAR(10) & "8." & CHAR(10) & "9." & CHAR(10) & "10." & CHAR(10) & "11." & CHAR(10) & "12." & CHAR(10) & "13." & CHAR(10) & "14." & CHAR(10) & "15." & CHAR(10) & "16." & CHAR(10) & "17." & CHAR(10) & "18." & CHAR(10), " ")))," ")
A28: =IF('Profit & Loss'!A31>=TODAY(),"Looking for friendly players to join the following game: " & CHAR(10) & CHAR(10) & "Date: " & TEXT('Profit & Loss'!A31,"dd mmm yyy") & ", " & 'Profit & Loss'!B31 & CHAR(10) & "Time: " & TEXT('Profit & Loss'!C31, "hh:mm AM/PM") & " - " & TEXT('Profit & Loss'!D31, "hh:mm AM/PM") & CHAR(10) & "Venue: " & 'Profit & Loss'!E31 & CHAR(10) & "Level: HB - LI" & CHAR(10) & "Cost: $" & 'Profit & Loss'!O31 & " per pax" & CHAR(10) & "Max " & 'Profit & Loss'!I31*6 & " pax," & " (" & 'Profit & Loss'!I31 & " courts)" & CHAR(10) & CHAR(10) & "RSL Ultimate shuttles provided" & CHAR(10) & CHAR(10) & "PM if interested, thank you!"," ") | B28: =IF('Profit & Loss'!A31>=TODAY(), "Date: " & TEXT('Profit & Loss'!A31,"dd mmm yyy") & ", " & 'Profit & Loss'!B31 & CHAR(10) & "Time: " & TEXT('Profit & Loss'!C31, "hh:mm AM/PM") & " - " & TEXT('Profit & Loss'!D31, "hh:mm AM/PM") & CHAR(10) & "Venue: " & 'Profit & Loss'!E31 & CHAR(10) & "Court No.: " & 'Profit & Loss'!F31 & CHAR(10) & "Level: HB - LI" & CHAR(10) & "Please transfer $" & 'Profit & Loss'!O31 & " per pax to Belle (83396501)" & CHAR(10) & CHAR(10) & IF('Profit & Loss'!I31=1, "1." & CHAR(10) & "2." & CHAR(10) & "3." & CHAR(10) & "4." & CHAR(10) & "5." & CHAR(10) & "6." & CHAR(10), IF('Profit & Loss'!I31=2, "1." & CHAR(10) & "2." & CHAR(10) & "3." & CHAR(10) & "4." & CHAR(10) & "5." & CHAR(10) & "6." & CHAR(10) & "7." & CHAR(10) & "8." & CHAR(10) & "9." & CHAR(10) & "10." & CHAR(10) & "11." & CHAR(10) & "12." & CHAR(10), IF('Profit & Loss'!I31=3, "1." & CHAR(10) & "2." & CHAR(10) & "3." & CHAR(10) & "4." & CHAR(10) & "5." & CHAR(10) & "6." & CHAR(10) & "7." & CHAR(10) & "8." & CHAR(10) & "9." & CHAR(10) & "10." & CHAR(10) & "11." & CHAR(10) & "12." & CHAR(10) & "13." & CHAR(10) & "14." & CHAR(10) & "15." & CHAR(10) & "16." & CHAR(10) & "17." & CHAR(10) & "18." & CHAR(10), " ")))," ")
... A32: =IF('Profit & Loss'!A35>=TODAY(),"Looking for friendly players to join the following game: " & CHAR(10) & CHAR(10) & "Date: " & TEXT('Profit & Loss'!A35,"dd mmm yyy") & ", " & 'Profit & Loss'!B35 & CHAR(10) & "Time: " & TEXT('Profit & Loss'!C35, "hh:mm AM/PM") & " - " & TEXT('Profit & Loss'!D35, "hh:mm AM/PM") & CHAR(10) & "Venue: " & 'Profit & Loss'!E35 & CHAR(10) & "Level: HB - LI" & CHAR(10) & "Cost: $" & 'Profit & Loss'!O35 & " per pax" & CHAR(10) & "Max " & 'Profit & Loss'!I35*6 & " pax," & " (" & 'Profit & Loss'!I35 & " courts)" & CHAR(10) & CHAR(10) & "RSL Ultimate shuttles provided" & CHAR(10) & CHAR(10) & "PM if interested, thank you!"," ") | B32: =IF('Profit & Loss'!A35>=TODAY(), "Date: " & TEXT('Profit & Loss'!A35,"dd mmm yyy") & ", " & 'Profit & Loss'!B35 & CHAR(10) & "Time: " & TEXT('Profit & Loss'!C35, "hh:mm AM/PM") & " - " & TEXT('Profit & Loss'!D35, "hh:mm AM/PM") & CHAR(10) & "Venue: " & 'Profit & Loss'!E35 & CHAR(10) & "Court No.: " & 'Profit & Loss'!F35 & CHAR(10) & "Level: HB - LI" & CHAR(10) & "Please transfer $" & 'Profit & Loss'!O35 & " per pax to Belle (83396501)" & CHAR(10) & CHAR(10) & IF('Profit & Loss'!I35=1, "1." & CHAR(10) & "2." & CHAR(10) & "3." & CHAR(10) & "4." & CHAR(10) & "5." & CHAR(10) & "6." & CHAR(10), IF('Profit & Loss'!I35=2, "1." & CHAR(10) & "2." & CHAR(10) & "3." & CHAR(10) & "4." & CHAR(10) & "5." & CHAR(10) & "6." & CHAR(10) & "7." & CHAR(10) & "8." & CHAR(10) & "9." & CHAR(10) & "10." & CHAR(10) & "11." & CHAR(10) & "12." & CHAR(10), IF('Profit & Loss'!I35=3, "1." & CHAR(10) & "2." & CHAR(10) & "3." & CHAR(10) & "4." & CHAR(10) & "5." & CHAR(10) & "6." & CHAR(10) & "7." & CHAR(10) & "8." & CHAR(10) & "9." & CHAR(10) & "10." & CHAR(10) & "11." & CHAR(10) & "12." & CHAR(10) & "13." & CHAR(10) & "14." & CHAR(10) & "15." & CHAR(10) & "16." & CHAR(10) & "17." & CHAR(10) & "18." & CHAR(10), " ")))," ")
A33: =IF('Profit & Loss'!A37>=TODAY(),"Looking for friendly players to join the following game: " & CHAR(10) & CHAR(10) & "Date: " & TEXT('Profit & Loss'!A37,"dd mmm yyy") & ", " & 'Profit & Loss'!B37 & CHAR(10) & "Time: " & TEXT('Profit & Loss'!C37, "hh:mm AM/PM") & " - " & TEXT('Profit & Loss'!D37, "hh:mm AM/PM") & CHAR(10) & "Venue: " & 'Profit & Loss'!E37 & CHAR(10) & "Level: HB - LI" & CHAR(10) & "Cost: $" & 'Profit & Loss'!O37 & " per pax" & CHAR(10) & "Max " & 'Profit & Loss'!I37*6 & " pax," & " (" & 'Profit & Loss'!I37 & " courts)" & CHAR(10) & CHAR(10) & "RSL Ultimate shuttles provided" & CHAR(10) & CHAR(10) & "PM if interested, thank you!"," ") | B33: =IF('Profit & Loss'!A37>=TODAY(), "Date: " & TEXT('Profit & Loss'!A37,"dd mmm yyy") & ", " & 'Profit & Loss'!B37 & CHAR(10) & "Time: " & TEXT('Profit & Loss'!C37, "hh:mm AM/PM") & " - " & TEXT('Profit & Loss'!D37, "hh:mm AM/PM") & CHAR(10) & "Venue: " & 'Profit & Loss'!E37 & CHAR(10) & "Court No.: " & 'Profit & Loss'!F37 & CHAR(10) & "Level: HB - LI" & CHAR(10) & "Please transfer $" & 'Profit & Loss'!O37 & " per pax to Belle (83396501)" & CHAR(10) & CHAR(10) & IF('Profit & Loss'!I37=1, "1." & CHAR(10) & "2." & CHAR(10) & "3." & CHAR(10) & "4." & CHAR(10) & "5." & CHAR(10) & "6." & CHAR(10), IF('Profit & Loss'!I37=2, "1." & CHAR(10) & "2." & CHAR(10) & "3." & CHAR(10) & "4." & CHAR(10) & "5." & CHAR(10) & "6." & CHAR(10) & "7." & CHAR(10) & "8." & CHAR(10) & "9." & CHAR(10) & "10." & CHAR(10) & "11." & CHAR(10) & "12." & CHAR(10), IF('Profit & Loss'!I37=3, "1." & CHAR(10) & "2." & CHAR(10) & "3." & CHAR(10) & "4." & CHAR(10) & "5." & CHAR(10) & "6." & CHAR(10) & "7." & CHAR(10) & "8." & CHAR(10) & "9." & CHAR(10) & "10." & CHAR(10) & "11." & CHAR(10) & "12." & CHAR(10) & "13." & CHAR(10) & "14." & CHAR(10) & "15." & CHAR(10) & "16." & CHAR(10) & "17." & CHAR(10) & "18." & CHAR(10), " ")))," ")
A34: =IF('Profit & Loss'!A36>=TODAY(),"Looking for friendly players to join the following game: " & CHAR(10) & CHAR(10) & "Date: " & TEXT('Profit & Loss'!A36,"dd mmm yyy") & ", " & 'Profit & Loss'!B36 & CHAR(10) & "Time: " & TEXT('Profit & Loss'!C36, "hh:mm AM/PM") & " - " & TEXT('Profit & Loss'!D36, "hh:mm AM/PM") & CHAR(10) & "Venue: " & 'Profit & Loss'!E36 & CHAR(10) & "Level: HB - LI" & CHAR(10) & "Cost: $" & 'Profit & Loss'!O36 & " per pax" & CHAR(10) & "Max " & 'Profit & Loss'!I36*6 & " pax," & " (" & 'Profit & Loss'!I36 & " courts)" & CHAR(10) & CHAR(10) & "RSL Ultimate shuttles provided" & CHAR(10) & CHAR(10) & "PM if interested, thank you!"," ") | B34: =IF('Profit & Loss'!A36>=TODAY(), "Date: " & TEXT('Profit & Loss'!A36,"dd mmm yyy") & ", " & 'Profit & Loss'!B36 & CHAR(10) & "Time: " & TEXT('Profit & Loss'!C36, "hh:mm AM/PM") & " - " & TEXT('Profit & Loss'!D36, "hh:mm AM/PM") & CHAR(10) & "Venue: " & 'Profit & Loss'!E36 & CHAR(10) & "Court No.: " & 'Profit & Loss'!F36 & CHAR(10) & "Level: HB - LI" & CHAR(10) & "Please transfer $" & 'Profit & Loss'!O36 & " per pax to Belle (83396501)" & CHAR(10) & CHAR(10) & IF('Profit & Loss'!I36=1, "1." & CHAR(10) & "2." & CHAR(10) & "3." & CHAR(10) & "4." & CHAR(10) & "5." & CHAR(10) & "6." & CHAR(10), IF('Profit & Loss'!I36=2, "1." & CHAR(10) & "2." & CHAR(10) & "3." & CHAR(10) & "4." & CHAR(10) & "5." & CHAR(10) & "6." & CHAR(10) & "7." & CHAR(10) & "8." & CHAR(10) & "9." & CHAR(10) & "10." & CHAR(10) & "11." & CHAR(10) & "12." & CHAR(10), IF('Profit & Loss'!I36=3, "1." & CHAR(10) & "2." & CHAR(10) & "3." & CHAR(10) & "4." & CHAR(10) & "5." & CHAR(10) & "6." & CHAR(10) & "7." & CHAR(10) & "8." & CHAR(10) & "9." & CHAR(10) & "10." & CHAR(10) & "11." & CHAR(10) & "12." & CHAR(10) & "13." & CHAR(10) & "14." & CHAR(10) & "15." & CHAR(10) & "16." & CHAR(10) & "17." & CHAR(10) & "18." & CHAR(10), " ")))," ")
A35: =IF('Profit & Loss'!A38>=TODAY(),"Looking for friendly players to join the following game: " & CHAR(10) & CHAR(10) & "Date: " & TEXT('Profit & Loss'!A38,"dd mmm yyy") & ", " & 'Profit & Loss'!B38 & CHAR(10) & "Time: " & TEXT('Profit & Loss'!C38, "hh:mm AM/PM") & " - " & TEXT('Profit & Loss'!D38, "hh:mm AM/PM") & CHAR(10) & "Venue: " & 'Profit & Loss'!E38 & CHAR(10) & "Level: HB - LI" & CHAR(10) & "Cost: $" & 'Profit & Loss'!O38 & " per pax" & CHAR(10) & "Max " & 'Profit & Loss'!I38*6 & " pax," & " (" & 'Profit & Loss'!I38 & " courts)" & CHAR(10) & CHAR(10) & "RSL Ultimate shuttles provided" & CHAR(10) & CHAR(10) & "PM if interested, thank you!"," ") | B35: =IF('Profit & Loss'!A38>=TODAY(), "Date: " & TEXT('Profit & Loss'!A38,"dd mmm yyy") & ", " & 'Profit & Loss'!B38 & CHAR(10) & "Time: " & TEXT('Profit & Loss'!C38, "hh:mm AM/PM") & " - " & TEXT('Profit & Loss'!D38, "hh:mm AM/PM") & CHAR(10) & "Venue: " & 'Profit & Loss'!E38 & CHAR(10) & "Court No.: " & 'Profit & Loss'!F38 & CHAR(10) & "Level: HB - LI" & CHAR(10) & "Please transfer $" & 'Profit & Loss'!O38 & " per pax to Belle (83396501)" & CHAR(10) & CHAR(10) & IF('Profit & Loss'!I38=1, "1." & CHAR(10) & "2." & CHAR(10) & "3." & CHAR(10) & "4." & CHAR(10) & "5." & CHAR(10) & "6." & CHAR(10), IF('Profit & Loss'!I38=2, "1." & CHAR(10) & "2." & CHAR(10) & "3." & CHAR(10) & "4." & CHAR(10) & "5." & CHAR(10) & "6." & CHAR(10) & "7." & CHAR(10) & "8." & CHAR(10) & "9." & CHAR(10) & "10." & CHAR(10) & "11." & CHAR(10) & "12." & CHAR(10), IF('Profit & Loss'!I38=3, "1." & CHAR(10) & "2." & CHAR(10) & "3." & CHAR(10) & "4." & CHAR(10) & "5." & CHAR(10) & "6." & CHAR(10) & "7." & CHAR(10) & "8." & CHAR(10) & "9." & CHAR(10) & "10." & CHAR(10) & "11." & CHAR(10) & "12." & CHAR(10) & "13." & CHAR(10) & "14." & CHAR(10) & "15." & CHAR(10) & "16." & CHAR(10) & "17." & CHAR(10) & "18." & CHAR(10), " ")))," ")
A36: =IF('Profit & Loss'!A39>=TODAY(),"Looking for friendly players to join the following game: " & CHAR(10) & CHAR(10) & "Date: " & TEXT('Profit & Loss'!A39,"dd mmm yyy") & ", " & 'Profit & Loss'!B39 & CHAR(10) & "Time: " & TEXT('Profit & Loss'!C39, "hh:mm AM/PM") & " - " & TEXT('Profit & Loss'!D39, "hh:mm AM/PM") & CHAR(10) & "Venue: " & 'Profit & Loss'!E39 & CHAR(10) & "Level: HB - LI" & CHAR(10) & "Cost: $" & 'Profit & Loss'!O39 & " per pax" & CHAR(10) & "Max " & 'Profit & Loss'!I39*6 & " pax," & " (" & 'Profit & Loss'!I39 & " courts)" & CHAR(10) & CHAR(10) & "RSL Ultimate shuttles provided" & CHAR(10) & CHAR(10) & "PM if interested, thank you!"," ") | B36: =IF('Profit & Loss'!A39>=TODAY(), "Date: " & TEXT('Profit & Loss'!A39,"dd mmm yyy") & ", " & 'Profit & Loss'!B39 & CHAR(10) & "Time: " & TEXT('Profit & Loss'!C39, "hh:mm AM/PM") & " - " & TEXT('Profit & Loss'!D39, "hh:mm AM/PM") & CHAR(10) & "Venue: " & 'Profit & Loss'!E39 & CHAR(10) & "Court No.: " & 'Profit & Loss'!F39 & CHAR(10) & "Level: HB - LI" & CHAR(10) & "Please transfer $" & 'Profit & Loss'!O39 & " per pax to Belle (83396501)" & CHAR(10) & CHAR(10) & IF('Profit & Loss'!I39=1, "1." & CHAR(10) & "2." & CHAR(10) & "3." & CHAR(10) & "4." & CHAR(10) & "5." & CHAR(10) & "6." & CHAR(10), IF('Profit & Loss'!I39=2, "1." & CHAR(10) & "2." & CHAR(10) & "3." & CHAR(10) & "4." & CHAR(10) & "5." & CHAR(10) & "6." & CHAR(10) & "7." & CHAR(10) & "8." & CHAR(10) & "9." & CHAR(10) & "10." & CHAR(10) & "11." & CHAR(10) & "12." & CHAR(10), IF('Profit & Loss'!I39=3, "1." & CHAR(10) & "2." & CHAR(10) & "3." & CHAR(10) & "4." & CHAR(10) & "5." & CHAR(10) & "6." & CHAR(10) & "7." & CHAR(10) & "8." & CHAR(10) & "9." & CHAR(10) & "10." & CHAR(10) & "11." & CHAR(10) & "12." & CHAR(10) & "13." & CHAR(10) & "14." & CHAR(10) & "15." & CHAR(10) & "16." & CHAR(10) & "17." & CHAR(10) & "18." & CHAR(10), " ")))," ")
A37: =IF('Profit & Loss'!A40>=TODAY(),"Looking for friendly players to join the following game: " & CHAR(10) & CHAR(10) & "Date: " & TEXT('Profit & Loss'!A40,"dd mmm yyy") & ", " & 'Profit & Loss'!B40 & CHAR(10) & "Time: " & TEXT('Profit & Loss'!C40, "hh:mm AM/PM") & " - " & TEXT('Profit & Loss'!D40, "hh:mm AM/PM") & CHAR(10) & "Venue: " & 'Profit & Loss'!E40 & CHAR(10) & "Level: HB - LI" & CHAR(10) & "Cost: $" & 'Profit & Loss'!O40 & " per pax" & CHAR(10) & "Max " & 'Profit & Loss'!I40*6 & " pax," & " (" & 'Profit & Loss'!I40 & " courts)" & CHAR(10) & CHAR(10) & "RSL Ultimate shuttles provided" & CHAR(10) & CHAR(10) & "PM if interested, thank you!"," ") | B37: =IF('Profit & Loss'!A40>=TODAY(), "Date: " & TEXT('Profit & Loss'!A40,"dd mmm yyy") & ", " & 'Profit & Loss'!B40 & CHAR(10) & "Time: " & TEXT('Profit & Loss'!C40, "hh:mm AM/PM") & " - " & TEXT('Profit & Loss'!D40, "hh:mm AM/PM") & CHAR(10) & "Venue: " & 'Profit & Loss'!E40 & CHAR(10) & "Court No.: " & 'Profit & Loss'!F40 & CHAR(10) & "Level: HB - LI" & CHAR(10) & "Please transfer $" & 'Profit & Loss'!O40 & " per pax to Belle (83396501)" & CHAR(10) & CHAR(10) & IF('Profit & Loss'!I40=1, "1." & CHAR(10) & "2." & CHAR(10) & "3." & CHAR(10) & "4." & CHAR(10) & "5." & CHAR(10) & "6." & CHAR(10), IF('Profit & Loss'!I40=2, "1." & CHAR(10) & "2." & CHAR(10) & "3." & CHAR(10) & "4." & CHAR(10) & "5." & CHAR(10) & "6." & CHAR(10) & "7." & CHAR(10) & "8." & CHAR(10) & "9." & CHAR(10) & "10." & CHAR(10) & "11." & CHAR(10) & "12." & CHAR(10), IF('Profit & Loss'!I40=3, "1." & CHAR(10) & "2." & CHAR(10) & "3." & CHAR(10) & "4." & CHAR(10) & "5." & CHAR(10) & "6." & CHAR(10) & "7." & CHAR(10) & "8." & CHAR(10) & "9." & CHAR(10) & "10." & CHAR(10) & "11." & CHAR(10) & "12." & CHAR(10) & "13." & CHAR(10) & "14." & CHAR(10) & "15." & CHAR(10) & "16." & CHAR(10) & "17." & CHAR(10) & "18." & CHAR(10), " ")))," ")
A38: =IF('Profit & Loss'!A41>=TODAY(),"Looking for friendly players to join the following game: " & CHAR(10) & CHAR(10) & "Date: " & TEXT('Profit & Loss'!A41,"dd mmm yyy") & ", " & 'Profit & Loss'!B41 & CHAR(10) & "Time: " & TEXT('Profit & Loss'!C41, "hh:mm AM/PM") & " - " & TEXT('Profit & Loss'!D41, "hh:mm AM/PM") & CHAR(10) & "Venue: " & 'Profit & Loss'!E41 & CHAR(10) & "Level: HB - LI" & CHAR(10) & "Cost: $" & 'Profit & Loss'!O41 & " per pax" & CHAR(10) & "Max " & 'Profit & Loss'!I41*6 & " pax," & " (" & 'Profit & Loss'!I41 & " courts)" & CHAR(10) & CHAR(10) & "RSL Ultimate shuttles provided" & CHAR(10) & CHAR(10) & "PM if interested, thank you!"," ") | B38: =IF('Profit & Loss'!A41>=TODAY(), "Date: " & TEXT('Profit & Loss'!A41,"dd mmm yyy") & ", " & 'Profit & Loss'!B41 & CHAR(10) & "Time: " & TEXT('Profit & Loss'!C41, "hh:mm AM/PM") & " - " & TEXT('Profit & Loss'!D41, "hh:mm AM/PM") & CHAR(10) & "Venue: " & 'Profit & Loss'!E41 & CHAR(10) & "Court No.: " & 'Profit & Loss'!F41 & CHAR(10) & "Level: HB - LI" & CHAR(10) & "Please transfer $" & 'Profit & Loss'!O41 & " per pax to Belle (83396501)" & CHAR(10) & CHAR(10) & IF('Profit & Loss'!I41=1, "1." & CHAR(10) & "2." & CHAR(10) & "3." & CHAR(10) & "4." & CHAR(10) & "5." & CHAR(10) & "6." & CHAR(10), IF('Profit & Loss'!I41=2, "1." & CHAR(10) & "2." & CHAR(10) & "3." & CHAR(10) & "4." & CHAR(10) & "5." & CHAR(10) & "6." & CHAR(10) & "7." & CHAR(10) & "8." & CHAR(10) & "9." & CHAR(10) & "10." & CHAR(10) & "11." & CHAR(10) & "12." & CHAR(10), IF('Profit & Loss'!I41=3, "1." & CHAR(10) & "2." & CHAR(10) & "3." & CHAR(10) & "4." & CHAR(10) & "5." & CHAR(10) & "6." & CHAR(10) & "7." & CHAR(10) & "8." & CHAR(10) & "9." & CHAR(10) & "10." & CHAR(10) & "11." & CHAR(10) & "12." & CHAR(10) & "13." & CHAR(10) & "14." & CHAR(10) & "15." & CHAR(10) & "16." & CHAR(10) & "17." & CHAR(10) & "18." & CHAR(10), " ")))," ")
A39: =IF('Profit & Loss'!A42>=TODAY(),"Looking for friendly players to join the following game: " & CHAR(10) & CHAR(10) & "Date: " & TEXT('Profit & Loss'!A42,"dd mmm yyy") & ", " & 'Profit & Loss'!B42 & CHAR(10) & "Time: " & TEXT('Profit & Loss'!C42, "hh:mm AM/PM") & " - " & TEXT('Profit & Loss'!D42, "hh:mm AM/PM") & CHAR(10) & "Venue: " & 'Profit & Loss'!E42 & CHAR(10) & "Level: HB - LI" & CHAR(10) & "Cost: $" & 'Profit & Loss'!O42 & " per pax" & CHAR(10) & "Max " & 'Profit & Loss'!I42*6 & " pax," & " (" & 'Profit & Loss'!I42 & " courts)" & CHAR(10) & CHAR(10) & "RSL Ultimate shuttles provided" & CHAR(10) & CHAR(10) & "PM if interested, thank you!"," ") | B39: =IF('Profit & Loss'!A42>=TODAY(), "Date: " & TEXT('Profit & Loss'!A42,"dd mmm yyy") & ", " & 'Profit & Loss'!B42 & CHAR(10) & "Time: " & TEXT('Profit & Loss'!C42, "hh:mm AM/PM") & " - " & TEXT('Profit & Loss'!D42, "hh:mm AM/PM") & CHAR(10) & "Venue: " & 'Profit & Loss'!E42 & CHAR(10) & "Court No.: " & 'Profit & Loss'!F42 & CHAR(10) & "Level: HB - LI" & CHAR(10) & "Please transfer $" & 'Profit & Loss'!O42 & " per pax to Belle (83396501)" & CHAR(10) & CHAR(10) & IF('Profit & Loss'!I42=1, "1." & CHAR(10) & "2." & CHAR(10) & "3." & CHAR(10) & "4." & CHAR(10) & "5." & CHAR(10) & "6." & CHAR(10), IF('Profit & Loss'!I42=2, "1." & CHAR(10) & "2." & CHAR(10) & "3." & CHAR(10) & "4." & CHAR(10) & "5." & CHAR(10) & "6." & CHAR(10) & "7." & CHAR(10) & "8." & CHAR(10) & "9." & CHAR(10) & "10." & CHAR(10) & "11." & CHAR(10) & "12." & CHAR(10), IF('Profit & Loss'!I42=3, "1." & CHAR(10) & "2." & CHAR(10) & "3." & CHAR(10) & "4." & CHAR(10) & "5." & CHAR(10) & "6." & CHAR(10) & "7." & CHAR(10) & "8." & CHAR(10) & "9." & CHAR(10) & "10." & CHAR(10) & "11." & CHAR(10) & "12." & CHAR(10) & "13." & CHAR(10) & "14." & CHAR(10) & "15." & CHAR(10) & "16." & CHAR(10) & "17." & CHAR(10) & "18." & CHAR(10), " ")))," ")
A40: =IF('Profit & Loss'!A43>=TODAY(),"Looking for friendly players to join the following game: " & CHAR(10) & CHAR(10) & "Date: " & TEXT('Profit & Loss'!A43,"dd mmm yyy") & ", " & 'Profit & Loss'!B43 & CHAR(10) & "Time: " & TEXT('Profit & Loss'!C43, "hh:mm AM/PM") & " - " & TEXT('Profit & Loss'!D43, "hh:mm AM/PM") & CHAR(10) & "Venue: " & 'Profit & Loss'!E43 & CHAR(10) & "Level: HB - LI" & CHAR(10) & "Cost: $" & 'Profit & Loss'!O43 & " per pax" & CHAR(10) & "Max " & 'Profit & Loss'!I43*6 & " pax," & " (" & 'Profit & Loss'!I43 & " courts)" & CHAR(10) & CHAR(10) & "RSL Ultimate shuttles provided" & CHAR(10) & CHAR(10) & "PM if interested, thank you!"," ") | B40: =IF('Profit & Loss'!A43>=TODAY(), "Date: " & TEXT('Profit & Loss'!A43,"dd mmm yyy") & ", " & 'Profit & Loss'!B43 & CHAR(10) & "Time: " & TEXT('Profit & Loss'!C43, "hh:mm AM/PM") & " - " & TEXT('Profit & Loss'!D43, "hh:mm AM/PM") & CHAR(10) & "Venue: " & 'Profit & Loss'!E43 & CHAR(10) & "Court No.: " & 'Profit & Loss'!F43 & CHAR(10) & "Level: HB - LI" & CHAR(10) & "Please transfer $" & 'Profit & Loss'!O43 & " per pax to Belle (83396501)" & CHAR(10) & CHAR(10) & IF('Profit & Loss'!I43=1, "1." & CHAR(10) & "2." & CHAR(10) & "3." & CHAR(10) & "4." & CHAR(10) & "5." & CHAR(10) & "6." & CHAR(10), IF('Profit & Loss'!I43=2, "1." & CHAR(10) & "2." & CHAR(10) & "3." & CHAR(10) & "4." & CHAR(10) & "5." & CHAR(10) & "6." & CHAR(10) & "7." & CHAR(10) & "8." & CHAR(10) & "9." & CHAR(10) & "10." & CHAR(10) & "11." & CHAR(10) & "12." & CHAR(10), IF('Profit & Loss'!I43=3, "1." & CHAR(10) & "2." & CHAR(10) & "3." & CHAR(10) & "4." & CHAR(10) & "5." & CHAR(10) & "6." & CHAR(10) & "7." & CHAR(10) & "8." & CHAR(10) & "9." & CHAR(10) & "10." & CHAR(10) & "11." & CHAR(10) & "12." & CHAR(10) & "13." & CHAR(10) & "14." & CHAR(10) & "15." & CHAR(10) & "16." & CHAR(10) & "17." & CHAR(10) & "18." & CHAR(10), " ")))," ")
A41: =IF('Profit & Loss'!A44>=TODAY(),"Looking for friendly players to join the following game: " & CHAR(10) & CHAR(10) & "Date: " & TEXT('Profit & Loss'!A44,"dd mmm yyy") & ", " & 'Profit & Loss'!B44 & CHAR(10) & "Time: " & TEXT('Profit & Loss'!C44, "hh:mm AM/PM") & " - " & TEXT('Profit & Loss'!D44, "hh:mm AM/PM") & CHAR(10) & "Venue: " & 'Profit & Loss'!E44 & CHAR(10) & "Level: HB - LI" & CHAR(10) & "Cost: $" & 'Profit & Loss'!O44 & " per pax" & CHAR(10) & "Max " & 'Profit & Loss'!I44*6 & " pax," & " (" & 'Profit & Loss'!I44 & " courts)" & CHAR(10) & CHAR(10) & "RSL Ultimate shuttles provided" & CHAR(10) & CHAR(10) & "PM if interested, thank you!"," ") | B41: =IF('Profit & Loss'!A44>=TODAY(), "Date: " & TEXT('Profit & Loss'!A44,"dd mmm yyy") & ", " & 'Profit & Loss'!B44 & CHAR(10) & "Time: " & TEXT('Profit & Loss'!C44, "hh:mm AM/PM") & " - " & TEXT('Profit & Loss'!D44, "hh:mm AM/PM") & CHAR(10) & "Venue: " & 'Profit & Loss'!E44 & CHAR(10) & "Court No.: " & 'Profit & Loss'!F44 & CHAR(10) & "Level: HB - LI" & CHAR(10) & "Please transfer $" & 'Profit & Loss'!O44 & " per pax to Belle (83396501)" & CHAR(10) & CHAR(10) & IF('Profit & Loss'!I44=1, "1." & CHAR(10) & "2." & CHAR(10) & "3." & CHAR(10) & "4." & CHAR(10) & "5." & CHAR(10) & "6." & CHAR(10), IF('Profit & Loss'!I44=2, "1." & CHAR(10) & "2." & CHAR(10) & "3." & CHAR(10) & "4." & CHAR(10) & "5." & CHAR(10) & "6." & CHAR(10) & "7." & CHAR(10) & "8." & CHAR(10) & "9." & CHAR(10) & "10." & CHAR(10) & "11." & CHAR(10) & "12." & CHAR(10), IF('Profit & Loss'!I44=3, "1." & CHAR(10) & "2." & CHAR(10) & "3." & CHAR(10) & "4." & CHAR(10) & "5." & CHAR(10) & "6." & CHAR(10) & "7." & CHAR(10) & "8." & CHAR(10) & "9." & CHAR(10) & "10." & CHAR(10) & "11." & CHAR(10) & "12." & CHAR(10) & "13." & CHAR(10) & "14." & CHAR(10) & "15." & CHAR(10) & "16." & CHAR(10) & "17." & CHAR(10) & "18." & CHAR(10), " ")))," ")
A42: =IF('Profit & Loss'!A45>=TODAY(),"Looking for friendly players to join the following game: " & CHAR(10) & CHAR(10) & "Date: " & TEXT('Profit & Loss'!A45,"dd mmm yyy") & ", " & 'Profit & Loss'!B45 & CHAR(10) & "Time: " & TEXT('Profit & Loss'!C45, "hh:mm AM/PM") & " - " & TEXT('Profit & Loss'!D45, "hh:mm AM/PM") & CHAR(10) & "Venue: " & 'Profit & Loss'!E45 & CHAR(10) & "Level: HB - LI" & CHAR(10) & "Cost: $" & 'Profit & Loss'!O45 & " per pax" & CHAR(10) & "Max " & 'Profit & Loss'!I45*6 & " pax," & " (" & 'Profit & Loss'!I45 & " courts)" & CHAR(10) & CHAR(10) & "RSL Ultimate shuttles provided" & CHAR(10) & CHAR(10) & "PM if interested, thank you!"," ") | B42: =IF('Profit & Loss'!A45>=TODAY(), "Date: " & TEXT('Profit & Loss'!A45,"dd mmm yyy") & ", " & 'Profit & Loss'!B45 & CHAR(10) & "Time: " & TEXT('Profit & Loss'!C45, "hh:mm AM/PM") & " - " & TEXT('Profit & Loss'!D45, "hh:mm AM/PM") & CHAR(10) & "Venue: " & 'Profit & Loss'!E45 & CHAR(10) & "Court No.: " & 'Profit & Loss'!F45 & CHAR(10) & "Level: HB - LI" & CHAR(10) & "Please transfer $" & 'Profit & Loss'!O45 & " per pax to Belle (83396501)" & CHAR(10) & CHAR(10) & IF('Profit & Loss'!I45=1, "1." & CHAR(10) & "2." & CHAR(10) & "3." & CHAR(10) & "4." & CHAR(10) & "5." & CHAR(10) & "6." & CHAR(10), IF('Profit & Loss'!I45=2, "1." & CHAR(10) & "2." & CHAR(10) & "3." & CHAR(10) & "4." & CHAR(10) & "5." & CHAR(10) & "6." & CHAR(10) & "7." & CHAR(10) & "8." & CHAR(10) & "9." & CHAR(10) & "10." & CHAR(10) & "11." & CHAR(10) & "12." & CHAR(10), IF('Profit & Loss'!I45=3, "1." & CHAR(10) & "2." & CHAR(10) & "3." & CHAR(10) & "4." & CHAR(10) & "5." & CHAR(10) & "6." & CHAR(10) & "7." & CHAR(10) & "8." & CHAR(10) & "9." & CHAR(10) & "10." & CHAR(10) & "11." & CHAR(10) & "12." & CHAR(10) & "13." & CHAR(10) & "14." & CHAR(10) & "15." & CHAR(10) & "16." & CHAR(10) & "17." & CHAR(10) & "18." & CHAR(10), " ")))," ")
A43: =IF('Profit & Loss'!A46>=TODAY(),"Looking for friendly players to join the following game: " & CHAR(10) & CHAR(10) & "Date: " & TEXT('Profit & Loss'!A46,"dd mmm yyy") & ", " & 'Profit & Loss'!B46 & CHAR(10) & "Time: " & TEXT('Profit & Loss'!C46, "hh:mm AM/PM") & " - " & TEXT('Profit & Loss'!D46, "hh:mm AM/PM") & CHAR(10) & "Venue: " & 'Profit & Loss'!E46 & CHAR(10) & "Level: HB - LI" & CHAR(10) & "Cost: $" & 'Profit & Loss'!O46 & " per pax" & CHAR(10) & "Max " & 'Profit & Loss'!I46*6 & " pax," & " (" & 'Profit & Loss'!I46 & " courts)" & CHAR(10) & CHAR(10) & "RSL Ultimate shuttles provided" & CHAR(10) & CHAR(10) & "PM if interested, thank you!"," ") | B43: =IF('Profit & Loss'!A46>=TODAY(), "Date: " & TEXT('Profit & Loss'!A46,"dd mmm yyy") & ", " & 'Profit & Loss'!B46 & CHAR(10) & "Time: " & TEXT('Profit & Loss'!C46, "hh:mm AM/PM") & " - " & TEXT('Profit & Loss'!D46, "hh:mm AM/PM") & CHAR(10) & "Venue: " & 'Profit & Loss'!E46 & CHAR(10) & "Court No.: " & 'Profit & Loss'!F46 & CHAR(10) & "Level: HB - LI" & CHAR(10) & "Please transfer $" & 'Profit & Loss'!O46 & " per pax to Belle (83396501)" & CHAR(10) & CHAR(10) & IF('Profit & Loss'!I46=1, "1." & CHAR(10) & "2." & CHAR(10) & "3." & CHAR(10) & "4." & CHAR(10) & "5." & CHAR(10) & "6." & CHAR(10), IF('Profit & Loss'!I46=2, "1." & CHAR(10) & "2." & CHAR(10) & "3." & CHAR(10) & "4." & CHAR(10) & "5." & CHAR(10) & "6." & CHAR(10) & "7." & CHAR(10) & "8." & CHAR(10) & "9." & CHAR(10) & "10." & CHAR(10) & "11." & CHAR(10) & "12." & CHAR(10), IF('Profit & Loss'!I46=3, "1." & CHAR(10) & "2." & CHAR(10) & "3." & CHAR(10) & "4." & CHAR(10) & "5." & CHAR(10) & "6." & CHAR(10) & "7." & CHAR(10) & "8." & CHAR(10) & "9." & CHAR(10) & "10." & CHAR(10) & "11." & CHAR(10) & "12." & CHAR(10) & "13." & CHAR(10) & "14." & CHAR(10) & "15." & CHAR(10) & "16." & CHAR(10) & "17." & CHAR(10) & "18." & CHAR(10), " ")))," ")
A44: =IF('Profit & Loss'!A47>=TODAY(),"Looking for friendly players to join the following game: " & CHAR(10) & CHAR(10) & "Date: " & TEXT('Profit & Loss'!A47,"dd mmm yyy") & ", " & 'Profit & Loss'!B47 & CHAR(10) & "Time: " & TEXT('Profit & Loss'!C47, "hh:mm AM/PM") & " - " & TEXT('Profit & Loss'!D47, "hh:mm AM/PM") & CHAR(10) & "Venue: " & 'Profit & Loss'!E47 & CHAR(10) & "Level: HB - LI" & CHAR(10) & "Cost: $" & 'Profit & Loss'!O47 & " per pax" & CHAR(10) & "Max " & 'Profit & Loss'!I47*6 & " pax," & " (" & 'Profit & Loss'!I47 & " courts)" & CHAR(10) & CHAR(10) & "RSL Ultimate shuttles provided" & CHAR(10) & CHAR(10) & "PM if interested, thank you!"," ") | B44: =IF('Profit & Loss'!A47>=TODAY(), "Date: " & TEXT('Profit & Loss'!A47,"dd mmm yyy") & ", " & 'Profit & Loss'!B47 & CHAR(10) & "Time: " & TEXT('Profit & Loss'!C47, "hh:mm AM/PM") & " - " & TEXT('Profit & Loss'!D47, "hh:mm AM/PM") & CHAR(10) & "Venue: " & 'Profit & Loss'!E47 & CHAR(10) & "Court No.: " & 'Profit & Loss'!F47 & CHAR(10) & "Level: HB - LI" & CHAR(10) & "Please transfer $" & 'Profit & Loss'!O47 & " per pax to Belle (83396501)" & CHAR(10) & CHAR(10) & IF('Profit & Loss'!I47=1, "1." & CHAR(10) & "2." & CHAR(10) & "3." & CHAR(10) & "4." & CHAR(10) & "5." & CHAR(10) & "6." & CHAR(10), IF('Profit & Loss'!I47=2, "1." & CHAR(10) & "2." & CHAR(10) & "3." & CHAR(10) & "4." & CHAR(10) & "5." & CHAR(10) & "6." & CHAR(10) & "7." & CHAR(10) & "8." & CHAR(10) & "9." & CHAR(10) & "10." & CHAR(10) & "11." & CHAR(10) & "12." & CHAR(10), IF('Profit & Loss'!I47=3, "1." & CHAR(10) & "2." & CHAR(10) & "3." & CHAR(10) & "4." & CHAR(10) & "5." & CHAR(10) & "6." & CHAR(10) & "7." & CHAR(10) & "8." & CHAR(10) & "9." & CHAR(10) & "10." & CHAR(10) & "11." & CHAR(10) & "12." & CHAR(10) & "13." & CHAR(10) & "14." & CHAR(10) & "15." & CHAR(10) & "16." & CHAR(10) & "17." & CHAR(10) & "18." & CHAR(10), " ")))," ")
A45: =IF('Profit & Loss'!A48>=TODAY(),"Looking for friendly players to join the following game: " & CHAR(10) & CHAR(10) & "Date: " & TEXT('Profit & Loss'!A48,"dd mmm yyy") & ", " & 'Profit & Loss'!B48 & CHAR(10) & "Time: " & TEXT('Profit & Loss'!C48, "hh:mm AM/PM") & " - " & TEXT('Profit & Loss'!D48, "hh:mm AM/PM") & CHAR(10) & "Venue: " & 'Profit & Loss'!E48 & CHAR(10) & "Level: HB - LI" & CHAR(10) & "Cost: $" & 'Profit & Loss'!O48 & " per pax" & CHAR(10) & "Max " & 'Profit & Loss'!I48*6 & " pax," & " (" & 'Profit & Loss'!I48 & " courts)" & CHAR(10) & CHAR(10) & "RSL Ultimate shuttles provided" & CHAR(10) & CHAR(10) & "PM if interested, thank you!"," ") | B45: =IF('Profit & Loss'!A48>=TODAY(), "Date: " & TEXT('Profit & Loss'!A48,"dd mmm yyy") & ", " & 'Profit & Loss'!B48 & CHAR(10) & "Time: " & TEXT('Profit & Loss'!C48, "hh:mm AM/PM") & " - " & TEXT('Profit & Loss'!D48, "hh:mm AM/PM") & CHAR(10) & "Venue: " & 'Profit & Loss'!E48 & CHAR(10) & "Court No.: " & 'Profit & Loss'!F48 & CHAR(10) & "Level: HB - LI" & CHAR(10) & "Please transfer $" & 'Profit & Loss'!O48 & " per pax to Belle (83396501)" & CHAR(10) & CHAR(10) & IF('Profit & Loss'!I48=1, "1." & CHAR(10) & "2." & CHAR(10) & "3." & CHAR(10) & "4." & CHAR(10) & "5." & CHAR(10) & "6." & CHAR(10), IF('Profit & Loss'!I48=2, "1." & CHAR(10) & "2." & CHAR(10) & "3." & CHAR(10) & "4." & CHAR(10) & "5." & CHAR(10) & "6." & CHAR(10) & "7." & CHAR(10) & "8." & CHAR(10) & "9." & CHAR(10) & "10." & CHAR(10) & "11." & CHAR(10) & "12." & CHAR(10), IF('Profit & Loss'!I48=3, "1." & CHAR(10) & "2." & CHAR(10) & "3." & CHAR(10) & "4." & CHAR(10) & "5." & CHAR(10) & "6." & CHAR(10) & "7." & CHAR(10) & "8." & CHAR(10) & "9." & CHAR(10) & "10." & CHAR(10) & "11." & CHAR(10) & "12." & CHAR(10) & "13." & CHAR(10) & "14." & CHAR(10) & "15." & CHAR(10) & "16." & CHAR(10) & "17." & CHAR(10) & "18." & CHAR(10), " ")))," ")
A46: =IF('Profit & Loss'!A49>=TODAY(),"Looking for friendly players to join the following game: " & CHAR(10) & CHAR(10) & "Date: " & TEXT('Profit & Loss'!A49,"dd mmm yyy") & ", " & 'Profit & Loss'!B49 & CHAR(10) & "Time: " & TEXT('Profit & Loss'!C49, "hh:mm AM/PM") & " - " & TEXT('Profit & Loss'!D49, "hh:mm AM/PM") & CHAR(10) & "Venue: " & 'Profit & Loss'!E49 & CHAR(10) & "Level: HB - LI" & CHAR(10) & "Cost: $" & 'Profit & Loss'!O49 & " per pax" & CHAR(10) & "Max " & 'Profit & Loss'!I49*6 & " pax," & " (" & 'Profit & Loss'!I49 & " courts)" & CHAR(10) & CHAR(10) & "RSL Ultimate shuttles provided" & CHAR(10) & CHAR(10) & "PM if interested, thank you!"," ") | B46: =IF('Profit & Loss'!A49>=TODAY(), "Date: " & TEXT('Profit & Loss'!A49,"dd mmm yyy") & ", " & 'Profit & Loss'!B49 & CHAR(10) & "Time: " & TEXT('Profit & Loss'!C49, "hh:mm AM/PM") & " - " & TEXT('Profit & Loss'!D49, "hh:mm AM/PM") & CHAR(10) & "Venue: " & 'Profit & Loss'!E49 & CHAR(10) & "Court No.: " & 'Profit & Loss'!F49 & CHAR(10) & "Level: HB - LI" & CHAR(10) & "Please transfer $" & 'Profit & Loss'!O49 & " per pax to Belle (83396501)" & CHAR(10) & CHAR(10) & IF('Profit & Loss'!I49=1, "1." & CHAR(10) & "2." & CHAR(10) & "3." & CHAR(10) & "4." & CHAR(10) & "5." & CHAR(10) & "6." & CHAR(10), IF('Profit & Loss'!I49=2, "1." & CHAR(10) & "2." & CHAR(10) & "3." & CHAR(10) & "4." & CHAR(10) & "5." & CHAR(10) & "6." & CHAR(10) & "7." & CHAR(10) & "8." & CHAR(10) & "9." & CHAR(10) & "10." & CHAR(10) & "11." & CHAR(10) & "12." & CHAR(10), IF('Profit & Loss'!I49=3, "1." & CHAR(10) & "2." & CHAR(10) & "3." & CHAR(10) & "4." & CHAR(10) & "5." & CHAR(10) & "6." & CHAR(10) & "7." & CHAR(10) & "8." & CHAR(10) & "9." & CHAR(10) & "10." & CHAR(10) & "11." & CHAR(10) & "12." & CHAR(10) & "13." & CHAR(10) & "14." & CHAR(10) & "15." & CHAR(10) & "16." & CHAR(10) & "17." & CHAR(10) & "18." & CHAR(10), " ")))," ")
... A53: =IF('Profit & Loss'!A56>=TODAY(),"Looking for friendly players to join the following game: " & CHAR(10) & CHAR(10) & "Date: " & TEXT('Profit & Loss'!A56,"dd mmm yyy") & ", " & 'Profit & Loss'!B56 & CHAR(10) & "Time: " & TEXT('Profit & Loss'!C56, "hh:mm AM/PM") & " - " & TEXT('Profit & Loss'!D56, "hh:mm AM/PM") & CHAR(10) & "Venue: " & 'Profit & Loss'!E56 & CHAR(10) & "Level: HB - LI" & CHAR(10) & "Cost: $" & 'Profit & Loss'!O56 & " per pax" & CHAR(10) & "Max " & 'Profit & Loss'!I56*6 & " pax," & " (" & 'Profit & Loss'!I56 & " courts)" & CHAR(10) & CHAR(10) & "RSL Ultimate shuttles provided" & CHAR(10) & CHAR(10) & "PM if interested, thank you!"," ") | B53: =IF('Profit & Loss'!A56>=TODAY(), "Date: " & TEXT('Profit & Loss'!A56,"dd mmm yyy") & ", " & 'Profit & Loss'!B56 & CHAR(10) & "Time: " & TEXT('Profit & Loss'!C56, "hh:mm AM/PM") & " - " & TEXT('Profit & Loss'!D56, "hh:mm AM/PM") & CHAR(10) & "Venue: " & 'Profit & Loss'!E56 & CHAR(10) & "Court No.: " & 'Profit & Loss'!F56 & CHAR(10) & "Level: HB - LI" & CHAR(10) & "Please transfer $" & 'Profit & Loss'!O56 & " per pax to Belle (83396501)" & CHAR(10) & CHAR(10) & IF('Profit & Loss'!I56=1, "1." & CHAR(10) & "2." & CHAR(10) & "3." & CHAR(10) & "4." & CHAR(10) & "5." & CHAR(10) & "6." & CHAR(10), IF('Profit & Loss'!I56=2, "1." & CHAR(10) & "2." & CHAR(10) & "3." & CHAR(10) & "4." & CHAR(10) & "5." & CHAR(10) & "6." & CHAR(10) & "7." & CHAR(10) & "8." & CHAR(10) & "9." & CHAR(10) & "10." & CHAR(10) & "11." & CHAR(10) & "12." & CHAR(10), IF('Profit & Loss'!I56=3, "1." & CHAR(10) & "2." & CHAR(10) & "3." & CHAR(10) & "4." & CHAR(10) & "5." & CHAR(10) & "6." & CHAR(10) & "7." & CHAR(10) & "8." & CHAR(10) & "9." & CHAR(10) & "10." & CHAR(10) & "11." & CHAR(10) & "12." & CHAR(10) & "13." & CHAR(10) & "14." & CHAR(10) & "15." & CHAR(10) & "16." & CHAR(10) & "17." & CHAR(10) & "18." & CHAR(10), " ")))," ")
A54: =IF('Profit & Loss'!A58>=TODAY(),"Looking for friendly players to join the following game: " & CHAR(10) & CHAR(10) & "Date: " & TEXT('Profit & Loss'!A58,"dd mmm yyy") & ", " & 'Profit & Loss'!B58 & CHAR(10) & "Time: " & TEXT('Profit & Loss'!C58, "hh:mm AM/PM") & " - " & TEXT('Profit & Loss'!D58, "hh:mm AM/PM") & CHAR(10) & "Venue: " & 'Profit & Loss'!E58 & CHAR(10) & "Level: HB - LI" & CHAR(10) & "Cost: $" & 'Profit & Loss'!O58 & " per pax" & CHAR(10) & "Max " & 'Profit & Loss'!I58*6 & " pax," & " (" & 'Profit & Loss'!I58 & " courts)" & CHAR(10) & CHAR(10) & "RSL Ultimate shuttles provided" & CHAR(10) & CHAR(10) & "PM if interested, thank you!"," ") | B54: =IF('Profit & Loss'!A58>=TODAY(), "Date: " & TEXT('Profit & Loss'!A58,"dd mmm yyy") & ", " & 'Profit & Loss'!B58 & CHAR(10) & "Time: " & TEXT('Profit & Loss'!C58, "hh:mm AM/PM") & " - " & TEXT('Profit & Loss'!D58, "hh:mm AM/PM") & CHAR(10) & "Venue: " & 'Profit & Loss'!E58 & CHAR(10) & "Court No.: " & 'Profit & Loss'!F58 & CHAR(10) & "Level: HB - LI" & CHAR(10) & "Please transfer $" & 'Profit & Loss'!O58 & " per pax to Belle (83396501)" & CHAR(10) & CHAR(10) & IF('Profit & Loss'!I58=1, "1." & CHAR(10) & "2." & CHAR(10) & "3." & CHAR(10) & "4." & CHAR(10) & "5." & CHAR(10) & "6." & CHAR(10), IF('Profit & Loss'!I58=2, "1." & CHAR(10) & "2." & CHAR(10) & "3." & CHAR(10) & "4." & CHAR(10) & "5." & CHAR(10) & "6." & CHAR(10) & "7." & CHAR(10) & "8." & CHAR(10) & "9." & CHAR(10) & "10." & CHAR(10) & "11." & CHAR(10) & "12." & CHAR(10), IF('Profit & Loss'!I58=3, "1." & CHAR(10) & "2." & CHAR(10) & "3." & CHAR(10) & "4." & CHAR(10) & "5." & CHAR(10) & "6." & CHAR(10) & "7." & CHAR(10) & "8." & CHAR(10) & "9." & CHAR(10) & "10." & CHAR(10) & "11." & CHAR(10) & "12." & CHAR(10) & "13." & CHAR(10) & "14." & CHAR(10) & "15." & CHAR(10) & "16." & CHAR(10) & "17." & CHAR(10) & "18." & CHAR(10), " ")))," ")
A55: =IF('Profit & Loss'!A59>=TODAY(),"Looking for friendly players to join the following game: " & CHAR(10) & CHAR(10) & "Date: " & TEXT('Profit & Loss'!A59,"dd mmm yyy") & ", " & 'Profit & Loss'!B59 & CHAR(10) & "Time: " & TEXT('Profit & Loss'!C59, "hh:mm AM/PM") & " - " & TEXT('Profit & Loss'!D59, "hh:mm AM/PM") & CHAR(10) & "Venue: " & 'Profit & Loss'!E59 & CHAR(10) & "Level: HB - LI" & CHAR(10) & "Cost: $" & 'Profit & Loss'!O59 & " per pax" & CHAR(10) & "Max " & 'Profit & Loss'!I59*6 & " pax," & " (" & 'Profit & Loss'!I59 & " courts)" & CHAR(10) & CHAR(10) & "RSL Ultimate shuttles provided" & CHAR(10) & CHAR(10) & "PM if interested, thank you!"," ") | B55: =IF('Profit & Loss'!A59>=TODAY(), "Date: " & TEXT('Profit & Loss'!A59,"dd mmm yyy") & ", " & 'Profit & Loss'!B59 & CHAR(10) & "Time: " & TEXT('Profit & Loss'!C59, "hh:mm AM/PM") & " - " & TEXT('Profit & Loss'!D59, "hh:mm AM/PM") & CHAR(10) & "Venue: " & 'Profit & Loss'!E59 & CHAR(10) & "Court No.: " & 'Profit & Loss'!F59 & CHAR(10) & "Level: HB - LI" & CHAR(10) & "Please transfer $" & 'Profit & Loss'!O59 & " per pax to Belle (83396501)" & CHAR(10) & CHAR(10) & IF('Profit & Loss'!I59=1, "1." & CHAR(10) & "2." & CHAR(10) & "3." & CHAR(10) & "4." & CHAR(10) & "5." & CHAR(10) & "6." & CHAR(10), IF('Profit & Loss'!I59=2, "1." & CHAR(10) & "2." & CHAR(10) & "3." & CHAR(10) & "4." & CHAR(10) & "5." & CHAR(10) & "6." & CHAR(10) & "7." & CHAR(10) & "8." & CHAR(10) & "9." & CHAR(10) & "10." & CHAR(10) & "11." & CHAR(10) & "12." & CHAR(10), IF('Profit & Loss'!I59=3, "1." & CHAR(10) & "2." & CHAR(10) & "3." & CHAR(10) & "4." & CHAR(10) & "5." & CHAR(10) & "6." & CHAR(10) & "7." & CHAR(10) & "8." & CHAR(10) & "9." & CHAR(10) & "10." & CHAR(10) & "11." & CHAR(10) & "12." & CHAR(10) & "13." & CHAR(10) & "14." & CHAR(10) & "15." & CHAR(10) & "16." & CHAR(10) & "17." & CHAR(10) & "18." & CHAR(10), " ")))," ")
A56: =IF('Profit & Loss'!A57>=TODAY(),"Looking for friendly players to join the following game: " & CHAR(10) & CHAR(10) & "Date: " & TEXT('Profit & Loss'!A57,"dd mmm yyy") & ", " & 'Profit & Loss'!B57 & CHAR(10) & "Time: " & TEXT('Profit & Loss'!C57, "hh:mm AM/PM") & " - " & TEXT('Profit & Loss'!D57, "hh:mm AM/PM") & CHAR(10) & "Venue: " & 'Profit & Loss'!E57 & CHAR(10) & "Level: HB - LI" & CHAR(10) & "Cost: $" & 'Profit & Loss'!O57 & " per pax" & CHAR(10) & "Max " & 'Profit & Loss'!I57*6 & " pax," & " (" & 'Profit & Loss'!I57 & " courts)" & CHAR(10) & CHAR(10) & "RSL Ultimate shuttles provided" & CHAR(10) & CHAR(10) & "PM if interested, thank you!"," ") | B56: =IF('Profit & Loss'!A57>=TODAY(), "Date: " & TEXT('Profit & Loss'!A57,"dd mmm yyy") & ", " & 'Profit & Loss'!B57 & CHAR(10) & "Time: " & TEXT('Profit & Loss'!C57, "hh:mm AM/PM") & " - " & TEXT('Profit & Loss'!D57, "hh:mm AM/PM") & CHAR(10) & "Venue: " & 'Profit & Loss'!E57 & CHAR(10) & "Court No.: " & 'Profit & Loss'!F57 & CHAR(10) & "Level: HB - LI" & CHAR(10) & "Please transfer $" & 'Profit & Loss'!O57 & " per pax to Belle (83396501)" & CHAR(10) & CHAR(10) & IF('Profit & Loss'!I57=1, "1." & CHAR(10) & "2." & CHAR(10) & "3." & CHAR(10) & "4." & CHAR(10) & "5." & CHAR(10) & "6." & CHAR(10), IF('Profit & Loss'!I57=2, "1." & CHAR(10) & "2." & CHAR(10) & "3." & CHAR(10) & "4." & CHAR(10) & "5." & CHAR(10) & "6." & CHAR(10) & "7." & CHAR(10) & "8." & CHAR(10) & "9." & CHAR(10) & "10." & CHAR(10) & "11." & CHAR(10) & "12." & CHAR(10), IF('Profit & Loss'!I57=3, "1." & CHAR(10) & "2." & CHAR(10) & "3." & CHAR(10) & "4." & CHAR(10) & "5." & CHAR(10) & "6." & CHAR(10) & "7." & CHAR(10) & "8." & CHAR(10) & "9." & CHAR(10) & "10." & CHAR(10) & "11." & CHAR(10) & "12." & CHAR(10) & "13." & CHAR(10) & "14." & CHAR(10) & "15." & CHAR(10) & "16." & CHAR(10) & "17." & CHAR(10) & "18." & CHAR(10), " ")))," ")
A57: =IF('Profit & Loss'!A60>=TODAY(),"Looking for friendly players to join the following game: " & CHAR(10) & CHAR(10) & "Date: " & TEXT('Profit & Loss'!A60,"dd mmm yyy") & ", " & 'Profit & Loss'!B60 & CHAR(10) & "Time: " & TEXT('Profit & Loss'!C60, "hh:mm AM/PM") & " - " & TEXT('Profit & Loss'!D60, "hh:mm AM/PM") & CHAR(10) & "Venue: " & 'Profit & Loss'!E60 & CHAR(10) & "Level: HB - LI" & CHAR(10) & "Cost: $" & 'Profit & Loss'!O60 & " per pax" & CHAR(10) & "Max " & 'Profit & Loss'!I60*6 & " pax," & " (" & 'Profit & Loss'!I60 & " courts)" & CHAR(10) & CHAR(10) & "RSL Ultimate shuttles provided" & CHAR(10) & CHAR(10) & "PM if interested, thank you!"," ") | B57: =IF('Profit & Loss'!A60>=TODAY(), "Date: " & TEXT('Profit & Loss'!A60,"dd mmm yyy") & ", " & 'Profit & Loss'!B60 & CHAR(10) & "Time: " & TEXT('Profit & Loss'!C60, "hh:mm AM/PM") & " - " & TEXT('Profit & Loss'!D60, "hh:mm AM/PM") & CHAR(10) & "Venue: " & 'Profit & Loss'!E60 & CHAR(10) & "Court No.: " & 'Profit & Loss'!F60 & CHAR(10) & "Level: HB - LI" & CHAR(10) & "Please transfer $" & 'Profit & Loss'!O60 & " per pax to Belle (83396501)" & CHAR(10) & CHAR(10) & IF('Profit & Loss'!I60=1, "1." & CHAR(10) & "2." & CHAR(10) & "3." & CHAR(10) & "4." & CHAR(10) & "5." & CHAR(10) & "6." & CHAR(10), IF('Profit & Loss'!I60=2, "1." & CHAR(10) & "2." & CHAR(10) & "3." & CHAR(10) & "4." & CHAR(10) & "5." & CHAR(10) & "6." & CHAR(10) & "7." & CHAR(10) & "8." & CHAR(10) & "9." & CHAR(10) & "10." & CHAR(10) & "11." & CHAR(10) & "12." & CHAR(10), IF('Profit & Loss'!I60=3, "1." & CHAR(10) & "2." & CHAR(10) & "3." & CHAR(10) & "4." & CHAR(10) & "5." & CHAR(10) & "6." & CHAR(10) & "7." & CHAR(10) & "8." & CHAR(10) & "9." & CHAR(10) & "10." & CHAR(10) & "11." & CHAR(10) & "12." & CHAR(10) & "13." & CHAR(10) & "14." & CHAR(10) & "15." & CHAR(10) & "16." & CHAR(10) & "17." & CHAR(10) & "18." & CHAR(10), " ")))," ")
A58: =IF('Profit & Loss'!A61>=TODAY(),"Looking for friendly players to join the following game: " & CHAR(10) & CHAR(10) & "Date: " & TEXT('Profit & Loss'!A61,"dd mmm yyy") & ", " & 'Profit & Loss'!B61 & CHAR(10) & "Time: " & TEXT('Profit & Loss'!C61, "hh:mm AM/PM") & " - " & TEXT('Profit & Loss'!D61, "hh:mm AM/PM") & CHAR(10) & "Venue: " & 'Profit & Loss'!E61 & CHAR(10) & "Level: HB - LI" & CHAR(10) & "Cost: $" & 'Profit & Loss'!O61 & " per pax" & CHAR(10) & "Max " & 'Profit & Loss'!I61*6 & " pax," & " (" & 'Profit & Loss'!I61 & " courts)" & CHAR(10) & CHAR(10) & "RSL Ultimate shuttles provided" & CHAR(10) & CHAR(10) & "PM if interested, thank you!"," ") | B58: =IF('Profit & Loss'!A61>=TODAY(), "Date: " & TEXT('Profit & Loss'!A61,"dd mmm yyy") & ", " & 'Profit & Loss'!B61 & CHAR(10) & "Time: " & TEXT('Profit & Loss'!C61, "hh:mm AM/PM") & " - " & TEXT('Profit & Loss'!D61, "hh:mm AM/PM") & CHAR(10) & "Venue: " & 'Profit & Loss'!E61 & CHAR(10) & "Court No.: " & 'Profit & Loss'!F61 & CHAR(10) & "Level: HB - LI" & CHAR(10) & "Please transfer $" & 'Profit & Loss'!O61 & " per pax to Belle (83396501)" & CHAR(10) & CHAR(10) & IF('Profit & Loss'!I61=1, "1." & CHAR(10) & "2." & CHAR(10) & "3." & CHAR(10) & "4." & CHAR(10) & "5." & CHAR(10) & "6." & CHAR(10), IF('Profit & Loss'!I61=2, "1." & CHAR(10) & "2." & CHAR(10) & "3." & CHAR(10) & "4." & CHAR(10) & "5." & CHAR(10) & "6." & CHAR(10) & "7." & CHAR(10) & "8." & CHAR(10) & "9." & CHAR(10) & "10." & CHAR(10) & "11." & CHAR(10) & "12." & CHAR(10), IF('Profit & Loss'!I61=3, "1." & CHAR(10) & "2." & CHAR(10) & "3." & CHAR(10) & "4." & CHAR(10) & "5." & CHAR(10) & "6." & CHAR(10) & "7." & CHAR(10) & "8." & CHAR(10) & "9." & CHAR(10) & "10." & CHAR(10) & "11." & CHAR(10) & "12." & CHAR(10) & "13." & CHAR(10) & "14." & CHAR(10) & "15." & CHAR(10) & "16." & CHAR(10) & "17." & CHAR(10) & "18." & CHAR(10), " ")))," ")
A59: =IF('Profit & Loss'!A62>=TODAY(),"Looking for friendly players to join the following game: " & CHAR(10) & CHAR(10) & "Date: " & TEXT('Profit & Loss'!A62,"dd mmm yyy") & ", " & 'Profit & Loss'!B62 & CHAR(10) & "Time: " & TEXT('Profit & Loss'!C62, "hh:mm AM/PM") & " - " & TEXT('Profit & Loss'!D62, "hh:mm AM/PM") & CHAR(10) & "Venue: " & 'Profit & Loss'!E62 & CHAR(10) & "Level: HB - LI" & CHAR(10) & "Cost: $" & 'Profit & Loss'!O62 & " per pax" & CHAR(10) & "Max " & 'Profit & Loss'!I62*6 & " pax," & " (" & 'Profit & Loss'!I62 & " courts)" & CHAR(10) & CHAR(10) & "RSL Ultimate shuttles provided" & CHAR(10) & CHAR(10) & "PM if interested, thank you!"," ") | B59: =IF('Profit & Loss'!A62>=TODAY(), "Date: " & TEXT('Profit & Loss'!A62,"dd mmm yyy") & ", " & 'Profit & Loss'!B62 & CHAR(10) & "Time: " & TEXT('Profit & Loss'!C62, "hh:mm AM/PM") & " - " & TEXT('Profit & Loss'!D62, "hh:mm AM/PM") & CHAR(10) & "Venue: " & 'Profit & Loss'!E62 & CHAR(10) & "Court No.: " & 'Profit & Loss'!F62 & CHAR(10) & "Level: HB - LI" & CHAR(10) & "Please transfer $" & 'Profit & Loss'!O62 & " per pax to Belle (83396501)" & CHAR(10) & CHAR(10) & IF('Profit & Loss'!I62=1, "1." & CHAR(10) & "2." & CHAR(10) & "3." & CHAR(10) & "4." & CHAR(10) & "5." & CHAR(10) & "6." & CHAR(10), IF('Profit & Loss'!I62=2, "1." & CHAR(10) & "2." & CHAR(10) & "3." & CHAR(10) & "4." & CHAR(10) & "5." & CHAR(10) & "6." & CHAR(10) & "7." & CHAR(10) & "8." & CHAR(10) & "9." & CHAR(10) & "10." & CHAR(10) & "11." & CHAR(10) & "12." & CHAR(10), IF('Profit & Loss'!I62=3, "1." & CHAR(10) & "2." & CHAR(10) & "3." & CHAR(10) & "4." & CHAR(10) & "5." & CHAR(10) & "6." & CHAR(10) & "7." & CHAR(10) & "8." & CHAR(10) & "9." & CHAR(10) & "10." & CHAR(10) & "11." & CHAR(10) & "12." & CHAR(10) & "13." & CHAR(10) & "14." & CHAR(10) & "15." & CHAR(10) & "16." & CHAR(10) & "17." & CHAR(10) & "18." & CHAR(10), " ")))," ")
A60: =IF('Profit & Loss'!A63>=TODAY(),"Looking for friendly players to join the following game: " & CHAR(10) & CHAR(10) & "Date: " & TEXT('Profit & Loss'!A63,"dd mmm yyy") & ", " & 'Profit & Loss'!B63 & CHAR(10) & "Time: " & TEXT('Profit & Loss'!C63, "hh:mm AM/PM") & " - " & TEXT('Profit & Loss'!D63, "hh:mm AM/PM") & CHAR(10) & "Venue: " & 'Profit & Loss'!E63 & CHAR(10) & "Level: HB - LI" & CHAR(10) & "Cost: $" & 'Profit & Loss'!O63 & " per pax" & CHAR(10) & "Max " & 'Profit & Loss'!I63*6 & " pax," & " (" & 'Profit & Loss'!I63 & " courts)" & CHAR(10) & CHAR(10) & "RSL Ultimate shuttles provided" & CHAR(10) & CHAR(10) & "PM if interested, thank you!"," ") | B60: =IF('Profit & Loss'!A63>=TODAY(), "Date: " & TEXT('Profit & Loss'!A63,"dd mmm yyy") & ", " & 'Profit & Loss'!B63 & CHAR(10) & "Time: " & TEXT('Profit & Loss'!C63, "hh:mm AM/PM") & " - " & TEXT('Profit & Loss'!D63, "hh:mm AM/PM") & CHAR(10) & "Venue: " & 'Profit & Loss'!E63 & CHAR(10) & "Court No.: " & 'Profit & Loss'!F63 & CHAR(10) & "Level: HB - LI" & CHAR(10) & "Please transfer $" & 'Profit & Loss'!O63 & " per pax to Belle (83396501)" & CHAR(10) & CHAR(10) & IF('Profit & Loss'!I63=1, "1." & CHAR(10) & "2." & CHAR(10) & "3." & CHAR(10) & "4." & CHAR(10) & "5." & CHAR(10) & "6." & CHAR(10), IF('Profit & Loss'!I63=2, "1." & CHAR(10) & "2." & CHAR(10) & "3." & CHAR(10) & "4." & CHAR(10) & "5." & CHAR(10) & "6." & CHAR(10) & "7." & CHAR(10) & "8." & CHAR(10) & "9." & CHAR(10) & "10." & CHAR(10) & "11." & CHAR(10) & "12." & CHAR(10), IF('Profit & Loss'!I63=3, "1." & CHAR(10) & "2." & CHAR(10) & "3." & CHAR(10) & "4." & CHAR(10) & "5." & CHAR(10) & "6." & CHAR(10) & "7." & CHAR(10) & "8." & CHAR(10) & "9." & CHAR(10) & "10." & CHAR(10) & "11." & CHAR(10) & "12." & CHAR(10) & "13." & CHAR(10) & "14." & CHAR(10) & "15." & CHAR(10) & "16." & CHAR(10) & "17." & CHAR(10) & "18." & CHAR(10), " ")))," ")
A61: =IF('Profit & Loss'!A64>=TODAY(),"Looking for friendly players to join the following game: " & CHAR(10) & CHAR(10) & "Date: " & TEXT('Profit & Loss'!A64,"dd mmm yyy") & ", " & 'Profit & Loss'!B64 & CHAR(10) & "Time: " & TEXT('Profit & Loss'!C64, "hh:mm AM/PM") & " - " & TEXT('Profit & Loss'!D64, "hh:mm AM/PM") & CHAR(10) & "Venue: " & 'Profit & Loss'!E64 & CHAR(10) & "Level: HB - LI" & CHAR(10) & "Cost: $" & 'Profit & Loss'!O64 & " per pax" & CHAR(10) & "Max " & 'Profit & Loss'!I64*6 & " pax," & " (" & 'Profit & Loss'!I64 & " courts)" & CHAR(10) & CHAR(10) & "RSL Ultimate shuttles provided" & CHAR(10) & CHAR(10) & "PM if interested, thank you!"," ") | B61: =IF('Profit & Loss'!A64>=TODAY(), "Date: " & TEXT('Profit & Loss'!A64,"dd mmm yyy") & ", " & 'Profit & Loss'!B64 & CHAR(10) & "Time: " & TEXT('Profit & Loss'!C64, "hh:mm AM/PM") & " - " & TEXT('Profit & Loss'!D64, "hh:mm AM/PM") & CHAR(10) & "Venue: " & 'Profit & Loss'!E64 & CHAR(10) & "Court No.: " & 'Profit & Loss'!F64 & CHAR(10) & "Level: HB - LI" & CHAR(10) & "Please transfer $" & 'Profit & Loss'!O64 & " per pax to Belle (83396501)" & CHAR(10) & CHAR(10) & IF('Profit & Loss'!I64=1, "1." & CHAR(10) & "2." & CHAR(10) & "3." & CHAR(10) & "4." & CHAR(10) & "5." & CHAR(10) & "6." & CHAR(10), IF('Profit & Loss'!I64=2, "1." & CHAR(10) & "2." & CHAR(10) & "3." & CHAR(10) & "4." & CHAR(10) & "5." & CHAR(10) & "6." & CHAR(10) & "7." & CHAR(10) & "8." & CHAR(10) & "9." & CHAR(10) & "10." & CHAR(10) & "11." & CHAR(10) & "12." & CHAR(10), IF('Profit & Loss'!I64=3, "1." & CHAR(10) & "2." & CHAR(10) & "3." & CHAR(10) & "4." & CHAR(10) & "5." & CHAR(10) & "6." & CHAR(10) & "7." & CHAR(10) & "8." & CHAR(10) & "9." & CHAR(10) & "10." & CHAR(10) & "11." & CHAR(10) & "12." & CHAR(10) & "13." & CHAR(10) & "14." & CHAR(10) & "15." & CHAR(10) & "16." & CHAR(10) & "17." & CHAR(10) & "18." & CHAR(10), " ")))," ")
A62: =IF('Profit & Loss'!A65>=TODAY(),"Looking for friendly players to join the following game: " & CHAR(10) & CHAR(10) & "Date: " & TEXT('Profit & Loss'!A65,"dd mmm yyy") & ", " & 'Profit & Loss'!B65 & CHAR(10) & "Time: " & TEXT('Profit & Loss'!C65, "hh:mm AM/PM") & " - " & TEXT('Profit & Loss'!D65, "hh:mm AM/PM") & CHAR(10) & "Venue: " & 'Profit & Loss'!E65 & CHAR(10) & "Level: HB - LI" & CHAR(10) & "Cost: $" & 'Profit & Loss'!O65 & " per pax" & CHAR(10) & "Max " & 'Profit & Loss'!I65*6 & " pax," & " (" & 'Profit & Loss'!I65 & " courts)" & CHAR(10) & CHAR(10) & "RSL Ultimate shuttles provided" & CHAR(10) & CHAR(10) & "PM if interested, thank you!"," ") | B62: =IF('Profit & Loss'!A65>=TODAY(), "Date: " & TEXT('Profit & Loss'!A65,"dd mmm yyy") & ", " & 'Profit & Loss'!B65 & CHAR(10) & "Time: " & TEXT('Profit & Loss'!C65, "hh:mm AM/PM") & " - " & TEXT('Profit & Loss'!D65, "hh:mm AM/PM") & CHAR(10) & "Venue: " & 'Profit & Loss'!E65 & CHAR(10) & "Court No.: " & 'Profit & Loss'!F65 & CHAR(10) & "Level: HB - LI" & CHAR(10) & "Please transfer $" & 'Profit & Loss'!O65 & " per pax to Belle (83396501)" & CHAR(10) & CHAR(10) & IF('Profit & Loss'!I65=1, "1." & CHAR(10) & "2." & CHAR(10) & "3." & CHAR(10) & "4." & CHAR(10) & "5." & CHAR(10) & "6." & CHAR(10), IF('Profit & Loss'!I65=2, "1." & CHAR(10) & "2." & CHAR(10) & "3." & CHAR(10) & "4." & CHAR(10) & "5." & CHAR(10) & "6." & CHAR(10) & "7." & CHAR(10) & "8." & CHAR(10) & "9." & CHAR(10) & "10." & CHAR(10) & "11." & CHAR(10) & "12." & CHAR(10), IF('Profit & Loss'!I65=3, "1." & CHAR(10) & "2." & CHAR(10) & "3." & CHAR(10) & "4." & CHAR(10) & "5." & CHAR(10) & "6." & CHAR(10) & "7." & CHAR(10) & "8." & CHAR(10) & "9." & CHAR(10) & "10." & CHAR(10) & "11." & CHAR(10) & "12." & CHAR(10) & "13." & CHAR(10) & "14." & CHAR(10) & "15." & CHAR(10) & "16." & CHAR(10) & "17." & CHAR(10) & "18." & CHAR(10), " ")))," ")
A63: =IF('Profit & Loss'!A66>=TODAY(),"Looking for friendly players to join the following game: " & CHAR(10) & CHAR(10) & "Date: " & TEXT('Profit & Loss'!A66,"dd mmm yyy") & ", " & 'Profit & Loss'!B66 & CHAR(10) & "Time: " & TEXT('Profit & Loss'!C66, "hh:mm AM/PM") & " - " & TEXT('Profit & Loss'!D66, "hh:mm AM/PM") & CHAR(10) & "Venue: " & 'Profit & Loss'!E66 & CHAR(10) & "Level: HB - LI" & CHAR(10) & "Cost: $" & 'Profit & Loss'!O66 & " per pax" & CHAR(10) & "Max " & 'Profit & Loss'!I66*6 & " pax," & " (" & 'Profit & Loss'!I66 & " courts)" & CHAR(10) & CHAR(10) & "RSL Ultimate shuttles provided" & CHAR(10) & CHAR(10) & "PM if interested, thank you!"," ") | B63: =IF('Profit & Loss'!A66>=TODAY(), "Date: " & TEXT('Profit & Loss'!A66,"dd mmm yyy") & ", " & 'Profit & Loss'!B66 & CHAR(10) & "Time: " & TEXT('Profit & Loss'!C66, "hh:mm AM/PM") & " - " & TEXT('Profit & Loss'!D66, "hh:mm AM/PM") & CHAR(10) & "Venue: " & 'Profit & Loss'!E66 & CHAR(10) & "Court No.: " & 'Profit & Loss'!F66 & CHAR(10) & "Level: HB - LI" & CHAR(10) & "Please transfer $" & 'Profit & Loss'!O66 & " per pax to Belle (83396501)" & CHAR(10) & CHAR(10) & IF('Profit & Loss'!I66=1, "1." & CHAR(10) & "2." & CHAR(10) & "3." & CHAR(10) & "4." & CHAR(10) & "5." & CHAR(10) & "6." & CHAR(10), IF('Profit & Loss'!I66=2, "1." & CHAR(10) & "2." & CHAR(10) & "3." & CHAR(10) & "4." & CHAR(10) & "5." & CHAR(10) & "6." & CHAR(10) & "7." & CHAR(10) & "8." & CHAR(10) & "9." & CHAR(10) & "10." & CHAR(10) & "11." & CHAR(10) & "12." & CHAR(10), IF('Profit & Loss'!I66=3, "1." & CHAR(10) & "2." & CHAR(10) & "3." & CHAR(10) & "4." & CHAR(10) & "5." & CHAR(10) & "6." & CHAR(10) & "7." & CHAR(10) & "8." & CHAR(10) & "9." & CHAR(10) & "10." & CHAR(10) & "11." & CHAR(10) & "12." & CHAR(10) & "13." & CHAR(10) & "14." & CHAR(10) & "15." & CHAR(10) & "16." & CHAR(10) & "17." & CHAR(10) & "18." & CHAR(10), " ")))," ")
A64: =IF('Profit & Loss'!A67>=TODAY(),"Looking for friendly players to join the following game: " & CHAR(10) & CHAR(10) & "Date: " & TEXT('Profit & Loss'!A67,"dd mmm yyy") & ", " & 'Profit & Loss'!B67 & CHAR(10) & "Time: " & TEXT('Profit & Loss'!C67, "hh:mm AM/PM") & " - " & TEXT('Profit & Loss'!D67, "hh:mm AM/PM") & CHAR(10) & "Venue: " & 'Profit & Loss'!E67 & CHAR(10) & "Level: HB - LI" & CHAR(10) & "Cost: $" & 'Profit & Loss'!O67 & " per pax" & CHAR(10) & "Max " & 'Profit & Loss'!I67*6 & " pax," & " (" & 'Profit & Loss'!I67 & " courts)" & CHAR(10) & CHAR(10) & "RSL Ultimate shuttles provided" & CHAR(10) & CHAR(10) & "PM if interested, thank you!"," ") | B64: =IF('Profit & Loss'!A67>=TODAY(), "Date: " & TEXT('Profit & Loss'!A67,"dd mmm yyy") & ", " & 'Profit & Loss'!B67 & CHAR(10) & "Time: " & TEXT('Profit & Loss'!C67, "hh:mm AM/PM") & " - " & TEXT('Profit & Loss'!D67, "hh:mm AM/PM") & CHAR(10) & "Venue: " & 'Profit & Loss'!E67 & CHAR(10) & "Court No.: " & 'Profit & Loss'!F67 & CHAR(10) & "Level: HB - LI" & CHAR(10) & "Please transfer $" & 'Profit & Loss'!O67 & " per pax to Belle (83396501)" & CHAR(10) & CHAR(10) & IF('Profit & Loss'!I67=1, "1." & CHAR(10) & "2." & CHAR(10) & "3." & CHAR(10) & "4." & CHAR(10) & "5." & CHAR(10) & "6." & CHAR(10), IF('Profit & Loss'!I67=2, "1." & CHAR(10) & "2." & CHAR(10) & "3." & CHAR(10) & "4." & CHAR(10) & "5." & CHAR(10) & "6." & CHAR(10) & "7." & CHAR(10) & "8." & CHAR(10) & "9." & CHAR(10) & "10." & CHAR(10) & "11." & CHAR(10) & "12." & CHAR(10), IF('Profit & Loss'!I67=3, "1." & CHAR(10) & "2." & CHAR(10) & "3." & CHAR(10) & "4." & CHAR(10) & "5." & CHAR(10) & "6." & CHAR(10) & "7." & CHAR(10) & "8." & CHAR(10) & "9." & CHAR(10) & "10." & CHAR(10) & "11." & CHAR(10) & "12." & CHAR(10) & "13." & CHAR(10) & "14." & CHAR(10) & "15." & CHAR(10) & "16." & CHAR(10) & "17." & CHAR(10) & "18." & CHAR(10), " ")))," ")
A65: =IF('Profit & Loss'!A68>=TODAY(),"Looking for friendly players to join the following game: " & CHAR(10) & CHAR(10) & "Date: " & TEXT('Profit & Loss'!A68,"dd mmm yyy") & ", " & 'Profit & Loss'!B68 & CHAR(10) & "Time: " & TEXT('Profit & Loss'!C68, "hh:mm AM/PM") & " - " & TEXT('Profit & Loss'!D68, "hh:mm AM/PM") & CHAR(10) & "Venue: " & 'Profit & Loss'!E68 & CHAR(10) & "Level: HB - LI" & CHAR(10) & "Cost: $" & 'Profit & Loss'!O68 & " per pax" & CHAR(10) & "Max " & 'Profit & Loss'!I68*6 & " pax," & " (" & 'Profit & Loss'!I68 & " courts)" & CHAR(10) & CHAR(10) & "RSL Ultimate shuttles provided" & CHAR(10) & CHAR(10) & "PM if interested, thank you!"," ") | B65: =IF('Profit & Loss'!A68>=TODAY(), "Date: " & TEXT('Profit & Loss'!A68,"dd mmm yyy") & ", " & 'Profit & Loss'!B68 & CHAR(10) & "Time: " & TEXT('Profit & Loss'!C68, "hh:mm AM/PM") & " - " & TEXT('Profit & Loss'!D68, "hh:mm AM/PM") & CHAR(10) & "Venue: " & 'Profit & Loss'!E68 & CHAR(10) & "Court No.: " & 'Profit & Loss'!F68 & CHAR(10) & "Level: HB - LI" & CHAR(10) & "Please transfer $" & 'Profit & Loss'!O68 & " per pax to Belle (83396501)" & CHAR(10) & CHAR(10) & IF('Profit & Loss'!I68=1, "1." & CHAR(10) & "2." & CHAR(10) & "3." & CHAR(10) & "4." & CHAR(10) & "5." & CHAR(10) & "6." & CHAR(10), IF('Profit & Loss'!I68=2, "1." & CHAR(10) & "2." & CHAR(10) & "3." & CHAR(10) & "4." & CHAR(10) & "5." & CHAR(10) & "6." & CHAR(10) & "7." & CHAR(10) & "8." & CHAR(10) & "9." & CHAR(10) & "10." & CHAR(10) & "11." & CHAR(10) & "12." & CHAR(10), IF('Profit & Loss'!I68=3, "1." & CHAR(10) & "2." & CHAR(10) & "3." & CHAR(10) & "4." & CHAR(10) & "5." & CHAR(10) & "6." & CHAR(10) & "7." & CHAR(10) & "8." & CHAR(10) & "9." & CHAR(10) & "10." & CHAR(10) & "11." & CHAR(10) & "12." & CHAR(10) & "13." & CHAR(10) & "14." & CHAR(10) & "15." & CHAR(10) & "16." & CHAR(10) & "17." & CHAR(10) & "18." & CHAR(10), " ")))," ")
A66: =IF('Profit & Loss'!A69>=TODAY(),"Looking for friendly players to join the following game: " & CHAR(10) & CHAR(10) & "Date: " & TEXT('Profit & Loss'!A69,"dd mmm yyy") & ", " & 'Profit & Loss'!B69 & CHAR(10) & "Time: " & TEXT('Profit & Loss'!C69, "hh:mm AM/PM") & " - " & TEXT('Profit & Loss'!D69, "hh:mm AM/PM") & CHAR(10) & "Venue: " & 'Profit & Loss'!E69 & CHAR(10) & "Level: HB - LI" & CHAR(10) & "Cost: $" & 'Profit & Loss'!O69 & " per pax" & CHAR(10) & "Max " & 'Profit & Loss'!I69*6 & " pax," & " (" & 'Profit & Loss'!I69 & " courts)" & CHAR(10) & CHAR(10) & "RSL Ultimate shuttles provided" & CHAR(10) & CHAR(10) & "PM if interested, thank you!"," ") | B66: =IF('Profit & Loss'!A69>=TODAY(), "Date: " & TEXT('Profit & Loss'!A69,"dd mmm yyy") & ", " & 'Profit & Loss'!B69 & CHAR(10) & "Time: " & TEXT('Profit & Loss'!C69, "hh:mm AM/PM") & " - " & TEXT('Profit & Loss'!D69, "hh:mm AM/PM") & CHAR(10) & "Venue: " & 'Profit & Loss'!E69 & CHAR(10) & "Court No.: " & 'Profit & Loss'!F69 & CHAR(10) & "Level: HB - LI" & CHAR(10) & "Please transfer $" & 'Profit & Loss'!O69 & " per pax to Belle (83396501)" & CHAR(10) & CHAR(10) & IF('Profit & Loss'!I69=1, "1." & CHAR(10) & "2." & CHAR(10) & "3." & CHAR(10) & "4." & CHAR(10) & "5." & CHAR(10) & "6." & CHAR(10), IF('Profit & Loss'!I69=2, "1." & CHAR(10) & "2." & CHAR(10) & "3." & CHAR(10) & "4." & CHAR(10) & "5." & CHAR(10) & "6." & CHAR(10) & "7." & CHAR(10) & "8." & CHAR(10) & "9." & CHAR(10) & "10." & CHAR(10) & "11." & CHAR(10) & "12." & CHAR(10), IF('Profit & Loss'!I69=3, "1." & CHAR(10) & "2." & CHAR(10) & "3." & CHAR(10) & "4." & CHAR(10) & "5." & CHAR(10) & "6." & CHAR(10) & "7." & CHAR(10) & "8." & CHAR(10) & "9." & CHAR(10) & "10." & CHAR(10) & "11." & CHAR(10) & "12." & CHAR(10) & "13." & CHAR(10) & "14." & CHAR(10) & "15." & CHAR(10) & "16." & CHAR(10) & "17." & CHAR(10) & "18." & CHAR(10), " ")))," ")
A67: =IF('Profit & Loss'!A70>=TODAY(),"Looking for friendly players to join the following game: " & CHAR(10) & CHAR(10) & "Date: " & TEXT('Profit & Loss'!A70,"dd mmm yyy") & ", " & 'Profit & Loss'!B70 & CHAR(10) & "Time: " & TEXT('Profit & Loss'!C70, "hh:mm AM/PM") & " - " & TEXT('Profit & Loss'!D70, "hh:mm AM/PM") & CHAR(10) & "Venue: " & 'Profit & Loss'!E70 & CHAR(10) & "Level: HB - LI" & CHAR(10) & "Cost: $" & 'Profit & Loss'!O70 & " per pax" & CHAR(10) & "Max " & 'Profit & Loss'!I70*6 & " pax," & " (" & 'Profit & Loss'!I70 & " courts)" & CHAR(10) & CHAR(10) & "RSL Ultimate shuttles provided" & CHAR(10) & CHAR(10) & "PM if interested, thank you!"," ") | B67: =IF('Profit & Loss'!A70>=TODAY(), "Date: " & TEXT('Profit & Loss'!A70,"dd mmm yyy") & ", " & 'Profit & Loss'!B70 & CHAR(10) & "Time: " & TEXT('Profit & Loss'!C70, "hh:mm AM/PM") & " - " & TEXT('Profit & Loss'!D70, "hh:mm AM/PM") & CHAR(10) & "Venue: " & 'Profit & Loss'!E70 & CHAR(10) & "Court No.: " & 'Profit & Loss'!F70 & CHAR(10) & "Level: HB - LI" & CHAR(10) & "Please transfer $" & 'Profit & Loss'!O70 & " per pax to Belle (83396501)" & CHAR(10) & CHAR(10) & IF('Profit & Loss'!I70=1, "1." & CHAR(10) & "2." & CHAR(10) & "3." & CHAR(10) & "4." & CHAR(10) & "5." & CHAR(10) & "6." & CHAR(10), IF('Profit & Loss'!I70=2, "1." & CHAR(10) & "2." & CHAR(10) & "3." & CHAR(10) & "4." & CHAR(10) & "5." & CHAR(10) & "6." & CHAR(10) & "7." & CHAR(10) & "8." & CHAR(10) & "9." & CHAR(10) & "10." & CHAR(10) & "11." & CHAR(10) & "12." & CHAR(10), IF('Profit & Loss'!I70=3, "1." & CHAR(10) & "2." & CHAR(10) & "3." & CHAR(10) & "4." & CHAR(10) & "5." & CHAR(10) & "6." & CHAR(10) & "7." & CHAR(10) & "8." & CHAR(10) & "9." & CHAR(10) & "10." & CHAR(10) & "11." & CHAR(10) & "12." & CHAR(10) & "13." & CHAR(10) & "14." & CHAR(10) & "15." & CHAR(10) & "16." & CHAR(10) & "17." & CHAR(10) & "18." & CHAR(10), " ")))," ")
A68: =IF('Profit & Loss'!A71>=TODAY(),"Looking for friendly players to join the following game: " & CHAR(10) & CHAR(10) & "Date: " & TEXT('Profit & Loss'!A71,"dd mmm yyy") & ", " & 'Profit & Loss'!B71 & CHAR(10) & "Time: " & TEXT('Profit & Loss'!C71, "hh:mm AM/PM") & " - " & TEXT('Profit & Loss'!D71, "hh:mm AM/PM") & CHAR(10) & "Venue: " & 'Profit & Loss'!E71 & CHAR(10) & "Level: HB - LI" & CHAR(10) & "Cost: $" & 'Profit & Loss'!O71 & " per pax" & CHAR(10) & "Max " & 'Profit & Loss'!I71*6 & " pax," & " (" & 'Profit & Loss'!I71 & " courts)" & CHAR(10) & CHAR(10) & "RSL Ultimate shuttles provided" & CHAR(10) & CHAR(10) & "PM if interested, thank you!"," ") -> Looking for friendly players to join the following game: Date: 29 May 2026, Fri Time: 07:30 pm - 09:30 pm Venue: Fengshan CC Level: HB - LI Cost: $12 per pax Max 12 pax, (2 courts) RSL Ultimate shuttles provided PM if interested, thank you! | B68: =IF('Profit & Loss'!A71>=TODAY(), "Date: " & TEXT('Profit & Loss'!A71,"dd mmm yyy") & ", " & 'Profit & Loss'!B71 & CHAR(10) & "Time: " & TEXT('Profit & Loss'!C71, "hh:mm AM/PM") & " - " & TEXT('Profit & Loss'!D71, "hh:mm AM/PM") & CHAR(10) & "Venue: " & 'Profit & Loss'!E71 & CHAR(10) & "Court No.: " & 'Profit & Loss'!F71 & CHAR(10) & "Level: HB - LI" & CHAR(10) & "Please transfer $" & 'Profit & Loss'!O71 & " per pax to Belle (83396501)" & CHAR(10) & CHAR(10) & IF('Profit & Loss'!I71=1, "1." & CHAR(10) & "2." & CHAR(10) & "3." & CHAR(10) & "4." & CHAR(10) & "5." & CHAR(10) & "6." & CHAR(10), IF('Profit & Loss'!I71=2, "1." & CHAR(10) & "2." & CHAR(10) & "3." & CHAR(10) & "4." & CHAR(10) & "5." & CHAR(10) & "6." & CHAR(10) & "7." & CHAR(10) & "8." & CHAR(10) & "9." & CHAR(10) & "10." & CHAR(10) & "11." & CHAR(10) & "12." & CHAR(10), IF('Profit & Loss'!I71=3, "1." & CHAR(10) & "2." & CHAR(10) & "3." & CHAR(10) & "4." & CHAR(10) & "5." & CHAR(10) & "6." & CHAR(10) & "7." & CHAR(10) & "8." & CHAR(10) & "9." & CHAR(10) & "10." & CHAR(10) & "11." & CHAR(10) & "12." & CHAR(10) & "13." & CHAR(10) & "14." & CHAR(10) & "15." & CHAR(10) & "16." & CHAR(10) & "17." & CHAR(10) & "18." & CHAR(10), " ")))," ") -> Date: 29 May 2026, Fri Time: 07:30 pm - 09:30 pm Venue: Fengshan CC Court No.: 1 & 2 Level: HB - LI Please transfer $12 per pax to Belle (83396501) 1. 2. 3. 4. 5. 6. 7. 8. 9. 10. 11. 12.
... A997: =IF('Profit & Loss'!A1000>=TODAY(),"Looking for friendly players to join the following game: " & CHAR(10) & CHAR(10) & "Date: " & TEXT('Profit & Loss'!A1000,"dd mmm yyy") & ", " & 'Profit & Loss'!B1000 & CHAR(10) & "Time: " & TEXT('Profit & Loss'!C1000, "hh:mm AM/PM") & " - " & TEXT('Profit & Loss'!D1000, "hh:mm AM/PM") & CHAR(10) & "Venue: " & 'Profit & Loss'!E1000 & CHAR(10) & "Level: HB - LI" & CHAR(10) & "Cost: $" & 'Profit & Loss'!O1000 & " per pax" & CHAR(10) & "Max " & 'Profit & Loss'!I1000*6 & " pax," & " (" & 'Profit & Loss'!I1000 & " courts)" & CHAR(10) & CHAR(10) & "RSL Ultimate shuttles provided" & CHAR(10) & CHAR(10) & "PM if interested, thank you!"," ") | B997: =IF('Profit & Loss'!A1000>=TODAY(), "Date: " & TEXT('Profit & Loss'!A1000,"dd mmm yyy") & ", " & 'Profit & Loss'!B1000 & CHAR(10) & "Time: " & TEXT('Profit & Loss'!C1000, "hh:mm AM/PM") & " - " & TEXT('Profit & Loss'!D1000, "hh:mm AM/PM") & CHAR(10) & "Venue: " & 'Profit & Loss'!E1000 & CHAR(10) & "Court No.: " & 'Profit & Loss'!F1000 & CHAR(10) & "Level: HB - LI" & CHAR(10) & "Please transfer $" & 'Profit & Loss'!O1000 & " per pax to Belle (83396501)" & CHAR(10) & CHAR(10) & IF('Profit & Loss'!I1000=1, "1." & CHAR(10) & "2." & CHAR(10) & "3." & CHAR(10) & "4." & CHAR(10) & "5." & CHAR(10) & "6." & CHAR(10), IF('Profit & Loss'!I1000=2, "1." & CHAR(10) & "2." & CHAR(10) & "3." & CHAR(10) & "4." & CHAR(10) & "5." & CHAR(10) & "6." & CHAR(10) & "7." & CHAR(10) & "8." & CHAR(10) & "9." & CHAR(10) & "10." & CHAR(10) & "11." & CHAR(10) & "12." & CHAR(10), IF('Profit & Loss'!I1000=3, "1." & CHAR(10) & "2." & CHAR(10) & "3." & CHAR(10) & "4." & CHAR(10) & "5." & CHAR(10) & "6." & CHAR(10) & "7." & CHAR(10) & "8." & CHAR(10) & "9." & CHAR(10) & "10." & CHAR(10) & "11." & CHAR(10) & "12." & CHAR(10) & "13." & CHAR(10) & "14." & CHAR(10) & "15." & CHAR(10) & "16." & CHAR(10) & "17." & CHAR(10) & "18." & CHAR(10), " ")))," ")

Sheet Profit & Loss
A1: Profit & Loss
A2: Starting Balance as at 23 Oct 2025 | C2: 61.71
G4: Court Details | K4: Shuttle Details | O4: Pub Details | R4: Members Details | U4: Per Game | Y4: Overall Funds
A5: Date | B5: Day | C5: Start Time | D5: End Time | E5: Location | F5: Court No. | G5: Court Cost ($ per hour) | H5: No. of Hours | I5: No. of Courts | J5: Total Court Cost ($) | K5: Shuttle Type | L5: No. of Shuttles Used | M5: Shuttle Cost ($ per shuttle) | N5: Total Shuttle Cost ($) | O5: Amount Paid by Pubs ($ per pax) | P5: No. of Pubs | Q5: Total Paid by Pubs ($) | R5: Amount Paid by Members ($) per pax) | S5: No. of Members | T5: Total Paid by Members ($) | U5: Total No. of Players | V5: Total Amount Received ($) | W5: Total Cost (Court + Shuttle $) | X5: Profit/Loss ($ per game) | Y5: Actual Earnings | Z5: In Flow (Pubs Joined) | AA5: Out Flow (Court Cost) | AB5: Out Flow (Shuttle Purchase) | AC5: Fund Balance Balance
A6: 45955 | B6: Sat | C6: 0.72916667 | D6: 0.8125 | E6: Siglap CC | G6: =VLOOKUP(E6,'Court List'!$A:$C,2,0) -> 18 | H6: 2 | I6: 2 | J6: =G6*(H6*I6) -> 72 | K6: Ultimate (Sep 2025) | L6: =SUM('Shuttle Count - Ultimate (Sep 2'!C6:F6) -> 11 | M6: =VLOOKUP(K6,'Shuttle Purchase'!A:C,3,0) -> 3.4458333 | N6: =L6*M6 -> 37.904167 | O6: =VLOOKUP(E6,'Court List'!$A:$C,3,0) -> 14 | P6: =COUNTIF('Pub List'!$C6:$T6,"<>") -> 8 | Q6: =O6*P6 -> 112 | S6: =COUNTIF('Member List'!$C6:$J6,"<>") -> 4 | U6: =P6+S6 -> 12 | V6: =Q6 -> 112 | W6: =J6+N6 -> 109.90417 | X6: =V6-W6 -> 2.0958333 | Y6: =C2+X6 -> 63.805833 | Z6: =V6 -> 112 | AA6: =-J6 -> -72 | AC6: =C2+Z6+AA6+AB6 -> 101.71
A7: 45960 | B7: Thurs | C7: 0.8125 | D7: 0.89583333 | E7: Kaki Bukit CC | G7: =VLOOKUP(E7,'Court List'!$A:$C,2,0) -> 6 | H7: 2 | I7: 1 | J7: =G7*(H7*I7) -> 12 | K7: Ultimate (Sep 2025) | L7: =SUM('Shuttle Count - Ultimate (Sep 2'!C7:F7) -> 5 | M7: =VLOOKUP(K7,'Shuttle Purchase'!A:C,3,0) -> 3.4458333 | N7: =L7*M7 -> 17.229167 | O7: =VLOOKUP(E7,'Court List'!$A:$C,3,0) -> 12 | P7: =COUNTIF('Pub List'!$C7:$T7,"<>") -> 3 | Q7: =O7*P7 -> 36 | S7: =COUNTIF('Member List'!$C7:$J7,"<>") -> 3 | U7: =P7+S7 -> 6 | V7: =Q7 -> 36 | W7: =J7+N7 -> 29.229167 | X7: =V7-W7 -> 6.7708333 | Y7: =Y6+X7 -> 70.576667 | Z7: =V7 -> 36 | AA7: =-J7 -> -12 | AC7: =AC6+Z7+AA7+AB7 -> 125.71
A8: 45963 | B8: Sun | C8: 0.8125 | D8: 0.89583333 | E8: Fengshan CC | G8: =VLOOKUP(E8,'Court List'!$A:$C,2,0) -> 8 | H8: 2 | I8: 2 | J8: =G8*(H8*I8) -> 32 | K8: Ultimate (Sep 2025) | L8: =SUM('Shuttle Count - Ultimate (Sep 2'!C8:F8) -> 11 | M8: =VLOOKUP(K8,'Shuttle Purchase'!A:C,3,0) -> 3.4458333 | N8: =L8*M8 -> 37.904167 | O8: =VLOOKUP(E8,'Court List'!$A:$C,3,0) -> 12 | P8: =COUNTIF('Pub List'!$C8:$T8,"<>") -> 7 | Q8: =O8*P8 -> 84 | S8: =COUNTIF('Member List'!$C8:$J8,"<>") -> 5 | U8: =P8+S8 -> 12 | V8: =Q8 -> 84 | W8: =J8+N8 -> 69.904167 | X8: =V8-W8 -> 14.095833 | Y8: =Y7+X8 -> 84.6725 | Z8: =V8 -> 84 | AA8: =-J8 -> -32 | AC8: =AC7+Z8+AA8+AB8 -> 177.71
A9: 45965 | B9: Tues | C9: 0.8125 | D9: 0.89583333 | E9: Kaki Bukit CC | G9: =VLOOKUP(E9,'Court List'!$A:$C,2,0) -> 6 | H9: 2 | I9: 1 | J9: =G9*(H9*I9) -> 12 | K9: Ultimate (Sep 2025) | L9: =SUM('Shuttle Count - Ultimate (Sep 2'!C9:F9) -> 3 | M9: =VLOOKUP(K9,'Shuttle Purchase'!A:C,3,0) -> 3.4458333 | N9: =L9*M9 -> 10.3375 | O9: =VLOOKUP(E9,'Court List'!$A:$C,3,0) -> 12 | P9: =COUNTIF('Pub List'!$C9:$T9,"<>") -> 1 | Q9: =O9*P9 -> 12 | S9: =COUNTIF('Member List'!$C9:$J9,"<>") -> 5 | U9: =P9+S9 -> 6 | V9: =Q9 -> 12 | W9: =J9+N9 -> 22.3375 | X9: =V9-W9 -> -10.3375 | Y9: =Y8+X9 -> 74.335 | Z9: =V9 -> 12 | AA9: =-J9 -> -12 | AC9: =AC8+Z9+AA9+AB9 -> 177.71
A10: 45969 | B10: Sat | C10: 0.72916667 | D10: 0.8125 | E10: Siglap CC | G10: =VLOOKUP(E10,'Court List'!$A:$C,2,0) -> 18 | H10: 2 | I10: 2 | J10: =G10*(H10*I10) -> 72 | K10: Ultimate (Sep 2025) | L10: =SUM('Shuttle Count - Ultimate (Sep 2'!C10:F10) -> 9 | M10: =VLOOKUP(K10,'Shuttle Purchase'!A:C,3,0) -> 3.4458333 | N10: =L10*M10 -> 31.0125 | O10: =VLOOKUP(E10,'Court List'!$A:$C,3,0) -> 14 | P10: =COUNTIF('Pub List'!$C10:$T10,"<>") -> 7 | Q10: =O10*P10 -> 98 | S10: =COUNTIF('Member List'!$C10:$J10,"<>") -> 5 | U10: =P10+S10 -> 12 | V10: =Q10 -> 98 | W10: =J10+N10 -> 103.0125 | X10: =V10-W10 -> -5.0125 | Y10: =Y9+X10 -> 69.3225 | Z10: =V10 -> 98 | AA10: =-J10 -> -72 | AC10: =AC9+Z10+AA10+AB10 -> 203.71
A11: 45973 | B11: Wed | C11: 0.8125 | D11: 0.89583333 | E11: Macpherson CC | G11: =VLOOKUP(E11,'Court List'!$A:$C,2,0) -> 6 | H11: 2 | I11: 1 | J11: =G11*(H11*I11) -> 12 | K11: Ultimate (Sep 2025) | L11: =SUM('Shuttle Count - Ultimate (Sep 2'!C11:F11) -> 5 | M11: =VLOOKUP(K11,'Shuttle Purchase'!A:C,3,0) -> 3.4458333 | N11: =L11*M11 -> 17.229167 | O11: =VLOOKUP(E11,'Court List'!$A:$C,3,0) -> 12 | P11: =COUNTIF('Pub List'!$C11:$T11,"<>") -> 3 | Q11: =O11*P11 -> 36 | S11: =COUNTIF('Member List'!$C11:$J11,"<>") -> 3 | U11: =P11+S11 -> 6 | V11: =Q11 -> 36 | W11: =J11+N11 -> 29.229167 | X11: =V11-W11 -> 6.7708333 | Y11: =Y10+X11 -> 76.093333 | Z11: =V11 -> 36 | AA11: =-J11 -> -12 | AC11: =AC10+Z11+AA11+AB11 -> 227.71
A12: 45977 | B12: Sun | C12: 0.72916667 | D12: 0.8125 | E12: Siglap CC | G12: =VLOOKUP(E12,'Court List'!$A:$C,2,0) -> 18 | H12: 2 | I12: 3 | J12: =G12*(H12*I12) -> 108 | K12: Ultimate (Sep 2025) | L12: =SUM('Shuttle Count - Ultimate (Sep 2'!C12:F12) -> 18 | M12: =VLOOKUP(K12,'Shuttle Purchase'!A:C,3,0) -> 3.4458333 | N12: =L12*M12 -> 62.025 | O12: =VLOOKUP(E12,'Court List'!$A:$C,3,0) -> 14 | P12: =COUNTIF('Pub List'!$C12:$T12,"<>") -> 11 | Q12: =O12*P12 -> 154 | S12: =COUNTIF('Member List'!$C12:$J12,"<>") -> 7 | U12: =P12+S12 -> 18 | V12: =Q12 -> 154 | W12: =J12+N12 -> 170.025 | X12: =V12-W12 -> -16.025 | Y12: =Y11+X12 -> 60.068333 | Z12: =V12 -> 154 | AA12: =-J12 -> -108 | AC12: =AC11+Z12+AA12+AB12 -> 273.71
A13: 45978 | B13: Mon | C13: 0.8125 | D13: 0.89583333 | E13: Macpherson CC | G13: =VLOOKUP(E13,'Court List'!$A:$C,2,0) -> 6 | H13: 2 | I13: 1 | J13: =G13*(H13*I13) -> 12 | K13: Ultimate (Sep 2025) | L13: =SUM('Shuttle Count - Ultimate (Sep 2'!C13:F13) -> 5 | M13: =VLOOKUP(K13,'Shuttle Purchase'!A:C,3,0) -> 3.4458333 | N13: =L13*M13 -> 17.229167 | O13: =VLOOKUP(E13,'Court List'!$A:$C,3,0) -> 12 | P13: =COUNTIF('Pub List'!$C13:$T13,"<>") -> 4 | Q13: =O13*P13 -> 48 | S13: =COUNTIF('Member List'!$C13:$J13,"<>") -> 2 | U13: =P13+S13 -> 6 | V13: =Q13 -> 48 | W13: =J13+N13 -> 29.229167 | X13: =V13-W13 -> 18.770833 | Y13: =Y12+X13 -> 78.839167 | Z13: =V13 -> 48 | AA13: =-J13 -> -12 | AC13: =AC12+Z13+AA13+AB13 -> 309.71
A14: 45979 | B14: Tues | C14: 0.83333333 | D14: 0.91666667 | E14: Expo Weekday | G14: =VLOOKUP(E14,'Court List'!$A:$C,2,0) -> 26 | H14: 2 | I14: 2 | J14: =G14*(H14*I14) -> 104 | K14: Ultimate (Sep 2025) | L14: =SUM('Shuttle Count - Ultimate (Sep 2'!C14:F14) -> 10 | M14: =VLOOKUP(K14,'Shuttle Purchase'!A:C,3,0) -> 3.4458333 | N14: =L14*M14 -> 34.458333 | O14: =VLOOKUP(E14,'Court List'!$A:$C,3,0) -> 16 | P14: =COUNTIF('Pub List'!$C14:$T14,"<>") -> 10 | Q14: =O14*P14 -> 160 | S14: =COUNTIF('Member List'!$C14:$J14,"<>") -> 2 | U14: =P14+S14 -> 12 | V14: =Q14 -> 160 | W14: =J14+N14 -> 138.45833 | X14: =V14-W14 -> 21.541667 | Y14: =Y13+X14 -> 100.38083 | Z14: =V14 -> 160 | AA14: =-J14 -> -104 | AC14: =AC13+Z14+AA14+AB14 -> 365.71
A15: 45981 | B15: Thurs | C15: 0.8125 | D15: 0.89583333 | E15: Changi Simei CC | G15: =VLOOKUP(E15,'Court List'!$A:$C,2,0) -> 6 | H15: 2 | I15: 1 | J15: =G15*(H15*I15) -> 12 | K15: Ultimate (Sep 2025) | L15: =SUM('Shuttle Count - Ultimate (Sep 2'!C15:F15) -> 4 | M15: =VLOOKUP(K15,'Shuttle Purchase'!A:C,3,0) -> 3.4458333 | N15: =L15*M15 -> 13.783333 | O15: =VLOOKUP(E15,'Court List'!$A:$C,3,0) -> 12 | P15: =COUNTIF('Pub List'!$C15:$T15,"<>") -> 1 | Q15: =O15*P15 -> 12 | S15: =COUNTIF('Member List'!$C15:$J15,"<>") -> 5 | U15: =P15+S15 -> 6 | V15: =Q15 -> 12 | W15: =J15+N15 -> 25.783333 | X15: =V15-W15 -> -13.783333 | Y15: =Y14+X15 -> 86.5975 | Z15: =V15 -> 12 | AA15: =-J15 -> -12 | AC15: =AC14+Z15+AA15+AB15 -> 365.71
A16: 45984 | B16: Sun | C16: 0.72916667 | D16: 0.8125 | E16: Siglap CC | G16: =VLOOKUP(E16,'Court List'!$A:$C,2,0) -> 18 | H16: 2 | I16: 2 | J16: =G16*(H16*I16) -> 72 | K16: Ultimate (Sep 2025) | L16: =SUM('Shuttle Count - Ultimate (Sep 2'!C16:F16) -> 11 | M16: =VLOOKUP(K16,'Shuttle Purchase'!A:C,3,0) -> 3.4458333 | N16: =L16*M16 -> 37.904167 | O16: =VLOOKUP(E16,'Court List'!$A:$C,3,0) -> 14 | P16: =COUNTIF('Pub List'!$C16:$T16,"<>") -> 8 | Q16: =O16*P16 -> 112 | S16: =COUNTIF('Member List'!$C16:$J16,"<>") -> 4 | U16: =P16+S16 -> 12 | V16: =Q16 -> 112 | W16: =J16+N16 -> 109.90417 | X16: =V16-W16 -> 2.0958333 | Y16: =Y15+X16 -> 88.693333 | Z16: =V16 -> 112 | AA16: =-J16 -> -72 | AC16: =AC15+Z16+AA16+AB16 -> 405.71
A17: 45987 | B17: Wed | C17: 0.83333333 | D17: 0.91666667 | E17: Pasir Ris SH | G17: =VLOOKUP(E17,'Court List'!$A:$C,2,0) -> 7.4 | H17: 2 | I17: 2 | J17: =G17*(H17*I17) -> 29.6 | K17: Ultimate (Sep 2025) | L17: =SUM('Shuttle Count - Ultimate (Sep 2'!C17:F17) -> 12 | M17: =VLOOKUP(K17,'Shuttle Purchase'!A:C,3,0) -> 3.4458333 | N17: =L17*M17 -> 41.35 | O17: =VLOOKUP(E17,'Court List'!$A:$C,3,0) -> 12 | P17: =COUNTIF('Pub List'!$C17:$T17,"<>") -> 7 | Q17: =O17*P17 -> 84 | S17: =COUNTIF('Member List'!$C17:$J17,"<>") -> 5 | U17: =P17+S17 -> 12 | V17: =Q17 -> 84 | W17: =J17+N17 -> 70.95 | X17: =V17-W17 -> 13.05 | Y17: =Y16+X17 -> 101.74333 | Z17: =V17 -> 84 | AA17: =-J17 -> -29.6 | AC17: =AC16+Z17+AA17+AB17 -> 460.11
A18: 45988 | B18: Thurs | C18: 0.8125 | D18: 0.89583333 | E18: Changi Simei CC | G18: =VLOOKUP(E18,'Court List'!$A:$C,2,0) -> 6 | H18: 2 | I18: 1 | J18: =G18*(H18*I18) -> 12 | K18: Ultimate (Sep 2025) | L18: =SUM('Shuttle Count - Ultimate (Sep 2'!C18:F18) -> 3 | M18: =VLOOKUP(K18,'Shuttle Purchase'!A:C,3,0) -> 3.4458333 | N18: =L18*M18 -> 10.3375 | O18: =VLOOKUP(E18,'Court List'!$A:$C,3,0) -> 12 | P18: =COUNTIF('Pub List'!$C18:$T18,"<>") -> 1 | Q18: =O18*P18 -> 12 | S18: =COUNTIF('Member List'!$C18:$J18,"<>") -> 5 | U18: =P18+S18 -> 6 | V18: =Q18 -> 12 | W18: =J18+N18 -> 22.3375 | X18: =V18-W18 -> -10.3375 | Y18: =Y17+X18 -> 91.405833 | Z18: =V18 -> 12 | AA18: =-J18 -> -12 | AC18: =AC17+Z18+AA18+AB18 -> 460.11
A19: 45991 | B19: Sun | C19: 0.72916667 | D19: 0.8125 | E19: Siglap CC | G19: =VLOOKUP(E19,'Court List'!$A:$C,2,0) -> 18 | H19: 2 | I19: 2 | J19: =G19*(H19*I19) -> 72 | K19: Ultimate (Sep 2025) | L19: =SUM('Shuttle Count - Ultimate (Sep 2'!C19:F19) -> 10 | M19: =VLOOKUP(K19,'Shuttle Purchase'!A:C,3,0) -> 3.4458333 | N19: =L19*M19 -> 34.458333 | O19: =VLOOKUP(E19,'Court List'!$A:$C,3,0) -> 14 | P19: =COUNTIF('Pub List'!$C19:$T19,"<>") -> 10 | Q19: =O19*P19 -> 140 | S19: =COUNTIF('Member List'!$C19:$J19,"<>") -> 2 | U19: =P19+S19 -> 12 | V19: =Q19 -> 140 | W19: =J19+N19 -> 106.45833 | X19: =V19-W19 -> 33.541667 | Y19: =Y18+X19 -> 124.9475 | Z19: =V19 -> 140 | AA19: =-J19 -> -72 | AB19: =-('Shuttle Purchase'!C8*('Shuttle Purchase'!E8+'Shuttle Purchase'!G8)+'Shuttle Purchase'!C9*('Shuttle Purchase'!E9+'Shuttle Purchase'!G9)) -> -844.55 | AC19: =AC18+Z19+AA19+AB19 -> -316.44
A20: 45998 | B20: Sun | C20: 0.72916667 | D20: 0.8125 | E20: Siglap CC | F20: 1, 2 & 3 | G20: =VLOOKUP(E20,'Court List'!$A:$C,2,0) -> 18 | H20: 2 | I20: 3 | J20: =G20*(H20*I20) -> 108 | K20: Ultimate (Sep 2025) | L20: =SUM('Shuttle Count - Ultimate (Sep 2'!C20:F20) -> 19 | M20: =VLOOKUP(K20,'Shuttle Purchase'!A:C,3,0) -> 3.4458333 | N20: =L20*M20 -> 65.470833 | O20: =VLOOKUP(E20,'Court List'!$A:$C,3,0) -> 14 | P20: =COUNTIF('Pub List'!$C20:$T20,"<>") -> 13 | Q20: =O20*P20 -> 182 | S20: =COUNTIF('Member List'!$C20:$J20,"<>") -> 5 | U20: =P20+S20 -> 18 | V20: =Q20 -> 182 | W20: =J20+N20 -> 173.47083 | X20: =V20-W20 -> 8.5291667 | Y20: =Y19+X20 -> 133.47667 | Z20: =V20 -> 182 | AA20: =-J20 -> -108 | AC20: =AC19+Z20+AA20+AB20 -> -242.44
A21: 45999 | B21: Mon | C21: 0.8125 | D21: 0.89583333 | E21: Macpherson CC | F21: 1A | G21: =VLOOKUP(E21,'Court List'!$A:$C,2,0) -> 6 | H21: 2 | I21: 1 | J21: =G21*(H21*I21) -> 12 | K21: Ultimate (Sep 2025) | L21: =SUM('Shuttle Count - Ultimate (Sep 2'!C21:F21) -> 5 | M21: =VLOOKUP(K21,'Shuttle Purchase'!A:C,3,0) -> 3.4458333 | N21: =L21*M21 -> 17.229167 | O21: =VLOOKUP(E21,'Court List'!$A:$C,3,0) -> 12 | P21: =COUNTIF('Pub List'!$C21:$T21,"<>") -> 2 | Q21: =O21*P21 -> 24 | S21: =COUNTIF('Member List'!$C21:$J21,"<>") -> 4 | U21: =P21+S21 -> 6 | V21: =Q21 -> 24 | W21: =J21+N21 -> 29.229167 | X21: =V21-W21 -> -5.2291667 | Y21: =Y20+X21 -> 128.2475 | Z21: =V21 -> 24 | AA21: =-J21 -> -12 | AC21: =AC20+Z21+AA21+AB21 -> -230.44
A22: 46001 | B22: Wed | C22: 0.8125 | D22: 0.89583333 | E22: Macpherson CC | F22: 1B | G22: =VLOOKUP(E22,'Court List'!$A:$C,2,0) -> 6 | H22: 2 | I22: 1 | J22: =G22*(H22*I22) -> 12 | K22: Ultimate (Sep 2025) | L22: =SUM('Shuttle Count - Ultimate (Sep 2'!C22:F22) -> 5 | M22: =VLOOKUP(K22,'Shuttle Purchase'!A:C,3,0) -> 3.4458333 | N22: =L22*M22 -> 17.229167 | O22: =VLOOKUP(E22,'Court List'!$A:$C,3,0) -> 12 | P22: =COUNTIF('Pub List'!$C22:$T22,"<>") -> 4 | Q22: =O22*P22 -> 48 | S22: =COUNTIF('Member List'!$C22:$J22,"<>") -> 2 | U22: =P22+S22 -> 6 | V22: =Q22 -> 48 | W22: =J22+N22 -> 29.229167 | X22: =V22-W22 -> 18.770833 | Y22: =Y21+X22 -> 147.01833 | Z22: =V22 -> 48 | AA22: =-J22 -> -12 | AC22: =AC21+Z22+AA22+AB22 -> -194.44
A23: 46004 | B23: Sat | C23: 0.77083333 | D23: 0.85416667 | E23: Fengshan CC | F23: 1 & 2 | G23: =VLOOKUP(E23,'Court List'!$A:$C,2,0) -> 8 | H23: 2 | I23: 2 | J23: =G23*(H23*I23) -> 32 | K23: Ultimate (Sep 2025) | L23: =SUM('Shuttle Count - Ultimate (Sep 2'!C23:F23) -> 12 | M23: =VLOOKUP(K23,'Shuttle Purchase'!A:C,3,0) -> 3.4458333 | N23: =L23*M23 -> 41.35 | O23: =VLOOKUP(E23,'Court List'!$A:$C,3,0) -> 12 | P23: =COUNTIF('Pub List'!$C23:$T23,"<>") -> 7 | Q23: =O23*P23 -> 84 | S23: =COUNTIF('Member List'!$C23:$J23,"<>") -> 5 | U23: =P23+S23 -> 12 | V23: =Q23 -> 84 | W23: =J23+N23 -> 73.35 | X23: =V23-W23 -> 10.65 | Y23: =Y22+X23 -> 157.66833 | Z23: =V23 -> 84 | AA23: =-J23 -> -32 | AC23: =AC22+Z23+AA23+AB23 -> -142.44
A24: 46006 | B24: Mon | C24: 0.8125 | D24: 0.89583333 | E24: Macpherson CC | F24: 1A | G24: =VLOOKUP(E24,'Court List'!$A:$C,2,0) -> 6 | H24: 2 | I24: 1 | J24: =G24*(H24*I24) -> 12 | K24: Ultimate (Sep 2025) | L24: =SUM('Shuttle Count - Ultimate (Sep 2'!C24:F24) -> 5 | M24: =VLOOKUP(K24,'Shuttle Purchase'!A:C,3,0) -> 3.4458333 | N24: =L24*M24 -> 17.229167 | O24: =VLOOKUP(E24,'Court List'!$A:$C,3,0) -> 12 | P24: =COUNTIF('Pub List'!$C24:$T24,"<>") -> 3 | Q24: =O24*P24 -> 36 | S24: =COUNTIF('Member List'!$C24:$J24,"<>") -> 3 | U24: =P24+S24 -> 6 | V24: =Q24 -> 36 | W24: =J24+N24 -> 29.229167 | X24: =V24-W24 -> 6.7708333 | Y24: =Y23+X24 -> 164.43917 | Z24: =V24 -> 36 | AA24: =-J24 -> -12 | AC24: =AC23+Z24+AA24+AB24 -> -118.44
A25: 46011 | B25: Sat | C25: 0.72916667 | D25: 0.8125 | E25: Siglap CC | F25: 1 & 2 | G25: =VLOOKUP(E25,'Court List'!$A:$C,2,0) -> 18 | H25: 2 | I25: 2 | J25: =G25*(H25*I25) -> 72 | K25: Ultimate (Sep 2025) | L25: =SUM('Shuttle Count - Ultimate (Sep 2'!C25:F25) -> 10 | M25: =VLOOKUP(K25,'Shuttle Purchase'!A:C,3,0) -> 3.4458333 | N25: =L25*M25 -> 34.458333 | O25: =VLOOKUP(E25,'Court List'!$A:$C,3,0) -> 14 | P25: =COUNTIF('Pub List'!$C25:$T25,"<>") -> 7 | Q25: =O25*P25 -> 98 | S25: =COUNTIF('Member List'!$C25:$J25,"<>") -> 4 | U25: =P25+S25 -> 11 | V25: =Q25 -> 98 | W25: =J25+N25 -> 106.45833 | X25: =V25-W25 -> -8.4583333 | Y25: =Y24+X25 -> 155.98083 | Z25: =V25 -> 98 | AA25: =-J25 -> -72 | AC25: =AC24+Z25+AA25+AB25 -> -92.44
A26: 46017 | B26: Fri | C26: 0.8125 | D26: 0.89583333 | E26: Siglap CC | F26: 1 & 3 | G26: =VLOOKUP(E26,'Court List'!$A:$C,2,0) -> 18 | H26: 2 | I26: 2 | J26: =G26*(H26*I26) -> 72 | K26: Ultimate (Sep 2025) | L26: =SUM('Shuttle Count - Ultimate (Sep 2'!C26:F26) -> 11 | M26: =VLOOKUP(K26,'Shuttle Purchase'!A:C,3,0) -> 3.4458333 | N26: =L26*M26 -> 37.904167 | O26: =VLOOKUP(E26,'Court List'!$A:$C,3,0) -> 14 | P26: =COUNTIF('Pub List'!$C26:$T26,"<>") -> 8 | Q26: =O26*P26 -> 112 | S26: =COUNTIF('Member List'!$C26:$J26,"<>") -> 4 | U26: =P26+S26 -> 12 | V26: =Q26 -> 112 | W26: =J26+N26 -> 109.90417 | X26: =V26-W26 -> 2.0958333 | Y26: =Y25+X26 -> 158.07667 | Z26: =V26 -> 112 | AA26: =-J26 -> -72 | AC26: =AC25+Z26+AA26+AB26 -> -52.44
A27: 46019 | B27: Sun | C27: 0.8125 | D27: 0.89583333 | E27: Macpherson CC | F27: 1A | G27: =VLOOKUP(E27,'Court List'!$A:$C,2,0) -> 6 | H27: 2 | I27: 1 | J27: =G27*(H27*I27) -> 12 | K27: Ultimate (Sep 2025) | L27: =SUM('Shuttle Count - Ultimate (Sep 2'!C27:F27) -> 6 | M27: =VLOOKUP(K27,'Shuttle Purchase'!A:C,3,0) -> 3.4458333 | N27: =L27*M27 -> 20.675 | O27: =VLOOKUP(E27,'Court List'!$A:$C,3,0) -> 12 | P27: =COUNTIF('Pub List'!$C27:$T27,"<>") -> 3 | Q27: =O27*P27 -> 36 | S27: =COUNTIF('Member List'!$C27:$J27,"<>") -> 3 | U27: =P27+S27 -> 6 | V27: =Q27 -> 36 | W27: =J27+N27 -> 32.675 | X27: =V27-W27 -> 3.325 | Y27: =Y26+X27 -> 161.40167 | Z27: =V27 -> 36 | AA27: =-J27 -> -12 | AC27: =AC26+Z27+AA27+AB27 -> -28.44
A28: 46020 | B28: Mon | C28: 0.8125 | D28: 0.89583333 | E28: Macpherson CC | F28: 1A | G28: =VLOOKUP(E28,'Court List'!$A:$C,2,0) -> 6 | H28: 2 | I28: 1 | J28: =G28*(H28*I28) -> 12 | K28: Ultimate (Sep 2025) | L28: =SUM('Shuttle Count - Ultimate (Sep 2'!C28:F28) -> 5 | M28: =VLOOKUP(K28,'Shuttle Purchase'!A:C,3,0) -> 3.4458333 | N28: =L28*M28 -> 17.229167 | O28: =VLOOKUP(E28,'Court List'!$A:$C,3,0) -> 12 | P28: =COUNTIF('Pub List'!$C28:$T28,"<>") -> 2 | Q28: =O28*P28 -> 24 | S28: =COUNTIF('Member List'!$C28:$J28,"<>") -> 4 | U28: =P28+S28 -> 6 | V28: =Q28 -> 24 | W28: =J28+N28 -> 29.229167 | X28: =V28-W28 -> -5.2291667 | Y28: =Y27+X28 -> 156.1725 | Z28: =V28 -> 24 | AA28: =-J28 -> -12 | AC28: =AC27+Z28+AA28+AB28 -> -16.44
A29: 46024 | B29: Fri | C29: 0.8125 | D29: 0.89583333 | E29: Fengshan CC | F29: 1 & 2 | G29: =VLOOKUP(E29,'Court List'!$A:$C,2,0) -> 8 | H29: 2 | I29: 2 | J29: =G29*(H29*I29) -> 32 | K29: Ultimate (Sep 2025) | L29: =SUM('Shuttle Count - Ultimate (Sep 2'!C29:F29) -> 15 | M29: =VLOOKUP(K29,'Shuttle Purchase'!A:C,3,0) -> 3.4458333 | N29: =L29*M29 -> 51.6875 | O29: =VLOOKUP(E29,'Court List'!$A:$C,3,0) -> 12 | P29: =COUNTIF('Pub List'!$C29:$T29,"<>") -> 8 | Q29: =O29*P29 -> 96 | S29: =COUNTIF('Member List'!$C29:$J29,"<>") -> 4 | U29: =P29+S29 -> 12 | V29: =Q29 -> 96 | W29: =J29+N29 -> 83.6875 | X29: =V29-W29 -> 12.3125 | Y29: =Y28+X29 -> 168.485 | Z29: =V29 -> 96 | AA29: =-J29 -> -32 | AC29: =AC28+Z29+AA29+AB29 -> 47.56
A30: 46026 | B30: Sun | C30: 0.8125 | D30: 0.89583333 | E30: Siglap CC | F30: 3 | G30: =VLOOKUP(E30,'Court List'!$A:$C,2,0) -> 18 | H30: 2 | I30: 1 | J30: =G30*(H30*I30) -> 36 | K30: Supreme (Nov 2025) | L30: =SUM('Shuttle Count - Supreme (Nov 20'!C30:D30) -> 4 | M30: =VLOOKUP(K30,'Shuttle Purchase'!A:C,3,0) -> 3.4664167 | N30: =L30*M30 -> 13.865667 | O30: =VLOOKUP(E30,'Court List'!$A:$C,3,0) -> 14 | P30: =COUNTIF('Pub List'!$C30:$T30,"<>") -> 3 | Q30: =O30*P30 -> 42 | S30: =COUNTIF('Member List'!$C30:$J30,"<>") -> 3 | U30: =P30+S30 -> 6 | V30: =Q30 -> 42 | W30: =J30+N30 -> 49.865667 | X30: =V30-W30 -> -7.8656667 | Y30: =Y29+X30 -> 160.61933 | Z30: =V30 -> 42 | AA30: =-J30 -> -36 | AC30: =AC29+Z30+AA30+AB30 -> 53.56
A31: 46033 | B31: Sun | C31: 0.72916667 | D31: 0.8125 | E31: Siglap CC | F31: 1, 2 & 3 | G31: =VLOOKUP(E31,'Court List'!$A:$C,2,0) -> 18 | H31: 2 | I31: 3 | J31: =G31*(H31*I31) -> 108 | K31: Ultimate (Sep 2025) Supreme (Nov 2025) | L31: 10 7 | M31: $3.45 $3.47 | N31: ='Shuttle Count - Ultimate (Sep 2'!D31*'Shuttle Purchase'!C5+'Shuttle Count - Supreme (Nov 20'!D31*'Shuttle Purchase'!C9 -> 58.72325 | O31: =VLOOKUP(E31,'Court List'!$A:$C,3,0) -> 14 | P31: =COUNTIF('Pub List'!$C31:$T31,"<>") -> 14 | Q31: =O31*P31 -> 196 | S31: =COUNTIF('Member List'!$C31:$J31,"<>") -> 4 | U31: =P31+S31 -> 18 | V31: =Q31 -> 196 | W31: =J31+N31 -> 166.72325 | X31: =V31-W31 -> 29.27675 | Y31: =Y30+X31 -> 189.89608 | Z31: =V31 -> 196 | AA31: =-J31 -> -108 | AB31: -40 | AC31: =AC30+Z31+AA31+AB31 -> 101.56
A32: 46036 | B32: Wed | C32: 0.83333333 | D32: 0.91666667 | E32: Pasir Ris SH | F32: 2 -> 3 | G32: =VLOOKUP(E32,'Court List'!$A:$C,2,0) -> 7.4 | H32: 2 | I32: 1 | J32: =G32*(H32*I32) -> 14.8 | K32: Ultimate (Sep 2025) Supreme (Nov 2025) | L32: 2 1 | M32: $3.45 $3.47 | N32: ='Shuttle Count - Ultimate (Sep 2'!D32*'Shuttle Purchase'!C5+'Shuttle Count - Supreme (Nov 20'!D32*'Shuttle Purchase'!C9 -> 10.358083 | O32: =VLOOKUP(E32,'Court List'!$A:$C,3,0) -> 12 | P32: =COUNTIF('Pub List'!$C32:$T32,"<>") -> 2 | Q32: =O32*P32 -> 24 | S32: =COUNTIF('Member List'!$C32:$J32,"<>") -> 4 | U32: =P32+S32 -> 6 | V32: =Q32 -> 24 | W32: =J32+N32 -> 25.158083 | X32: =V32-W32 -> -1.1580833 | Y32: =Y31+X32 -> 188.738 | Z32: =V32 -> 24 | AA32: =-J32 -> -14.8 | AC32: =AC31+Z32+AA32+AB32 -> 110.76
A33: 46038 | B33: Fri | C33: 0.8125 | D33: 0.89583333 | E33: Fengshan CC | F33: 1 | G33: =VLOOKUP(E33,'Court List'!$A:$C,2,0) -> 8 | H33: 2 | I33: 1 | J33: =G33*(H33*I33) -> 16 | K33: Ultimate (Sep 2025) | L33: =SUM('Shuttle Count - Ultimate (Sep 2'!C33:F33) -> 7 | M33: =VLOOKUP(K33,'Shuttle Purchase'!A:C,3,0) -> 3.4458333 | N33: =L33*M33 -> 24.120833 | O33: =VLOOKUP(E33,'Court List'!$A:$C,3,0) -> 12 | P33: =COUNTIF('Pub List'!$C33:$T33,"<>") -> 4 | Q33: =O33*P33 -> 48 | S33: =COUNTIF('Member List'!$C33:$J33,"<>") -> 2 | U33: =P33+S33 -> 6 | V33: =Q33 -> 48 | W33: =J33+N33 -> 40.120833 | X33: =V33-W33 -> 7.8791667 | Y33: =Y32+X33 -> 196.61717 | Z33: =V33 -> 48 | AA33: =-J33 -> -16 | AC33: =AC32+Z33+AA33+AB33 -> 142.76
A34: 46040 | B34: Sun | C34: 0.72916667 | D34: 0.8125 | E34: Fengshan CC | F34: 1 & 2 | G34: =VLOOKUP(E34,'Court List'!$A:$C,2,0) -> 8 | H34: 2 | I34: 2 | J34: =G34*(H34*I34) -> 32 | K34: Ultimate (Sep 2025) | L34: =SUM('Shuttle Count - Ultimate (Sep 2'!C34:F34) -> 13 | M34: =VLOOKUP(K34,'Shuttle Purchase'!A:C,3,0) -> 3.4458333 | N34: =L34*M34 -> 44.795833 | O34: =VLOOKUP(E34,'Court List'!$A:$C,3,0) -> 12 | P34: =COUNTIF('Pub List'!$C34:$T34,"<>") -> 8 | Q34: =O34*P34 -> 96 | S34: =COUNTIF('Member List'!$C34:$J34,"<>") -> 4 | U34: =P34+S34 -> 12 | V34: =Q34 -> 96 | W34: =J34+N34 -> 76.795833 | X34: =V34-W34 -> 19.204167 | Y34: =Y33+X34 -> 215.82133 | Z34: =V34 -> 96 | AA34: =-J34 -> -32 | AC34: =AC33+Z34+AA34+AB34 -> 206.76
A35: 46044 | B35: Thurs | C35: 0.83333333 | D35: 0.91666667 | E35: Pasir Ris SH | F35: 1 | G35: =VLOOKUP(E35,'Court List'!$A:$C,2,0) -> 7.4 | H35: 2 | I35: 1 | J35: =G35*(H35*I35) -> 14.8 | K35: Ultimate (Sep 2025) | L35: =SUM('Shuttle Count - Ultimate (Sep 2'!C35:F35) -> 5 | M35: =VLOOKUP(K35,'Shuttle Purchase'!A:C,3,0) -> 3.4458333 | N35: =L35*M35 -> 17.229167 | O35: =VLOOKUP(E35,'Court List'!$A:$C,3,0) -> 12 | P35: =COUNTIF('Pub List'!$C35:$T35,"<>") -> 2 | Q35: =O35*P35 -> 24 | S35: =COUNTIF('Member List'!$C35:$J35,"<>") -> 4 | U35: =P35+S35 -> 6 | V35: =Q35 -> 24 | W35: =J35+N35 -> 32.029167 | X35: =V35-W35 -> -8.0291667 | Y35: =Y34+X35 -> 207.79217 | Z35: =V35 -> 24 | AA35: =-J35 -> -14.8 | AC35: =AC34+Z35+AA35+AB35 -> 215.96
A36: 46047 | B36: Sun | C36: 0.6875 | D36: 0.77083333 | E36: Changi Simei CC | F36: 2 | G36: =VLOOKUP(E36,'Court List'!$A:$C,2,0) -> 6 | H36: 2 | I36: 1 | J36: =G36*(H36*I36) -> 12 | K36: Ultimate (Sep 2025) | L36: =SUM('Shuttle Count - Ultimate (Sep 2'!C36:F36) -> 4 | M36: =VLOOKUP(K36,'Shuttle Purchase'!A:C,3,0) -> 3.4458333 | N36: =L36*M36 -> 13.783333 | O36: =VLOOKUP(E36,'Court List'!$A:$C,3,0) -> 12 | P36: =COUNTIF('Pub List'!$C36:$T36,"<>") -> 3 | Q36: =O36*P36 -> 36 | S36: =COUNTIF('Member List'!$C36:$J36,"<>") -> 3 | U36: =P36+S36 -> 6 | V36: =Q36 -> 36 | W36: =J36+N36 -> 25.783333 | X36: =V36-W36 -> 10.216667 | Y36: =Y35+X36 -> 218.00883 | Z36: =V36 -> 36 | AA36: =-J36 -> -12 | AC36: =AC35+Z36+AA36+AB36 -> 239.96
A37: 46050 | B37: Wed | C37: 0.83333333 | D37: 0.91666667 | E37: Pasir Ris SH | F37: 2 | G37: =VLOOKUP(E37,'Court List'!$A:$C,2,0) -> 7.4 | H37: 2 | I37: 1 | J37: =G37*(H37*I37) -> 14.8 | K37: Ultimate (Sep 2025) | L37: =SUM('Shuttle Count - Ultimate (Sep 2'!C37:F37) -> 5 | M37: =VLOOKUP(K37,'Shuttle Purchase'!A:C,3,0) -> 3.4458333 | N37: =L37*M37 -> 17.229167 | O37: =VLOOKUP(E37,'Court List'!$A:$C,3,0) -> 12 | P37: =COUNTIF('Pub List'!$C37:$T37,"<>") -> 2 | Q37: =O37*P37 -> 24 | S37: =COUNTIF('Member List'!$C37:$J37,"<>") -> 4 | U37: =P37+S37 -> 6 | V37: =Q37 -> 24 | W37: =J37+N37 -> 32.029167 | X37: =V37-W37 -> -8.0291667 | Y37: =Y36+X37 -> 209.97967 | Z37: =V37 -> 24 | AA37: =-J37 -> -14.8 | AC37: =AC36+Z37+AA37+AB37 -> 249.16
A38: 46054 | B38: Sun | C38: 0.8125 | D38: 0.89583333 | E38: Changi Simei CC | F38: 1 & 2 | G38: =VLOOKUP(E38,'Court List'!$A:$C,2,0) -> 6 | H38: 2 | I38: 2 | J38: =G38*(H38*I38) -> 24 | K38: Ultimate (Sep 2025) | L38: =SUM('Shuttle Count - Ultimate (Sep 2'!C38:F38) -> 10 | M38: =VLOOKUP(K38,'Shuttle Purchase'!A:C,3,0) -> 3.4458333 | N38: =L38*M38 -> 34.458333 | O38: =VLOOKUP(E38,'Court List'!$A:$C,3,0) -> 12 | P38: =COUNTIF('Pub List'!$C38:$T38,"<>") -> 7 | Q38: =O38*P38 -> 84 | S38: =COUNTIF('Member List'!$C38:$J38,"<>") -> 5 | U38: =P38+S38 -> 12 | V38: =Q38 -> 84 | W38: =J38+N38 -> 58.458333 | X38: =V38-W38 -> 25.541667 | Y38: =Y37+X38 -> 235.52133 | Z38: =V38 -> 84 | AA38: =-J38 -> -24 | AC38: =AC37+Z38+AA38+AB38 -> 309.16
A39: 46060 | B39: Sat | C39: 0.8125 | D39: 0.89583333 | E39: Fengshan CC | F39: 1 | G39: =VLOOKUP(E39,'Court List'!$A:$C,2,0) -> 8 | H39: 2 | I39: 1 | J39: =G39*(H39*I39) -> 16 | K39: Ultimate (Sep 2025) | L39: =SUM('Shuttle Count - Ultimate (Sep 2'!C39:F39) -> 4 | M39: =VLOOKUP(K39,'Shuttle Purchase'!A:C,3,0) -> 3.4458333 | N39: =L39*M39 -> 13.783333 | O39: =VLOOKUP(E39,'Court List'!$A:$C,3,0) -> 12 | P39: =COUNTIF('Pub List'!$C39:$T39,"<>") -> 2 | Q39: =O39*P39 -> 24 | S39: =COUNTIF('Member List'!$C39:$J39,"<>") -> 4 | U39: =P39+S39 -> 6 | V39: =Q39 -> 24 | W39: =J39+N39 -> 29.783333 | X39: =V39-W39 -> -5.7833333 | Y39: =Y38+X39 -> 229.738 | Z39: =V39 -> 24 | AA39: =-J39 -> -16 | AC39: =AC38+Z39+AA39+AB39 -> 317.16
A40: 46061 | B40: Sun | C40: 0.8125 | D40: 0.89583333 | E40: Fengshan CC | F40: 1 & 2 | G40: =VLOOKUP(E40,'Court List'!$A:$C,2,0) -> 8 | H40: 2 | I40: 2 | J40: =G40*(H40*I40) -> 32 | K40: Supreme (Nov 2025) | L40: =SUM('Shuttle Count - Supreme (Nov 20'!C40:D40) -> 10 | M40: =VLOOKUP(K40,'Shuttle Purchase'!A:C,3,0) -> 3.4664167 | N40: =L40*M40 -> 34.664167 | O40: =VLOOKUP(E40,'Court List'!$A:$C,3,0) -> 12 | P40: =COUNTIF('Pub List'!$C40:$T40,"<>") -> 8 | Q40: =O40*P40 -> 96 | S40: =COUNTIF('Member List'!$C40:$J40,"<>") -> 4 | U40: =P40+S40 -> 12 | V40: =Q40 -> 96 | W40: =J40+N40 -> 66.664167 | X40: =V40-W40 -> 29.335833 | Y40: =Y39+X40 -> 259.07383 | Z40: =V40 -> 96 | AA40: =-J40 -> -32 | AC40: =AC39+Z40+AA40+AB40 -> 381.16
A41: 46065 | B41: Thurs | C41: 0.8125 | D41: 0.89583333 | E41: Changi Simei CC | F41: 2 | G41: =VLOOKUP(E41,'Court List'!$A:$C,2,0) -> 6 | H41: 2 | I41: 1 | J41: =G41*(H41*I41) -> 12 | K41: Supreme (Nov 2025) Supreme (Joo Ching) | L41: 2 1 | M41: $3.47 $3.33 | N41: ='Shuttle Purchase'!C9*'Shuttle Count - Supreme (Nov 20'!D41+'Shuttle Purchase'!C10*1 -> 10.266167 | O41: =VLOOKUP(E41,'Court List'!$A:$C,3,0) -> 12 | P41: =COUNTIF('Pub List'!$C41:$T41,"<>") -> 2 | Q41: =O41*P41 -> 24 | S41: =COUNTIF('Member List'!$C41:$J41,"<>") -> 4 | U41: =P41+S41 -> 6 | V41: =Q41 -> 24 | W41: =J41+N41 -> 22.266167 | X41: =V41-W41 -> 1.7338333 | Y41: =Y40+X41 -> 260.80767 | Z41: =V41 -> 24 | AA41: =-J41 -> -12 | AC41: =AC40+Z41+AA41+AB41 -> 393.16
A42: 46066 | B42: Fri | C42: 0.8125 | D42: 0.89583333 | E42: Changi Simei CC | F42: 1 & 2 | G42: =VLOOKUP(E42,'Court List'!$A:$C,2,0) -> 6 | H42: 2 | I42: 2 | J42: =G42*(H42*I42) -> 24 | K42: Ultimate (Sep 2025) Supreme (Joo Ching) | L42: 2 11 | M42: $3.45 $3.33 | N42: ='Shuttle Count - Ultimate (Sep 2'!C42*'Shuttle Purchase'!C5+'Shuttle Purchase'!C10*11 -> 43.558333 | O42: =VLOOKUP(E42,'Court List'!$A:$C,3,0) -> 12 | P42: =COUNTIF('Pub List'!$C42:$T42,"<>") -> 8 | Q42: =O42*P42 -> 96 | S42: =COUNTIF('Member List'!$C42:$J42,"<>") -> 4 | U42: =P42+S42 -> 12 | V42: =Q42 -> 96 | W42: =J42+N42 -> 67.558333 | X42: =V42-W42 -> 28.441667 | Y42: =Y41+X42 -> 289.24933 | Z42: =V42 -> 96 | AA42: =-J42 -> -24 | AC42: =AC41+Z42+AA42+AB42 -> 465.16
A43: 46067 | B43: Sat | C43: 0.72916667 | D43: 0.8125 | E43: Siglap CC | F43: 1 & 2 | G43: =VLOOKUP(E43,'Court List'!$A:$C,2,0) -> 18 | H43: 2 | I43: 2 | J43: =G43*(H43*I43) -> 72 | K43: Supreme (Nov 2025) | L43: =SUM('Shuttle Count - Supreme (Nov 20'!C43:D43) -> 15 | M43: =VLOOKUP(K43,'Shuttle Purchase'!A:C,3,0) -> 3.4664167 | N43: =L43*M43 -> 51.99625 | O43: =VLOOKUP(E43,'Court List'!$A:$C,3,0) -> 14 | P43: =COUNTIF('Pub List'!$C43:$T43,"<>") -> 8 | Q43: =O43*P43 -> 112 | S43: =COUNTIF('Member List'!$C43:$J43,"<>") -> 4 | U43: =P43+S43 -> 12 | V43: =Q43 -> 112 | W43: =J43+N43 -> 123.99625 | X43: =V43-W43 -> -11.99625 | Y43: =Y42+X43 -> 277.25308 | Z43: =V43 -> 112 | AA43: =-J43 -> -72 | AC43: =AC42+Z43+AA43+AB43 -> 505.16
A44: 46076 | B44: Mon | C44: 0.8125 | D44: 0.89583333 | E44: Macpherson CC | F44: 1A | G44: =VLOOKUP(E44,'Court List'!$A:$C,2,0) -> 6 | H44: 2 | I44: 1 | J44: =G44*(H44*I44) -> 12 | K44: Supreme (Nov 2025) | L44: =SUM('Shuttle Count - Supreme (Nov 20'!C44:D44) -> 5 | M44: =VLOOKUP(K44,'Shuttle Purchase'!A:C,3,0) -> 3.4664167 | N44: =L44*M44 -> 17.332083 | O44: =VLOOKUP(E44,'Court List'!$A:$C,3,0) -> 12 | P44: =COUNTIF('Pub List'!$C44:$T44,"<>") -> 2 | Q44: =O44*P44 -> 24 | S44: =COUNTIF('Member List'!$C44:$J44,"<>") -> 4 | U44: =P44+S44 -> 6 | V44: =Q44 -> 24 | W44: =J44+N44 -> 29.332083 | X44: =V44-W44 -> -5.3320833 | Y44: =Y43+X44 -> 271.921 | Z44: =V44 -> 24 | AA44: =-J44 -> -12 | AC44: =AC43+Z44+AA44+AB44 -> 517.16
A45: 46077 | B45: Tues | C45: 0.8125 | D45: 0.89583333 | E45: Changi Simei CC | F45: 1 & 2 | G45: =VLOOKUP(E45,'Court List'!$A:$C,2,0) -> 6 | H45: 2 | I45: 2 | J45: =G45*(H45*I45) -> 24 | K45: Supreme (Nov 2025) | L45: =SUM('Shuttle Count - Supreme (Nov 20'!C45:D45) -> 13 | M45: =VLOOKUP(K45,'Shuttle Purchase'!A:C,3,0) -> 3.4664167 | N45: =L45*M45 -> 45.063417 | O45: =VLOOKUP(E45,'Court List'!$A:$C,3,0) -> 12 | P45: =COUNTIF('Pub List'!$C45:$T45,"<>") -> 8 | Q45: =O45*P45 -> 96 | S45: =COUNTIF('Member List'!$C45:$J45,"<>") -> 4 | U45: =P45+S45 -> 12 | V45: =Q45 -> 96 | W45: =J45+N45 -> 69.063417 | X45: =V45-W45 -> 26.936583 | Y45: =Y44+X45 -> 298.85758 | Z45: =V45 -> 96 | AA45: =-J45 -> -24 | AC45: =AC44+Z45+AA45+AB45 -> 589.16
A46: 46082 | B46: Sun | C46: 0.72916667 | D46: 0.8125 | E46: Fengshan CC | F46: 1 & 2 | G46: =VLOOKUP(E46,'Court List'!$A:$C,2,0) -> 8 | H46: 2 | I46: 2 | J46: =G46*(H46*I46) -> 32 | K46: Supreme (Nov 2025) | L46: =SUM('Shuttle Count - Supreme (Nov 20'!C46:D46) -> 12 | M46: =VLOOKUP(K46,'Shuttle Purchase'!A:C,3,0) -> 3.4664167 | N46: =L46*M46 -> 41.597 | O46: =VLOOKUP(E46,'Court List'!$A:$C,3,0) -> 12 | P46: =COUNTIF('Pub List'!$C46:$T46,"<>") -> 8 | Q46: =O46*P46 -> 96 | S46: =COUNTIF('Member List'!$C46:$J46,"<>") -> 4 | U46: =P46+S46 -> 12 | V46: =Q46 -> 96 | W46: =J46+N46 -> 73.597 | X46: =V46-W46 -> 22.403 | Y46: =Y45+X46 -> 321.26058 | Z46: =V46 -> 96 | AA46: =-J46 -> -32 | AC46: =AC45+Z46+AA46+AB46 -> 653.16
A47: 46084 | B47: Tues | C47: 0.8125 | D47: 0.89583333 | E47: Fengshan CC | F47: 1 | G47: =VLOOKUP(E47,'Court List'!$A:$C,2,0) -> 8 | H47: 2 | I47: 1 | J47: =G47*(H47*I47) -> 16 | K47: Supreme (Nov 2025) | L47: =SUM('Shuttle Count - Supreme (Nov 20'!C47:D47) -> 5 | M47: =VLOOKUP(K47,'Shuttle Purchase'!A:C,3,0) -> 3.4664167 | N47: =L47*M47 -> 17.332083 | O47: =VLOOKUP(E47,'Court List'!$A:$C,3,0) -> 12 | P47: =COUNTIF('Pub List'!$C47:$T47,"<>") -> 2 | Q47: =O47*P47 -> 24 | S47: =COUNTIF('Member List'!$C47:$J47,"<>") -> 4 | U47: =P47+S47 -> 6 | V47: =Q47 -> 24 | W47: =J47+N47 -> 33.332083 | X47: =V47-W47 -> -9.3320833 | Y47: =Y46+X47 -> 311.9285 | Z47: =V47 -> 24 | AA47: =-J47 -> -16 | AC47: =AC46+Z47+AA47+AB47 -> 661.16
A48: 46087 | B48: Fri | C48: 0.8125 | D48: 0.89583333 | E48: Fengshan CC | F48: 1 | G48: =VLOOKUP(E48,'Court List'!$A:$C,2,0) -> 8 | H48: 2 | I48: 1 | J48: =G48*(H48*I48) -> 16 | K48: Ultimate (Nov 2025) | L48: =SUM('Shuttle Count - Ultimate (Nov 2'!C48:D48) -> 9 | M48: =VLOOKUP(K48,'Shuttle Purchase'!A:C,3,0) -> 3.5715 | N48: =L48*M48 -> 32.1435 | O48: =VLOOKUP(E48,'Court List'!$A:$C,3,0) -> 12 | P48: =COUNTIF('Pub List'!$C48:$T48,"<>") -> 4 | Q48: =O48*P48 -> 48 | S48: =COUNTIF('Member List'!$C48:$J48,"<>") -> 2 | U48: =P48+S48 -> 6 | V48: =Q48 -> 48 | W48: =J48+N48 -> 48.1435 | X48: =V48-W48 -> -0.1435 | Y48: =Y47+X48 -> 311.785 | Z48: =V48 -> 48 | AA48: =-J48 -> -16 | AC48: =AC47+Z48+AA48+AB48 -> 693.16
A49: 46089 | B49: Sun | C49: 0.8125 | D49: 0.89583333 | E49: Siglap CC | F49: 1 & 3 | G49: =VLOOKUP(E49,'Court List'!$A:$C,2,0) -> 18 | H49: 2 | I49: 2 | J49: =G49*(H49*I49) -> 72 | K49: Supreme (Nov 2025) Ultimate (Nov 2025) | L49: 7 8 | M49: $3.47 $3.57 | N49: ='Shuttle Purchase'!C9*'Shuttle Count - Supreme (Nov 20'!D49+'Shuttle Purchase'!C8*'Shuttle Count - Ultimate (Nov 2'!C49 -> 52.836917 | O49: =VLOOKUP(E49,'Court List'!$A:$C,3,0) -> 14 | P49: =COUNTIF('Pub List'!$C49:$T49,"<>") -> 8 | Q49: =O49*P49 -> 112 | S49: =COUNTIF('Member List'!$C49:$J49,"<>") -> 4 | U49: =P49+S49 -> 12 | V49: =Q49 -> 112 | W49: =J49+N49 -> 124.83692 | X49: =V49-W49 -> -12.836917 | Y49: =Y48+X49 -> 298.94808 | Z49: =V49 -> 112 | AA49: =-J49 -> -72 | AC49: =AC48+Z49+AA49+AB49 -> 733.16
A50: 46096 | B50: Sun | C50: 0.8125 | D50: 0.89583333 | E50: Changi Simei CC | F50: 1 & 2 | G50: =VLOOKUP(E50,'Court List'!$A:$C,2,0) -> 6 | H50: 2 | I50: 2 | J50: =G50*(H50*I50) -> 24 | K50: Ultimate (Nov 2025) | L50: =SUM('Shuttle Count - Ultimate (Nov 2'!C50:D50) -> 12 | M50: =VLOOKUP(K50,'Shuttle Purchase'!A:C,3,0) -> 3.5715 | N50: =L50*M50 -> 42.858 | O50: =VLOOKUP(E50,'Court List'!$A:$C,3,0) -> 12 | P50: =COUNTIF('Pub List'!$C50:$T50,"<>") -> 10 | Q50: =O50*P50 -> 120 | S50: =COUNTIF('Member List'!$C50:$J50,"<>") -> 2 | U50: =P50+S50 -> 12 | V50: =Q50 -> 120 | W50: =J50+N50 -> 66.858 | X50: =V50-W50 -> 53.142 | Y50: =Y49+X50 -> 352.09008 | Z50: =V50 -> 120 | AA50: =-J50 -> -24 | AC50: =AC49+Z50+AA50+AB50 -> 829.16
A51: 46099 | B51: Wed | C51: 0.83333333 | D51: 0.91666667 | E51: Pasir Ris SH | F51: 1 | G51: =VLOOKUP(E51,'Court List'!$A:$C,2,0) -> 7.4 | H51: 2 | I51: 1 | J51: =G51*(H51*I51) -> 14.8 | K51: Supreme (Nov 2025) | L51: =SUM('Shuttle Count - Supreme (Nov 20'!C51:D51) -> 5 | M51: =VLOOKUP(K51,'Shuttle Purchase'!A:C,3,0) -> 3.4664167 | N51: =L51*M51 -> 17.332083 | O51: =VLOOKUP(E51,'Court List'!$A:$C,3,0) -> 12 | P51: =COUNTIF('Pub List'!$C51:$T51,"<>") -> 3 | Q51: =O51*P51 -> 36 | S51: =COUNTIF('Member List'!$C51:$J51,"<>") -> 3 | U51: =P51+S51 -> 6 | V51: =Q51 -> 36 | W51: =J51+N51 -> 32.132083 | X51: =V51-W51 -> 3.8679167 | Y51: =Y50+X51 -> 355.958 | Z51: =V51 -> 36 | AA51: =-J51 -> -14.8 | AC51: =AC50+Z51+AA51+AB51 -> 850.36
A52: 46103 | B52: Sun | C52: 0.77083333 | D52: 0.85416667 | E52: Siglap CC | F52: 1 & 2 | G52: =VLOOKUP(E52,'Court List'!$A:$C,2,0) -> 18 | H52: 2 | I52: 2 | J52: =G52*(H52*I52) -> 72 | K52: Supreme (Nov 2025) | L52: =SUM('Shuttle Count - Supreme (Nov 20'!C52:D52) + SUM('Shuttle Count - Ultimate (Nov 2'!C52:D52) -> 10 | M52: =VLOOKUP(K52,'Shuttle Purchase'!A:C,3,0) -> 3.4664167 | N52: =L52*M52 -> 34.664167 | O52: =VLOOKUP(E52,'Court List'!$A:$C,3,0) -> 14 | P52: =COUNTIF('Pub List'!$C52:$T52,"<>") -> 7 | Q52: =O52*P52 -> 98 | S52: =COUNTIF('Member List'!$C52:$J52,"<>") -> 5 | U52: =P52+S52 -> 12 | V52: =Q52 -> 98 | W52: =J52+N52 -> 106.66417 | X52: =V52-W52 -> -8.6641667 | Y52: =Y51+X52 -> 347.29383 | Z52: =V52 -> 98 | AA52: =-J52 -> -72 | AC52: =AC51+Z52+AA52+AB52 -> 876.36
A53: 46104 | B53: Mon | C53: 0.8125 | D53: 0.89583333 | E53: Macpherson CC | F53: 1 | G53: =VLOOKUP(E53,'Court List'!$A:$C,2,0) -> 6 | H53: 2 | I53: 1 | J53: =G53*(H53*I53) -> 12 | K53: Ultimate (Nov 2025) | L53: =SUM('Shuttle Count - Ultimate (Nov 2'!C53:D53) -> 5 | M53: =VLOOKUP(K53,'Shuttle Purchase'!A:C,3,0) -> 3.5715 | N53: =L53*M53 -> 17.8575 | O53: =VLOOKUP(E53,'Court List'!$A:$C,3,0) -> 12 | P53: =COUNTIF('Pub List'!$C53:$T53,"<>") -> 2 | Q53: =O53*P53 -> 24 | S53: =COUNTIF('Member List'!$C53:$J53,"<>") -> 4 | U53: =P53+S53 -> 6 | V53: =Q53 -> 24 | W53: =J53+N53 -> 29.8575 | X53: =V53-W53 -> -5.8575 | Y53: =Y52+X53 -> 341.43633 | Z53: =V53 -> 24 | AA53: =-J53 -> -12 | AC53: =AC52+Z53+AA53+AB53 -> 888.36
A54: 46115 | B54: Fri | C54: 0.83333333 | D54: 0.91666667 | E54: Pasir Ris SH | F54: 6 | G54: =VLOOKUP(E54,'Court List'!$A:$C,2,0) -> 7.4 | H54: 2 | I54: 1 | J54: =G54*(H54*I54) -> 14.8 | K54: Supreme (Nov 2025) Ultimate (Nov 2025) | L54: 2 3 | M54: $3.47 $3.57 | N54: =2*3.47+3*3.57 -> 17.65 | O54: =VLOOKUP(E54,'Court List'!$A:$C,3,0) -> 12 | P54: =COUNTIF('Pub List'!$C54:$T54,"<>") -> 4 | Q54: =O54*P54 -> 48 | S54: =COUNTIF('Member List'!$C54:$J54,"<>") -> 2 | U54: =P54+S54 -> 6 | V54: =Q54 -> 48 | W54: =J54+N54 -> 32.45 | X54: =V54-W54 -> 15.55 | Y54: =Y53+X54 -> 356.98633 | Z54: =V54 -> 48 | AA54: =-J54 -> -14.8 | AC54: =AC53+Z54+AA54+AB54 -> 921.56
A55: 46124 | B55: Sun | C55: 0.72916667 | D55: 0.8125 | E55: Siglap CC | F55: 1 & 2 | G55: =VLOOKUP(E55,'Court List'!$A:$C,2,0) -> 18 | H55: 2 | I55: 2 | J55: =G55*(H55*I55) -> 72 | K55: Supreme (Nov 2025) | L55: =SUM('Shuttle Count - Supreme (Nov 20'!C55:D55) -> 7 | M55: =VLOOKUP(K55,'Shuttle Purchase'!A:C,3,0) -> 3.4664167 | N55: =L55*M55 -> 24.264917 | O55: =VLOOKUP(E55,'Court List'!$A:$C,3,0) -> 14 | P55: =COUNTIF('Pub List'!$C55:$T55,"<>") -> 10 | Q55: =O55*P55 -> 140 | S55: =COUNTIF('Member List'!$C55:$J55,"<>") -> 2 | U55: =P55+S55 -> 12 | V55: =Q55 -> 140 | W55: =J55+N55 -> 96.264917 | X55: =V55-W55 -> 43.735083 | Y55: =Y54+X55 -> 400.72142 | Z55: =V55 -> 140 | AA55: =-J55 -> -72 | AC55: =AC54+Z55+AA55+AB55 -> 989.56
A56: 46125 | B56: Mon | C56: 0.8125 | D56: 0.89583333 | E56: Macpherson CC | F56: 1A | G56: =VLOOKUP(E56,'Court List'!$A:$C,2,0) -> 6 | H56: 2 | I56: 1 | J56: =G56*(H56*I56) -> 12 | K56: Supreme (Nov 2025) | L56: =SUM('Shuttle Count - Supreme (Nov 20'!C56:D56) -> 4 | M56: =VLOOKUP(K56,'Shuttle Purchase'!A:C,3,0) -> 3.4664167 | N56: =L56*M56 -> 13.865667 | O56: =VLOOKUP(E56,'Court List'!$A:$C,3,0) -> 12 | P56: =COUNTIF('Pub List'!$C56:$T56,"<>") -> 2 | Q56: =O56*P56 -> 24 | S56: =COUNTIF('Member List'!$C56:$J56,"<>") -> 4 | U56: =P56+S56 -> 6 | V56: =Q56 -> 24 | W56: =J56+N56 -> 25.865667 | X56: =V56-W56 -> -1.8656667 | Y56: =Y55+X56 -> 398.85575 | Z56: =V56 -> 24 | AA56: =-J56 -> -12 | AB56: -438.86 | AC56: =AC55+Z56+AA56+AB56 -> 562.7
A57: 46128 | B57: Thurs | C57: 0.83333333 | D57: 0.91666667 | E57: Seng Kang SH | F57: 6 | G57: =VLOOKUP(E57,'Court List'!$A:$C,2,0) -> 7.4 | H57: 2 | I57: 1 | J57: =G57*(H57*I57) -> 14.8 | K57: Supreme (Nov 2025) | L57: =SUM('Shuttle Count - Supreme (Nov 20'!C57:D57) -> 5 | M57: =VLOOKUP(K57,'Shuttle Purchase'!A:C,3,0) -> 3.4664167 | N57: =L57*M57 -> 17.332083 | O57: =VLOOKUP(E57,'Court List'!$A:$C,3,0) -> 12 | P57: =COUNTIF('Pub List'!$C57:$T57,"<>") -> 4 | Q57: =O57*P57 -> 48 | S57: =COUNTIF('Member List'!$C57:$J57,"<>") -> 2 | U57: =P57+S57 -> 6 | V57: =Q57 -> 48 | W57: =J57+N57 -> 32.132083 | X57: =V57-W57 -> 15.867917 | Y57: =Y56+X57 -> 414.72367 | Z57: =V57 -> 48 | AA57: =-J57 -> -14.8 | AC57: =AC56+Z57+AA57+AB57 -> 595.9
A58: 46130 | B58: Sat | C58: 0.8125 | D58: 0.89583333 | E58: Siglap CC | F58: 1 -> 3 & 2 | G58: =VLOOKUP(E58,'Court List'!$A:$C,2,0) -> 18 | H58: 2 | I58: 2 | J58: =G58*(H58*I58) -> 72 | K58: Supreme (Nov 2025) Ultimate (Nov 2025) | L58: 5 6 | M58: $3.47 $3.57 | N58: =5*3.47+6*3.57 -> 38.77 | O58: =VLOOKUP(E58,'Court List'!$A:$C,3,0) -> 14 | P58: =COUNTIF('Pub List'!$C58:$T58,"<>") -> 8 | Q58: =O58*P58 -> 112 | S58: =COUNTIF('Member List'!$C58:$J58,"<>") -> 4 | U58: =P58+S58 -> 12 | V58: =Q58 -> 112 | W58: =J58+N58 -> 110.77 | X58: =V58-W58 -> 1.23 | Y58: =Y57+X58 -> 415.95367 | Z58: =V58 -> 112 | AA58: =-J58 -> -72 | AC58: =AC57+Z58+AA58+AB58 -> 635.9
A59: 46132 | B59: Mon | C59: 0.8125 | D59: 0.89583333 | E59: Macpherson CC | F59: 1A | G59: =VLOOKUP(E59,'Court List'!$A:$C,2,0) -> 6 | H59: 2 | I59: 1 | J59: =G59*(H59*I59) -> 12 | K59: Ultimate (Nov 2025) | L59: =SUM('Shuttle Count - Ultimate (Nov 2'!C59:D59) -> 5 | M59: =VLOOKUP(K59,'Shuttle Purchase'!A:C,3,0) -> 3.5715 | N59: =L59*M59 -> 17.8575 | O59: =VLOOKUP(E59,'Court List'!$A:$C,3,0) -> 12 | P59: =COUNTIF('Pub List'!$C59:$T59,"<>") -> 2 | Q59: =O59*P59 -> 24 | S59: =COUNTIF('Member List'!$C59:$J59,"<>") -> 4 | U59: =P59+S59 -> 6 | V59: =Q59 -> 24 | W59: =J59+N59 -> 29.8575 | X59: =V59-W59 -> -5.8575 | Y59: =Y58+X59 -> 410.09617 | Z59: =V59 -> 24 | AA59: =-J59 -> -12 | AC59: =AC58+Z59+AA59+AB59 -> 647.9
A60: 46134 | B60: Wed | C60: 0.8125 | D60: 0.89583333 | E60: Changi Simei CC | F60: 1 -> 2 | G60: =VLOOKUP(E60,'Court List'!$A:$C,2,0) -> 6 | H60: 2 | I60: 1 | J60: =G60*(H60*I60) -> 12 | K60: Ultimate (Nov 2025) | L60: =SUM('Shuttle Count - Ultimate (Nov 2'!C60:D60) -> 5 | M60: =VLOOKUP(K60,'Shuttle Purchase'!A:C,3,0) -> 3.5715 | N60: =L60*M60 -> 17.8575 | O60: =VLOOKUP(E60,'Court List'!$A:$C,3,0) -> 12 | P60: =COUNTIF('Pub List'!$C60:$T60,"<>") -> 2 | Q60: =O60*P60 -> 24 | S60: =COUNTIF('Member List'!$C60:$J60,"<>") -> 4 | U60: =P60+S60 -> 6 | V60: =Q60 -> 24 | W60: =J60+N60 -> 29.8575 | X60: =V60-W60 -> -5.8575 | Y60: =Y59+X60 -> 404.23867 | Z60: =V60 -> 24 | AA60: =-J60 -> -12 | AC60: =AC59+Z60+AA60+AB60 -> 659.9
A61: 46138 | B61: Sun | C61: 0.70833333 | D61: 0.79166667 | E61: Pasir Ris SH | F61: 2 | G61: =VLOOKUP(E61,'Court List'!$A:$C,2,0) -> 7.4 | H61: 2 | I61: 1 | J61: =G61*(H61*I61) -> 14.8 | K61: Ultimate (Nov 2025) | L61: =SUM('Shuttle Count - Ultimate (Nov 2'!C61:D61) -> 3 | M61: =VLOOKUP(K61,'Shuttle Purchase'!A:C,3,0) -> 3.5715 | N61: =L61*M61 -> 10.7145 | O61: =VLOOKUP(E61,'Court List'!$A:$C,3,0) -> 12 | P61: =COUNTIF('Pub List'!$C61:$T61,"<>") -> 2 | Q61: =O61*P61 -> 24 | S61: =COUNTIF('Member List'!$C61:$J61,"<>") -> 4 | U61: =P61+S61 -> 6 | V61: =Q61 -> 24 | W61: =J61+N61 -> 25.5145 | X61: =V61-W61 -> -1.5145 | Y61: =Y60+X61 -> 402.72417 | Z61: =V61 -> 24 | AA61: =-J61 -> -14.8 | AC61: =AC60+Z61+AA61+AB61 -> 669.1
A62: 46140 | B62: Tues | C62: 0.8125 | D62: 0.89583333 | E62: Changi Simei CC | F62: 1 | G62: =VLOOKUP(E62,'Court List'!$A:$C,2,0) -> 6 | H62: 2 | I62: 1 | J62: =G62*(H62*I62) -> 12 | K62: Ultimate (Nov 2025) | L62: =SUM('Shuttle Count - Ultimate (Nov 2'!C62:D62) -> 4 | M62: =VLOOKUP(K62,'Shuttle Purchase'!A:C,3,0) -> 3.5715 | N62: =L62*M62 -> 14.286 | O62: =VLOOKUP(E62,'Court List'!$A:$C,3,0) -> 12 | P62: =COUNTIF('Pub List'!$C62:$T62,"<>") -> 2 | Q62: =O62*P62 -> 24 | S62: =COUNTIF('Member List'!$C62:$J62,"<>") -> 4 | U62: =P62+S62 -> 6 | V62: =Q62 -> 24 | W62: =J62+N62 -> 26.286 | X62: =V62-W62 -> -2.286 | Y62: =Y61+X62 -> 400.43817 | Z62: =V62 -> 24 | AA62: =-J62 -> -12 | AC62: =AC61+Z62+AA62+AB62 -> 681.1
A63: 46141 | B63: Wed | C63: 0.8125 | D63: 0.89583333 | E63: Macpherson CC | F63: 1B | G63: =VLOOKUP(E63,'Court List'!$A:$C,2,0) -> 6 | H63: 2 | I63: 1 | J63: =G63*(H63*I63) -> 12 | K63: Ultimate (Nov 2025) | L63: =SUM('Shuttle Count - Ultimate (Nov 2'!C63:D63) -> 6 | M63: =VLOOKUP(K63,'Shuttle Purchase'!A:C,3,0) -> 3.5715 | N63: =L63*M63 -> 21.429 | O63: =VLOOKUP(E63,'Court List'!$A:$C,3,0) -> 12 | P63: =COUNTIF('Pub List'!$C63:$T63,"<>") -> 2 | Q63: =O63*P63 -> 24 | S63: =COUNTIF('Member List'!$C63:$J63,"<>") -> 4 | U63: =P63+S63 -> 6 | V63: =Q63 -> 24 | W63: =J63+N63 -> 33.429 | X63: =V63-W63 -> -9.429 | Y63: =Y62+X63 -> 391.00917 | Z63: =V63 -> 24 | AA63: =-J63 -> -12 | AC63: =AC62+Z63+AA63+AB63 -> 693.1
A64: 46144 | B64: Sat | C64: 0.8125 | D64: 0.89583333 | E64: Changi Simei CC | F64: 1 & 2 | G64: =VLOOKUP(E64,'Court List'!$A:$C,2,0) -> 6 | H64: 2 | I64: 2 | J64: =G64*(H64*I64) -> 24 | K64: Ultimate (Nov 2025) | L64: =SUM('Shuttle Count - Ultimate (Nov 2'!C64:D64) -> 7 | M64: =VLOOKUP(K64,'Shuttle Purchase'!A:C,3,0) -> 3.5715 | N64: =L64*M64 -> 25.0005 | O64: =VLOOKUP(E64,'Court List'!$A:$C,3,0) -> 12 | P64: =COUNTIF('Pub List'!$C64:$T64,"<>") -> 7 | Q64: =O64*P64 -> 84 | S64: =COUNTIF('Member List'!$C64:$J64,"<>") -> 5 | U64: =P64+S64 -> 12 | V64: =Q64 -> 84 | W64: =J64+N64 -> 49.0005 | X64: =V64-W64 -> 34.9995 | Y64: =Y63+X64 -> 426.00867 | Z64: =V64 -> 84 | AA64: =-J64 -> -24 | AC64: =AC63+Z64+AA64+AB64 -> 753.1
A65: 46152 | B65: Sun | C65: 0.72916667 | D65: 0.8125 | E65: Siglap CC | F65: 1 & 2 | G65: =VLOOKUP(E65,'Court List'!$A:$C,2,0) -> 18 | H65: 2 | I65: 2 | J65: =G65*(H65*I65) -> 72 | K65: Ultimate (Nov 2025) | L65: =SUM('Shuttle Count - Ultimate (Nov 2'!C65:D65) -> 13 | M65: =VLOOKUP(K65,'Shuttle Purchase'!A:C,3,0) -> 3.5715 | N65: =L65*M65 -> 46.4295 | O65: =VLOOKUP(E65,'Court List'!$A:$C,3,0) -> 14 | P65: =COUNTIF('Pub List'!$C65:$T65,"<>") -> 8 | Q65: =O65*P65 -> 112 | S65: =COUNTIF('Member List'!$C65:$J65,"<>") -> 4 | U65: =P65+S65 -> 12 | V65: =Q65 -> 112 | W65: =J65+N65 -> 118.4295 | X65: =V65-W65 -> -6.4295 | Y65: =Y64+X65 -> 419.57917 | Z65: =V65 -> 112 | AA65: =-J65 -> -72 | AC65: =AC64+Z65+AA65+AB65 -> 793.1
A66: 46156 | B66: Thurs | C66: 0.8125 | D66: 0.89583333 | E66: Kaki Bukit CC | F66: 1 | G66: =VLOOKUP(E66,'Court List'!$A:$C,2,0) -> 6 | H66: 2 | I66: 1 | J66: =G66*(H66*I66) -> 12 | K66: Ultimate (Nov 2025) | L66: =SUM('Shuttle Count - Ultimate (Nov 2'!C66:D66) -> 6 | M66: =VLOOKUP(K66,'Shuttle Purchase'!A:C,3,0) -> 3.5715 | N66: =L66*M66 -> 21.429 | O66: =VLOOKUP(E66,'Court List'!$A:$C,3,0) -> 12 | P66: =COUNTIF('Pub List'!$C66:$T66,"<>") -> 2 | Q66: =O66*P66 -> 24 | S66: =COUNTIF('Member List'!$C66:$J66,"<>") -> 4 | U66: =P66+S66 -> 6 | V66: =Q66 -> 24 | W66: =J66+N66 -> 33.429 | X66: =V66-W66 -> -9.429 | Y66: =Y65+X66 -> 410.15017 | Z66: =V66 -> 24 | AA66: =-J66 -> -12 | AC66: =AC65+Z66+AA66+AB66 -> 805.1
A67: 46157 | B67: Fri | C67: 0.8125 | D67: 0.89583333 | E67: Changi Simei CC | F67: 1 & 2 | G67: =VLOOKUP(E67,'Court List'!$A:$C,2,0) -> 6 | H67: 2 | I67: 2 | J67: =G67*(H67*I67) -> 24 | K67: Ultimate (Nov 2025) | L67: =SUM('Shuttle Count - Ultimate (Nov 2'!C67:D67) -> 12 | M67: =VLOOKUP(K67,'Shuttle Purchase'!A:C,3,0) -> 3.5715 | N67: =L67*M67 -> 42.858 | O67: =VLOOKUP(E67,'Court List'!$A:$C,3,0) -> 12 | P67: =COUNTIF('Pub List'!$C67:$T67,"<>") -> 8 | Q67: =O67*P67 -> 96 | S67: =COUNTIF('Member List'!$C67:$J67,"<>") -> 4 | U67: =P67+S67 -> 12 | V67: =Q67 -> 96 | W67: =J67+N67 -> 66.858 | X67: =V67-W67 -> 29.142 | Y67: =Y66+X67 -> 439.29217 | Z67: =V67 -> 96 | AA67: =-J67 -> -24 | AC67: =AC66+Z67+AA67+AB67 -> 877.1
A68: 46158 | B68: Sat | C68: 0.72916667 | D68: 0.8125 | E68: Fengshan CC | F68: 1 & 2 | G68: =VLOOKUP(E68,'Court List'!$A:$C,2,0) -> 8 | H68: 2 | I68: 2 | J68: =G68*(H68*I68) -> 32 | L68: =SUM('Shuttle Count - Supreme (Nov 20'!C68:D68) -> 0 | M68: =VLOOKUP(K68,'Shuttle Purchase'!A:C,3,0) -> #N/A | N68: =L68*M68 -> #N/A | O68: =VLOOKUP(E68,'Court List'!$A:$C,3,0) -> 12 | P68: =COUNTIF('Pub List'!$C68:$T68,"<>") -> 8 | Q68: =O68*P68 -> 96 | S68: =COUNTIF('Member List'!$C68:$J68,"<>") -> 4 | U68: =P68+S68 -> 12 | V68: =Q68 -> 96 | W68: =J68+N68 -> #N/A | X68: =V68-W68 -> #N/A | Y68: =Y67+X68 -> #N/A | Z68: =V68 -> 96 | AA68: =-J68 -> -32 | AC68: =AC67+Z68+AA68+AB68 -> 941.1
A69: 46160 | B69: Mon | C69: 0.8125 | D69: 0.89583333 | E69: Macpherson CC | F69: 1A | G69: =VLOOKUP(E69,'Court List'!$A:$C,2,0) -> 6 | H69: 2 | I69: 1 | J69: =G69*(H69*I69) -> 12 | L69: =SUM('Shuttle Count - Supreme (Nov 20'!C69:D69) -> 0 | M69: =VLOOKUP(K69,'Shuttle Purchase'!A:C,3,0) -> #N/A | N69: =L69*M69 -> #N/A | O69: =VLOOKUP(E69,'Court List'!$A:$C,3,0) -> 12 | P69: =COUNTIF('Pub List'!$C69:$T69,"<>") -> 2 | Q69: =O69*P69 -> 24 | S69: =COUNTIF('Member List'!$C69:$J69,"<>") -> 4 | U69: =P69+S69 -> 6 | V69: =Q69 -> 24 | W69: =J69+N69 -> #N/A | X69: =V69-W69 -> #N/A | Y69: =Y68+X69 -> #N/A | Z69: =V69 -> 24 | AA69: =-J69 -> -12 | AC69: =AC68+Z69+AA69+AB69 -> 953.1
A70: 46166 | B70: Sun | C70: 0.72916667 | D70: 0.8125 | E70: Fengshan CC | F70: 1 | G70: =VLOOKUP(E70,'Court List'!$A:$C,2,0) -> 8 | H70: 2 | I70: 1 | J70: =G70*(H70*I70) -> 16 | L70: =SUM('Shuttle Count - Supreme (Nov 20'!C70:D70) -> 0 | M70: =VLOOKUP(K70,'Shuttle Purchase'!A:C,3,0) -> #N/A | N70: =L70*M70 -> #N/A | O70: =VLOOKUP(E70,'Court List'!$A:$C,3,0) -> 12 | P70: =COUNTIF('Pub List'!$C70:$T70,"<>") -> 2 | Q70: =O70*P70 -> 24 | S70: =COUNTIF('Member List'!$C70:$J70,"<>") -> 2 | U70: =P70+S70 -> 4 | V70: =Q70 -> 24 | W70: =J70+N70 -> #N/A | X70: =V70-W70 -> #N/A | Y70: =Y69+X70 -> #N/A | Z70: =V70 -> 24 | AA70: =-J70 -> -16 | AC70: =AC69+Z70+AA70+AB70 -> 961.1
A71: 46171 | B71: Fri | C71: 0.8125 | D71: 0.89583333 | E71: Fengshan CC | F71: 1 & 2 | G71: =VLOOKUP(E71,'Court List'!$A:$C,2,0) -> 8 | H71: 2 | I71: 2 | J71: =G71*(H71*I71) -> 32 | L71: =SUM('Shuttle Count - Supreme (Nov 20'!C71:D71) -> 0 | M71: =VLOOKUP(K71,'Shuttle Purchase'!A:C,3,0) -> #N/A | N71: =L71*M71 -> #N/A | O71: =VLOOKUP(E71,'Court List'!$A:$C,3,0) -> 12 | P71: =COUNTIF('Pub List'!$C71:$T71,"<>") -> 1 | Q71: =O71*P71 -> 12 | S71: =COUNTIF('Member List'!$C71:$J71,"<>") -> 2 | U71: =P71+S71 -> 3 | V71: =Q71 -> 12 | W71: =J71+N71 -> #N/A | X71: =V71-W71 -> #N/A | Y71: =Y70+X71 -> #N/A | Z71: =V71 -> 12 | AA71: =-J71 -> -32 | AC71: =AC70+Z71+AA71+AB71 -> 941.1
A72: 46172 | B72: Sat | C72: 0.8125 | D72: 0.89583333 | E72: Siglap CC | F72: 3 | G72: =VLOOKUP(E72,'Court List'!$A:$C,2,0) -> 18 | H72: 2 | I72: 1 | J72: =G72*(H72*I72) -> 36 | L72: =SUM('Shuttle Count - Supreme (Nov 20'!C72:D72) -> 0 | M72: =VLOOKUP(K72,'Shuttle Purchase'!A:C,3,0) -> #N/A | N72: =L72*M72 -> #N/A | O72: =VLOOKUP(E72,'Court List'!$A:$C,3,0) -> 14 | P72: =COUNTIF('Pub List'!$C72:$T72,"<>") -> 0 | Q72: =O72*P72 -> 0 | S72: =COUNTIF('Member List'!$C72:$J72,"<>") -> 2 | U72: =P72+S72 -> 2 | V72: =Q72 -> 0 | W72: =J72+N72 -> #N/A | X72: =V72-W72 -> #N/A | Y72: =Y71+X72 -> #N/A | Z72: =V72 -> 0 | AA72: =-J72 -> -36 | AC72: =AC71+Z72+AA72+AB72 -> 905.1
A73: 46180 | B73: Sun | C73: 0.77083333 | D73: 0.85416667 | E73: Siglap CC | F73: 1 & 2 | G73: =VLOOKUP(E73,'Court List'!$A:$C,2,0) -> 18 | H73: 2 | I73: 2 | J73: =G73*(H73*I73) -> 72 | L73: =SUM('Shuttle Count - Supreme (Nov 20'!C73:D73) -> 0 | M73: =VLOOKUP(K73,'Shuttle Purchase'!A:C,3,0) -> #N/A | N73: =L73*M73 -> #N/A | O73: =VLOOKUP(E73,'Court List'!$A:$C,3,0) -> 14 | P73: =COUNTIF('Pub List'!$C73:$T73,"<>") -> 0 | Q73: =O73*P73 -> 0 | S73: =COUNTIF('Member List'!$C73:$J73,"<>") -> 2 | U73: =P73+S73 -> 2 | V73: =Q73 -> 0 | W73: =J73+N73 -> #N/A | X73: =V73-W73 -> #N/A | Y73: =Y72+X73 -> #N/A | Z73: =V73 -> 0 | AA73: =-J73 -> -72 | AC73: =AC72+Z73+AA73+AB73 -> 833.1
G74: =VLOOKUP(E74,'Court List'!$A:$C,2,0) -> #N/A | J74: =G74*(H74*I74) -> #N/A | L74: =SUM('Shuttle Count - Supreme (Nov 20'!C74:D74) -> 0 | M74: =VLOOKUP(K74,'Shuttle Purchase'!A:C,3,0) -> #N/A | N74: =L74*M74 -> #N/A | O74: =VLOOKUP(E74,'Court List'!$A:$C,3,0) -> #N/A | P74: =COUNTIF('Pub List'!$C74:$T74,"<>") -> 0 | Q74: =O74*P74 -> #N/A | S74: =COUNTIF('Member List'!$C74:$J74,"<>") -> 0 | U74: =P74+S74 -> 0 | V74: =Q74 -> #N/A | W74: =J74+N74 -> #N/A | X74: =V74-W74 -> #N/A | Y74: =Y73+X74 -> #N/A | Z74: =V74 -> #N/A | AA74: =-J74 -> #N/A | AC74: =AC73+Z74+AA74+AB74 -> #N/A
G75: =VLOOKUP(E75,'Court List'!$A:$C,2,0) -> #N/A | J75: =G75*(H75*I75) -> #N/A | L75: =SUM('Shuttle Count - Supreme (Nov 20'!C75:D75) -> 0 | M75: =VLOOKUP(K75,'Shuttle Purchase'!A:C,3,0) -> #N/A | N75: =L75*M75 -> #N/A | O75: =VLOOKUP(E75,'Court List'!$A:$C,3,0) -> #N/A | P75: =COUNTIF('Pub List'!$C75:$T75,"<>") -> 0 | Q75: =O75*P75 -> #N/A | S75: =COUNTIF('Member List'!$C75:$J75,"<>") -> 0 | U75: =P75+S75 -> 0 | V75: =Q75 -> #N/A | W75: =J75+N75 -> #N/A | X75: =V75-W75 -> #N/A | Y75: =Y74+X75 -> #N/A | Z75: =V75 -> #N/A | AA75: =-J75 -> #N/A | AC75: =AC74+Z75+AA75+AB75 -> #N/A
G76: =VLOOKUP(E76,'Court List'!$A:$C,2,0) -> #N/A | J76: =G76*(H76*I76) -> #N/A | L76: =SUM('Shuttle Count - Supreme (Nov 20'!C76:D76) -> 0 | M76: =VLOOKUP(K76,'Shuttle Purchase'!A:C,3,0) -> #N/A | N76: =L76*M76 -> #N/A | O76: =VLOOKUP(E76,'Court List'!$A:$C,3,0) -> #N/A | P76: =COUNTIF('Pub List'!$C76:$T76,"<>") -> 0 | Q76: =O76*P76 -> #N/A | S76: =COUNTIF('Member List'!$C76:$J76,"<>") -> 0 | U76: =P76+S76 -> 0 | V76: =Q76 -> #N/A | W76: =J76+N76 -> #N/A | X76: =V76-W76 -> #N/A | Y76: =Y75+X76 -> #N/A | Z76: =V76 -> #N/A | AA76: =-J76 -> #N/A | AC76: =AC75+Z76+AA76+AB76 -> #N/A
G77: =VLOOKUP(E77,'Court List'!$A:$C,2,0) -> #N/A | J77: =G77*(H77*I77) -> #N/A | L77: =SUM('Shuttle Count - Supreme (Nov 20'!C77:D77) -> 0 | M77: =VLOOKUP(K77,'Shuttle Purchase'!A:C,3,0) -> #N/A | N77: =L77*M77 -> #N/A | O77: =VLOOKUP(E77,'Court List'!$A:$C,3,0) -> #N/A | P77: =COUNTIF('Pub List'!$C77:$T77,"<>") -> 0 | Q77: =O77*P77 -> #N/A | S77: =COUNTIF('Member List'!$C77:$J77,"<>") -> 0 | U77: =P77+S77 -> 0 | V77: =Q77 -> #N/A | W77: =J77+N77 -> #N/A | X77: =V77-W77 -> #N/A | Y77: =Y76+X77 -> #N/A | Z77: =V77 -> #N/A | AA77: =-J77 -> #N/A | AC77: =AC76+Z77+AA77+AB77 -> #N/A
G78: =VLOOKUP(E78,'Court List'!$A:$C,2,0) -> #N/A | J78: =G78*(H78*I78) -> #N/A | L78: =SUM('Shuttle Count - Supreme (Nov 20'!C78:D78) -> 0 | M78: =VLOOKUP(K78,'Shuttle Purchase'!A:C,3,0) -> #N/A | N78: =L78*M78 -> #N/A | O78: =VLOOKUP(E78,'Court List'!$A:$C,3,0) -> #N/A | P78: =COUNTIF('Pub List'!$C78:$T78,"<>") -> 0 | Q78: =O78*P78 -> #N/A | S78: =COUNTIF('Member List'!$C78:$J78,"<>") -> 0 | U78: =P78+S78 -> 0 | V78: =Q78 -> #N/A | W78: =J78+N78 -> #N/A | X78: =V78-W78 -> #N/A | Y78: =Y77+X78 -> #N/A | Z78: =V78 -> #N/A | AA78: =-J78 -> #N/A | AC78: =AC77+Z78+AA78+AB78 -> #N/A
G79: =VLOOKUP(E79,'Court List'!$A:$C,2,0) -> #N/A | J79: =G79*(H79*I79) -> #N/A | L79: =SUM('Shuttle Count - Supreme (Nov 20'!C79:D79) -> 0 | M79: =VLOOKUP(K79,'Shuttle Purchase'!A:C,3,0) -> #N/A | N79: =L79*M79 -> #N/A | O79: =VLOOKUP(E79,'Court List'!$A:$C,3,0) -> #N/A | P79: =COUNTIF('Pub List'!$C79:$T79,"<>") -> 0 | Q79: =O79*P79 -> #N/A | S79: =COUNTIF('Member List'!$C79:$J79,"<>") -> 0 | U79: =P79+S79 -> 0 | V79: =Q79 -> #N/A | W79: =J79+N79 -> #N/A | X79: =V79-W79 -> #N/A | Y79: =Y78+X79 -> #N/A | Z79: =V79 -> #N/A | AA79: =-J79 -> #N/A | AC79: =AC78+Z79+AA79+AB79 -> #N/A
G80: =VLOOKUP(E80,'Court List'!$A:$C,2,0) -> #N/A | J80: =G80*(H80*I80) -> #N/A | L80: =SUM('Shuttle Count - Supreme (Nov 20'!C80:D80) -> 0 | M80: =VLOOKUP(K80,'Shuttle Purchase'!A:C,3,0) -> #N/A | N80: =L80*M80 -> #N/A | O80: =VLOOKUP(E80,'Court List'!$A:$C,3,0) -> #N/A | P80: =COUNTIF('Pub List'!$C80:$T80,"<>") -> 0 | Q80: =O80*P80 -> #N/A | S80: =COUNTIF('Member List'!$C80:$J80,"<>") -> 0 | U80: =P80+S80 -> 0 | V80: =Q80 -> #N/A | W80: =J80+N80 -> #N/A | X80: =V80-W80 -> #N/A | Y80: =Y79+X80 -> #N/A | Z80: =V80 -> #N/A | AA80: =-J80 -> #N/A | AC80: =AC79+Z80+AA80+AB80 -> #N/A
G81: =VLOOKUP(E81,'Court List'!$A:$C,2,0) -> #N/A | J81: =G81*(H81*I81) -> #N/A | L81: =SUM('Shuttle Count - Supreme (Nov 20'!C81:D81) -> 0 | M81: =VLOOKUP(K81,'Shuttle Purchase'!A:C,3,0) -> #N/A | N81: =L81*M81 -> #N/A | O81: =VLOOKUP(E81,'Court List'!$A:$C,3,0) -> #N/A | P81: =COUNTIF('Pub List'!$C81:$T81,"<>") -> 0 | Q81: =O81*P81 -> #N/A | S81: =COUNTIF('Member List'!$C81:$J81,"<>") -> 0 | U81: =P81+S81 -> 0 | V81: =Q81 -> #N/A | W81: =J81+N81 -> #N/A | X81: =V81-W81 -> #N/A | Y81: =Y80+X81 -> #N/A | Z81: =V81 -> #N/A | AA81: =-J81 -> #N/A | AC81: =AC80+Z81+AA81+AB81 -> #N/A
G82: =VLOOKUP(E82,'Court List'!$A:$C,2,0) -> #N/A | J82: =G82*(H82*I82) -> #N/A | L82: =SUM('Shuttle Count - Supreme (Nov 20'!C82:D82) -> 0 | M82: =VLOOKUP(K82,'Shuttle Purchase'!A:C,3,0) -> #N/A | N82: =L82*M82 -> #N/A | O82: =VLOOKUP(E82,'Court List'!$A:$C,3,0) -> #N/A | P82: =COUNTIF('Pub List'!$C82:$T82,"<>") -> 0 | Q82: =O82*P82 -> #N/A | S82: =COUNTIF('Member List'!$C82:$J82,"<>") -> 0 | U82: =P82+S82 -> 0 | V82: =Q82 -> #N/A | W82: =J82+N82 -> #N/A | X82: =V82-W82 -> #N/A | Y82: =Y81+X82 -> #N/A | Z82: =V82 -> #N/A | AA82: =-J82 -> #N/A | AC82: =AC81+Z82+AA82+AB82 -> #N/A
G83: =VLOOKUP(E83,'Court List'!$A:$C,2,0) -> #N/A | J83: =G83*(H83*I83) -> #N/A | L83: =SUM('Shuttle Count - Supreme (Nov 20'!C83:D83) -> 0 | M83: =VLOOKUP(K83,'Shuttle Purchase'!A:C,3,0) -> #N/A | N83: =L83*M83 -> #N/A | O83: =VLOOKUP(E83,'Court List'!$A:$C,3,0) -> #N/A | P83: =COUNTIF('Pub List'!$C83:$T83,"<>") -> 0 | Q83: =O83*P83 -> #N/A | S83: =COUNTIF('Member List'!$C83:$J83,"<>") -> 0 | U83: =P83+S83 -> 0 | V83: =Q83 -> #N/A | W83: =J83+N83 -> #N/A | X83: =V83-W83 -> #N/A | Y83: =Y82+X83 -> #N/A | Z83: =V83 -> #N/A | AA83: =-J83 -> #N/A | AC83: =AC82+Z83+AA83+AB83 -> #N/A
G84: =VLOOKUP(E84,'Court List'!$A:$C,2,0) -> #N/A | J84: =G84*(H84*I84) -> #N/A | L84: =SUM('Shuttle Count - Supreme (Nov 20'!C84:D84) -> 0 | M84: =VLOOKUP(K84,'Shuttle Purchase'!A:C,3,0) -> #N/A | N84: =L84*M84 -> #N/A | O84: =VLOOKUP(E84,'Court List'!$A:$C,3,0) -> #N/A | P84: =COUNTIF('Pub List'!$C84:$T84,"<>") -> 0 | Q84: =O84*P84 -> #N/A | S84: =COUNTIF('Member List'!$C84:$J84,"<>") -> 0 | U84: =P84+S84 -> 0 | V84: =Q84 -> #N/A | W84: =J84+N84 -> #N/A | X84: =V84-W84 -> #N/A | Y84: =Y83+X84 -> #N/A | Z84: =V84 -> #N/A | AA84: =-J84 -> #N/A | AC84: =AC83+Z84+AA84+AB84 -> #N/A
G85: =VLOOKUP(E85,'Court List'!$A:$C,2,0) -> #N/A | J85: =G85*(H85*I85) -> #N/A | L85: =SUM('Shuttle Count - Supreme (Nov 20'!C85:D85) -> 0 | M85: =VLOOKUP(K85,'Shuttle Purchase'!A:C,3,0) -> #N/A | N85: =L85*M85 -> #N/A | O85: =VLOOKUP(E85,'Court List'!$A:$C,3,0) -> #N/A | P85: =COUNTIF('Pub List'!$C85:$T85,"<>") -> 0 | Q85: =O85*P85 -> #N/A | S85: =COUNTIF('Member List'!$C85:$J85,"<>") -> 0 | U85: =P85+S85 -> 0 | V85: =Q85 -> #N/A | W85: =J85+N85 -> #N/A | X85: =V85-W85 -> #N/A | Y85: =Y84+X85 -> #N/A | Z85: =V85 -> #N/A | AA85: =-J85 -> #N/A | AC85: =AC84+Z85+AA85+AB85 -> #N/A
... G991: =VLOOKUP(E991,'Court List'!$A:$C,2,0) -> #N/A | J991: =G991*(H991*I991) -> #N/A | L991: =SUM('Shuttle Count - Supreme (Nov 20'!C991:D991) -> 0 | M991: =VLOOKUP(K991,'Shuttle Purchase'!A:C,3,0) -> #N/A | N991: =L991*M991 -> #N/A | O991: =VLOOKUP(E991,'Court List'!$A:$C,3,0) -> #N/A | P991: =COUNTIF('Pub List'!$C991:$T991,"<>") -> 0 | Q991: =O991*P991 -> #N/A | S991: =COUNTIF('Member List'!$C991:$J991,"<>") -> 0 | U991: =P991+S991 -> 0 | V991: =Q991 -> #N/A | W991: =J991+N991 -> #N/A | X991: =V991-W991 -> #N/A | Y991: =Y990+X991 -> #N/A | Z991: =V991 -> #N/A | AA991: =-J991 -> #N/A | AC991: =AC990+Z991+AA991+AB991 -> #N/A

Sheet Pub List
A1: Pub List
A5: Date | B5: Day | C5: Pub 1 | D5: Pub 2 | E5: Pub 3 | F5: Pub 4 | G5: Pub 5 | H5: Pub 6 | I5: Pub 7 | J5: Pub 8 | K5: Pub 9 | L5: Pub 10 | M5: Pub 11 | N5: Pub 12 | O5: Pub 13 | P5: Pub 14 | Q5: Pub 15 | R5: Pub 16 | S5: Pub 17 | T5: Pub 18
A6: ='Profit & Loss'!A6 -> 45955 | B6: ='Profit & Loss'!B6 -> Sat | C6: Joo Ching | D6: Fish - Ban | E6: Fish - Nellie | F6: Jia Sheng | G6: Kurt | H6: Ray | I6: MVT | J6: YS
A7: ='Profit & Loss'!A7 -> 45960 | B7: ='Profit & Loss'!B7 -> Thurs | C7: Shannon | D7: Shao Heng | E7: Javier
A8: ='Profit & Loss'!A8 -> 45963 | B8: ='Profit & Loss'!B8 -> Sun | C8: Joo Ching | D8: Lim Kang | E8: Lewis | F8: Kang +1 | G8: Ray | H8: Zenn | I8: Shao Heng
A9: ='Profit & Loss'!A9 -> 45965 | B9: ='Profit & Loss'!B9 -> Tues | C9: Lewis
A10: ='Profit & Loss'!A10 -> 45969 | B10: ='Profit & Loss'!B10 -> Sat | C10: Joo Ching | D10: Shary | E10: Jia Sheng | F10: Jian Hong | G10: Kang Wei | H10: Wei Liang | I10: Nic
A11: ='Profit & Loss'!A11 -> 45973 | B11: ='Profit & Loss'!B11 -> Wed | C11: Joey | D11: Wei Liang | E11: Shannon
A12: ='Profit & Loss'!A12 -> 45977 | B12: ='Profit & Loss'!B12 -> Sun | C12: Joo Ching | D12: Brendan | E12: Brendan +1 | F12: Chong Seng | G12: Chong Seng +1 | H12: Ivan | I12: Ivan +1 | J12: Ivan +2 | K12: Nic | L12: KC | M12: Ray
A13: ='Profit & Loss'!A13 -> 45978 | B13: ='Profit & Loss'!B13 -> Mon | C13: Kang Wei | D13: Kang Wei +1 | E13: Kang Wei +2 | F13: Lewis
A14: ='Profit & Loss'!A14 -> 45979 | B14: ='Profit & Loss'!B14 -> Tues | C14: Melvin | D14: Melvin +1 | E14: Marcus | F14: Marcus +1 | G14: Joey | H14: Xing Shuo | I14: Jian Hong | J14: Shannon | K14: Ben | L14: Lewis
A15: ='Profit & Loss'!A15 -> 45981 | B15: ='Profit & Loss'!B15 -> Thurs | C15: Nic
A16: ='Profit & Loss'!A16 -> 45984 | B16: ='Profit & Loss'!B16 -> Sun | C16: Joo Ching | D16: Jia Sheng | E16: Sharry | F16: Wind Ong | G16: Jadon | H16: Jadon +1 | I16: Kang Yee | J16: Kwok Kah Hao
A17: ='Profit & Loss'!A17 -> 45987 | B17: ='Profit & Loss'!B17 -> Wed | C17: Brendan | D17: Brendan +1 | E17: Wai Seng | F17: Dylan | G17: Shannon | H17: Edwin | I17: Eugene Lian
A18: ='Profit & Loss'!A18 -> 45988 | B18: ='Profit & Loss'!B18 -> Thurs | C18: Javier
A19: ='Profit & Loss'!A19 -> 45991 | B19: ='Profit & Loss'!B19 -> Sun | C19: Brendan | D19: Brendan +1 | E19: Joo Ching | F19: Owen | G19: Len | H19: Andy | I19: William | J19: Dan | K19: Gerry | L19: Zenn Goh
A20: ='Profit & Loss'!A20 -> 45998 | B20: ='Profit & Loss'!B20 -> Sun | C20: Joo Ching | D20: Brendan | E20: Brendan +1 | F20: Zenn Goh | G20: Gerry | H20: Kurt | I20: Owen | J20: Jensen Tie | K20: Nic | L20: Lai Chung Hin (Ah Lai) | M20: KC | N20: Jadon | O20: Jadon +1
A21: ='Profit & Loss'!A21 -> 45999 | B21: ='Profit & Loss'!B21 -> Mon | C21: Lewis | D21: Jasper
A22: ='Profit & Loss'!A22 -> 46001 | B22: ='Profit & Loss'!B22 -> Wed | C22: Lewis | D22: Joey | E22: Jian Hong | F22: Shannon
A23: ='Profit & Loss'!A23 -> 46004 | B23: ='Profit & Loss'!B23 -> Sat | C23: Alex | D23: Alex +1 | E23: Alex +2 | F23: Lewis | G23: Kang Wei | H23: Nobody | I23: Nobody +1
A24: ='Profit & Loss'!A24 -> 46006 | B24: ='Profit & Loss'!B24 -> Mon | C24: Lewis | D24: Jadon | E24: Anton
A25: ='Profit & Loss'!A25 -> 46011 | B25: ='Profit & Loss'!B25 -> Sat | C25: Brendan | D25: Brendan +1 | E25: Joo Ching | F25: Kah Hao | G25: Shao Heng | H25: Nathan | I25: Steve
A26: ='Profit & Loss'!A26 -> 46017 | B26: ='Profit & Loss'!B26 -> Fri | C26: Joo Ching | D26: Thomas | E26: Zenn Goh | F26: Fish - Ban | G26: Melvin | H26: Melvin +1 | I26: Mike | J26: Foo Hin +1
A27: ='Profit & Loss'!A27 -> 46019 | B27: ='Profit & Loss'!B27 -> Sun | C27: Nicholas | D27: Lewis | E27: Ray
A28: ='Profit & Loss'!A28 -> 46020 | B28: ='Profit & Loss'!B28 -> Mon | C28: Zilong | D28: Edwin
A29: ='Profit & Loss'!A29 -> 46024 | B29: ='Profit & Loss'!B29 -> Fri | C29: Angel | D29: Dylan | E29: Melvin | F29: Melvin +1 | G29: Lewis | H29: Edwin | I29: Robinson | J29: Nic
A30: ='Profit & Loss'!A30 -> 46026 | B30: ='Profit & Loss'!B30 -> Sun | C30: Joo Ching | D30: Zenn Goh | E30: Zilong
A31: ='Profit & Loss'!A31 -> 46033 | B31: ='Profit & Loss'!B31 -> Sun | C31: Joo Ching | D31: Lian | E31: Chong | F31: Chong +1 | G31: Chong +2 | H31: Zenn | I31: Kah Hao | J31: Melvin | K31: Melvin +1 | L31: Gerry | M31: Wai Chin | N31: Foo Hin | O31: Nic | P31: Jia Sheng
A32: ='Profit & Loss'!A32 -> 46036 | B32: ='Profit & Loss'!B32 -> Wed | C32: Joo Ching | D32: Edwin
A33: ='Profit & Loss'!A33 -> 46038 | B33: ='Profit & Loss'!B33 -> Fri | C33: Ray | D33: Dylan | E33: Neo BK | F33: Neo BK +1
A34: ='Profit & Loss'!A34 -> 46040 | B34: ='Profit & Loss'!B34 -> Sun | C34: Joo Ching | D34: Melvin | E34: Melvin +1 | F34: Melvin +2 | G34: Gerry | H34: Lewis | I34: Kc | J34: Nic
A35: ='Profit & Loss'!A35 -> 46044 | B35: ='Profit & Loss'!B35 -> Thurs | C35: Shannon | D35: Lim Kang
A36: ='Profit & Loss'!A36 -> 46047 | B36: ='Profit & Loss'!B36 -> Sun | C36: Joo Ching | D36: Jadon | E36: Weng Hong
A37: ='Profit & Loss'!A37 -> 46050 | B37: ='Profit & Loss'!B37 -> Wed | C37: Leon | D37: Lim Kang
A38: ='Profit & Loss'!A38 -> 46054 | B38: ='Profit & Loss'!B38 -> Sun | C38: Joo Ching | D38: Zenn Goh | E38: Joo Ching +1 (benjamin) | F38: Joo Ching +2 (edwin) | G38: Lewis | H38: Ray | I38: Zilong
A39: ='Profit & Loss'!A39 -> 46060 | B39: ='Profit & Loss'!B39 -> Sat | C39: Wei Nan | D39: Lewis
A40: ='Profit & Loss'!A40 -> 46061 | B40: ='Profit & Loss'!B40 -> Sun | C40: Joo Ching | D40: Zenn Goh | E40: Lim | F40: Zilong | G40: Jadon | H40: Jadon +1 (Yuuki) | I40: Jadon +2 (Xavier) | J40: Jadon +3 (Gabriel)
A41: ='Profit & Loss'!A41 -> 46065 | B41: ='Profit & Loss'!B41 -> Thurs | C41: Shannon | D41: Wei Nan
A42: ='Profit & Loss'!A42 -> 46066 | B42: ='Profit & Loss'!B42 -> Fri | C42: Jasper | D42: Lu | E42: Dylan | F42: Shary | G42: Jia Yan | H42: Jadon | I42: Jadon +1 (Yuuki) | J42: Wei Nan
A43: ='Profit & Loss'!A43 -> 46067 | B43: ='Profit & Loss'!B43 -> Sat | C43: Joo Ching | D43: Lu | E43: Zenn | F43: Shao Heng | G43: Rahul | H43: Zilong | I43: Jia Sheng | J43: Kang Wei
A44: ='Profit & Loss'!A44 -> 46076 | B44: ='Profit & Loss'!B44 -> Mon | C44: Joo Ching | D44: Jia Sheng
A45: ='Profit & Loss'!A45 -> 46077 | B45: ='Profit & Loss'!B45 -> Tues | C45: Zenn | D45: Javier | E45: Lewis | F45: Shao Heng | G45: Weng Hong | H45: Jason | I45: Wong (Stella's husband) | J45: Shannon
A46: ='Profit & Loss'!A46 -> 46082 | B46: ='Profit & Loss'!B46 -> Sun | C46: Weng Hong | D46: Lewis | E46: Nic | F46: Jadon | G46: Jadon +1 (Yuuki) | H46: Jadon +2 (Xavier) | I46: Jadon +3 (Gabriel) | J46: Jadon +4 (JC)
A47: ='Profit & Loss'!A47 -> 46084 | B47: ='Profit & Loss'!B47 -> Tues | C47: Shao Heng | D47: Ray
A48: ='Profit & Loss'!A48 -> 46087 | B48: ='Profit & Loss'!B48 -> Fri | C48: Shao Heng | D48: Jasper | E48: Javier | F48: CG
A49: ='Profit & Loss'!A49 -> 46089 | B49: ='Profit & Loss'!B49 -> Sun | C49: Joo Ching | D49: Zenn | E49: Chong Seng | F49: Chong Seng +1 | G49: Chong Seng +2 | H49: Chong Seng +3 | I49: Shao heng | J49: Jia Sheng
A50: ='Profit & Loss'!A50 -> 46096 | B50: ='Profit & Loss'!B50 -> Sun | C50: Joo Ching | D50: Zenn | E50: CJ | F50: CJ +1 | G50: Weng Hong | H50: Zilong | I50: Shao Heng | J50: KZ | K50: Yun Wee | L50: Dylan
A51: ='Profit & Loss'!A51 -> 46099 | B51: ='Profit & Loss'!B51 -> Wed | C51: KC | D51: Jia Sheng | E51: Douglas
A52: ='Profit & Loss'!A52 -> 46103 | B52: ='Profit & Loss'!B52 -> Sun | C52: Joo Ching | D52: Zenn | E52: Gerry | F52: Lewis | G52: Keith | H52: Keith +1 | I52: Andy
A53: ='Profit & Loss'!A53 -> 46104 | B53: ='Profit & Loss'!B53 -> Mon | C53: Jia Sheng | D53: Louis
A54: ='Profit & Loss'!A54 -> 46115 | B54: ='Profit & Loss'!B54 -> Fri | C54: KT | D54: Qi Xiang | E54: Johnny Lee | F54: Nicholas Lee
A55: ='Profit & Loss'!A55 -> 46124 | B55: ='Profit & Loss'!B55 -> Sun | C55: Sharry | D55: Joo Ching | E55: Jovina | F55: Louis | G55: Zenn | H55: Calvin | I55: Foo Hin | J55: Andy | K55: Andy +1 | L55: Hazel
A56: ='Profit & Loss'!A56 -> 46125 | B56: ='Profit & Loss'!B56 -> Mon | C56: Jasper | D56: Jia Sheng
A57: ='Profit & Loss'!A57 -> 46128 | B57: ='Profit & Loss'!B57 -> Thurs | C57: Foo Hin | D57: Praveen | E57: Han Wei | F57: Kelly
A58: ='Profit & Loss'!A58 -> 46130 | B58: ='Profit & Loss'!B58 -> Sat | C58: Brendan | D58: Brendan +1 | E58: Joo Ching | F58: Javier | G58: Andy | H58: Andy +1 | I58: Jia Sheng | J58: Shao Heng
A59: ='Profit & Loss'!A59 -> 46132 | B59: ='Profit & Loss'!B59 -> Mon | C59: Shao Heng | D59: Jadon
A60: ='Profit & Loss'!A60 -> 46134 | B60: ='Profit & Loss'!B60 -> Wed | C60: Shao Heng | D60: Jia Sheng
A61: ='Profit & Loss'!A61 -> 46138 | B61: ='Profit & Loss'!B61 -> Sun | C61: Joo Ching | D61: Jia Sheng
A62: ='Profit & Loss'!A62 -> 46140 | B62: ='Profit & Loss'!B62 -> Tues | C62: Pool Seng | D62: ST
A63: ='Profit & Loss'!A63 -> 46141 | B63: ='Profit & Loss'!B63 -> Wed | C63: Le Quang | D63: Jia Sheng
A64: ='Profit & Loss'!A64 -> 46144 | B64: ='Profit & Loss'!B64 -> Sat | C64: Joo Ching | D64: Shao Heng | E64: Jia Sheng | F64: Shawn | G64: ST | H64: Wai Meng | I64: KC
A65: ='Profit & Loss'!A65 -> 46152 | B65: ='Profit & Loss'!B65 -> Sun | C65: Joo Ching | D65: Brendan | E65: Brendan +1 | F65: Zenn Goh | G65: Shao Heng | H65: KC | I65: Gerry | J65: Foo Hin
A66: ='Profit & Loss'!A66 -> 46156 | B66: ='Profit & Loss'!B66 -> Thurs | C66: Shao Heng | D66: Daniel
A67: ='Profit & Loss'!A67 -> 46157 | B67: ='Profit & Loss'!B67 -> Fri | C67: Zenn Goh | D67: Dylan | E67: Amos | F67: Amos +1 (Daniel) | G67: Ong Kai Jun +1 (Gladius) | H67: Ong Kai Jun | I67: Mere | J67: Irene
A68: ='Profit & Loss'!A68 -> 46158 | B68: ='Profit & Loss'!B68 -> Sat | C68: Shao Heng | D68: Ken Goh | E68: Wai Co | F68: Alvin | G68: Alvin +1 | H68: Kang Wei | I68: Kang Wei +1 | J68: Nic
A69: ='Profit & Loss'!A69 -> 46160 | B69: ='Profit & Loss'!B69 -> Mon | C69: Kuang | D69: John Tei
A70: ='Profit & Loss'!A70 -> 46166 | B70: ='Profit & Loss'!B70 -> Sun | C70: Joo Ching | D70: Ken Goh
A71: ='Profit & Loss'!A71 -> 46171 | B71: ='Profit & Loss'!B71 -> Fri | C71: Shao Heng
A72: ='Profit & Loss'!A72 -> 46172 | B72: ='Profit & Loss'!B72 -> Sat
A73: ='Profit & Loss'!A73 -> 46180 | B73: ='Profit & Loss'!B73 -> Sun
A74: ='Profit & Loss'!A74 -> 0 | B74: ='Profit & Loss'!B74 -> 0
A75: ='Profit & Loss'!A75 -> 0 | B75: ='Profit & Loss'!B75 -> 0
A76: ='Profit & Loss'!A76 -> 0 | B76: ='Profit & Loss'!B76 -> 0
A77: ='Profit & Loss'!A77 -> 0 | B77: ='Profit & Loss'!B77 -> 0
A78: ='Profit & Loss'!A78 -> 0 | B78: ='Profit & Loss'!B78 -> 0
A79: ='Profit & Loss'!A79 -> 0 | B79: ='Profit & Loss'!B79 -> 0
A80: ='Profit & Loss'!A80 -> 0 | B80: ='Profit & Loss'!B80 -> 0
A81: ='Profit & Loss'!A81 -> 0 | B81: ='Profit & Loss'!B81 -> 0
A82: ='Profit & Loss'!A82 -> 0 | B82: ='Profit & Loss'!B82 -> 0
A83: ='Profit & Loss'!A83 -> 0 | B83: ='Profit & Loss'!B83 -> 0
... A999: ='Profit & Loss'!A999 -> 0 | B999: ='Profit & Loss'!B999 -> 0

Sheet Member List
A1: Member List
A5: Date | B5: Day | C5: Member 1 | D5: Member 2 | E5: Member 3 | F5: Member 4 | G5: Member 5 | H5: Member 6 | I5: Member 7 | J5: Member 8
A6: ='Profit & Loss'!A6 -> 45955 | B6: ='Profit & Loss'!B6 -> Sat | C6: Wei Cong | D6: Hui Min | E6: Belle | F6: Hazel
A7: ='Profit & Loss'!A7 -> 45960 | B7: ='Profit & Loss'!B7 -> Thurs | C7: Belle | D7: Seet | E7: Yiling
A8: ='Profit & Loss'!A8 -> 45963 | B8: ='Profit & Loss'!B8 -> Sun | C8: Belle | D8: Boo | E8: Seet | F8: Yiling | G8: Hazel
A9: ='Profit & Loss'!A9 -> 45965 | B9: ='Profit & Loss'!B9 -> Tues | C9: Belle | D9: Boo | E9: Seet | F9: Yiling | G9: Hazel
A10: ='Profit & Loss'!A10 -> 45969 | B10: ='Profit & Loss'!B10 -> Sat | C10: Hui Min | D10: Wei Cong | E10: Boo | F10: Seet | G10: Lionell
A11: ='Profit & Loss'!A11 -> 45973 | B11: ='Profit & Loss'!B11 -> Wed | C11: Boo | D11: Hui Min | E11: Seet
A12: ='Profit & Loss'!A12 -> 45977 | B12: ='Profit & Loss'!B12 -> Sun | C12: Belle | D12: Boo | E12: Hui Min | F12: Seet | G12: Wei Cong | H12: Yiling | I12: Lionell
A13: ='Profit & Loss'!A13 -> 45978 | B13: ='Profit & Loss'!B13 -> Mon | C13: Belle | D13: Boo
A14: ='Profit & Loss'!A14 -> 45979 | B14: ='Profit & Loss'!B14 -> Tues | C14: Hui Min | D14: Wei Cong
A15: ='Profit & Loss'!A15 -> 45981 | B15: ='Profit & Loss'!B15 -> Thurs | C15: Belle | D15: Boo | E15: Seet | F15: Yiling | G15: Hazel
A16: ='Profit & Loss'!A16 -> 45984 | B16: ='Profit & Loss'!B16 -> Sun | C16: Belle | D16: Boo | E16: Seet | F16: Yiling
A17: ='Profit & Loss'!A17 -> 45987 | B17: ='Profit & Loss'!B17 -> Wed | C17: Belle | D17: Boo | E17: Seet | F17: Yiling | G17: Hazel
A18: ='Profit & Loss'!A18 -> 45988 | B18: ='Profit & Loss'!B18 -> Thurs | C18: Belle | D18: Boo | E18: Seet | F18: Yiling | G18: Hazel
A19: ='Profit & Loss'!A19 -> 45991 | B19: ='Profit & Loss'!B19 -> Sun | C19: Seet | D19: Yiling
A20: ='Profit & Loss'!A20 -> 45998 | B20: ='Profit & Loss'!B20 -> Sun | C20: Belle | D20: Boo | E20: Seet | F20: Yiling | G20: Hazel
A21: ='Profit & Loss'!A21 -> 45999 | B21: ='Profit & Loss'!B21 -> Mon | C21: Belle | D21: Boo | E21: Seet | F21: Yiling
A22: ='Profit & Loss'!A22 -> 46001 | B22: ='Profit & Loss'!B22 -> Wed | C22: Belle | D22: Boo
A23: ='Profit & Loss'!A23 -> 46004 | B23: ='Profit & Loss'!B23 -> Sat | C23: Belle | D23: Boo | E23: Seet | F23: Yiling | G23: Hazel
A24: ='Profit & Loss'!A24 -> 46006 | B24: ='Profit & Loss'!B24 -> Mon | C24: Belle | D24: Belle | E24: Hui Min
A25: ='Profit & Loss'!A25 -> 46011 | B25: ='Profit & Loss'!B25 -> Sat | C25: Belle | D25: Boo | E25: Seet | F25: Yiling
A26: ='Profit & Loss'!A26 -> 46017 | B26: ='Profit & Loss'!B26 -> Fri | C26: Belle | D26: Boo | E26: Seet | F26: Yiling
A27: ='Profit & Loss'!A27 -> 46019 | B27: ='Profit & Loss'!B27 -> Sun | C27: Boo | D27: Seet | E27: Yiling
A28: ='Profit & Loss'!A28 -> 46020 | B28: ='Profit & Loss'!B28 -> Mon | C28: Belle | D28: Boo | E28: Seet | F28: Yiling
A29: ='Profit & Loss'!A29 -> 46024 | B29: ='Profit & Loss'!B29 -> Fri | C29: Belle | D29: Boo | E29: Seet | F29: Yiling
A30: ='Profit & Loss'!A30 -> 46026 | B30: ='Profit & Loss'!B30 -> Sun | C30: Seet | D30: Yiling | E30: Hazel
A31: ='Profit & Loss'!A31 -> 46033 | B31: ='Profit & Loss'!B31 -> Sun | C31: Belle | D31: Boo | E31: Seet | F31: Yiling
A32: ='Profit & Loss'!A32 -> 46036 | B32: ='Profit & Loss'!B32 -> Wed | C32: Belle | D32: Boo | E32: Seet | F32: Yiling
A33: ='Profit & Loss'!A33 -> 46038 | B33: ='Profit & Loss'!B33 -> Fri | C33: Seet | D33: Yiling
A34: ='Profit & Loss'!A34 -> 46040 | B34: ='Profit & Loss'!B34 -> Sun | C34: Belle | D34: Boo | E34: Seet | F34: Yiling
A35: ='Profit & Loss'!A35 -> 46044 | B35: ='Profit & Loss'!B35 -> Thurs | C35: Belle | D35: Boo | E35: Seet | F35: Yiling
A36: ='Profit & Loss'!A36 -> 46047 | B36: ='Profit & Loss'!B36 -> Sun | C36: Belle | D36: Boo | E36: Hazel
A37: ='Profit & Loss'!A37 -> 46050 | B37: ='Profit & Loss'!B37 -> Wed | C37: Belle | D37: Boo | E37: Seet | F37: Yiling
A38: ='Profit & Loss'!A38 -> 46054 | B38: ='Profit & Loss'!B38 -> Sun | C38: Belle | D38: Boo | E38: Seet | F38: Yiling | G38: Hazel
A39: ='Profit & Loss'!A39 -> 46060 | B39: ='Profit & Loss'!B39 -> Sat | C39: Belle | D39: Boo | E39: Seet | F39: Yiling
A40: ='Profit & Loss'!A40 -> 46061 | B40: ='Profit & Loss'!B40 -> Sun | C40: Belle | D40: Boo | E40: Seet | F40: Yiling
A41: ='Profit & Loss'!A41 -> 46065 | B41: ='Profit & Loss'!B41 -> Thurs | C41: Belle | D41: Boo | E41: Seet | F41: Yiling
A42: ='Profit & Loss'!A42 -> 46066 | B42: ='Profit & Loss'!B42 -> Fri | C42: Belle | D42: Boo | E42: Seet | F42: Yiling
A43: ='Profit & Loss'!A43 -> 46067 | B43: ='Profit & Loss'!B43 -> Sat | C43: Belle | D43: Boo | E43: Seet | F43: Yiling
A44: ='Profit & Loss'!A44 -> 46076 | B44: ='Profit & Loss'!B44 -> Mon | C44: Belle | D44: Boo | E44: Seet | F44: Yiling
A45: ='Profit & Loss'!A45 -> 46077 | B45: ='Profit & Loss'!B45 -> Tues | C45: Belle | D45: Boo | E45: Seet | F45: Yiling
A46: ='Profit & Loss'!A46 -> 46082 | B46: ='Profit & Loss'!B46 -> Sun | C46: Belle | D46: Boo | E46: Seet | F46: Yiling
A47: ='Profit & Loss'!A47 -> 46084 | B47: ='Profit & Loss'!B47 -> Tues | C47: Belle | D47: Boo | E47: Seet | F47: Yiling
A48: ='Profit & Loss'!A48 -> 46087 | B48: ='Profit & Loss'!B48 -> Fri | C48: Belle | D48: Boo
A49: ='Profit & Loss'!A49 -> 46089 | B49: ='Profit & Loss'!B49 -> Sun | C49: Belle | D49: Boo | E49: Seet | F49: Yiling
A50: ='Profit & Loss'!A50 -> 46096 | B50: ='Profit & Loss'!B50 -> Sun | C50: Hazel | D50: Boo
A51: ='Profit & Loss'!A51 -> 46099 | B51: ='Profit & Loss'!B51 -> Wed | C51: Yiling | D51: Boo | E51: Seet
A52: ='Profit & Loss'!A52 -> 46103 | B52: ='Profit & Loss'!B52 -> Sun | C52: Belle | D52: Boo | E52: Seet | F52: Yiling | G52: Hazel
A53: ='Profit & Loss'!A53 -> 46104 | B53: ='Profit & Loss'!B53 -> Mon | C53: Belle | D53: Boo | E53: Seet | F53: Yiling
A54: ='Profit & Loss'!A54 -> 46115 | B54: ='Profit & Loss'!B54 -> Fri | C54: Seet | D54: Yiling
A55: ='Profit & Loss'!A55 -> 46124 | B55: ='Profit & Loss'!B55 -> Sun | C55: Seet | D55: Yiling
A56: ='Profit & Loss'!A56 -> 46125 | B56: ='Profit & Loss'!B56 -> Mon | C56: Belle | D56: Boo | E56: Seet | F56: Yiling
A57: ='Profit & Loss'!A57 -> 46128 | B57: ='Profit & Loss'!B57 -> Thurs | C57: Seet | D57: Yiling
A58: ='Profit & Loss'!A58 -> 46130 | B58: ='Profit & Loss'!B58 -> Sat | C58: Belle | D58: Boo | E58: Seet | F58: Yiling
A59: ='Profit & Loss'!A59 -> 46132 | B59: ='Profit & Loss'!B59 -> Mon | C59: Belle | D59: Boo | E59: Seet | F59: Yiling
A60: ='Profit & Loss'!A60 -> 46134 | B60: ='Profit & Loss'!B60 -> Wed | C60: Belle | D60: Boo | E60: Seet | F60: Yiling
A61: ='Profit & Loss'!A61 -> 46138 | B61: ='Profit & Loss'!B61 -> Sun | C61: Belle | D61: Boo | E61: Seet | F61: Yiling
A62: ='Profit & Loss'!A62 -> 46140 | B62: ='Profit & Loss'!B62 -> Tues | C62: Belle | D62: Boo | E62: Seet | F62: Yiling
A63: ='Profit & Loss'!A63 -> 46141 | B63: ='Profit & Loss'!B63 -> Wed | C63: Belle | D63: Boo | E63: Seet | F63: Yiling
A64: ='Profit & Loss'!A64 -> 46144 | B64: ='Profit & Loss'!B64 -> Sat | C64: Belle | D64: Boo | E64: Seet | F64: Yiling | G64: Hazel
A65: ='Profit & Loss'!A65 -> 46152 | B65: ='Profit & Loss'!B65 -> Sun | C65: Belle | D65: Boo | E65: Seet | F65: Yiling
A66: ='Profit & Loss'!A66 -> 46156 | B66: ='Profit & Loss'!B66 -> Thurs | C66: Belle | D66: Boo | E66: Seet | F66: Yiling
A67: ='Profit & Loss'!A67 -> 46157 | B67: ='Profit & Loss'!B67 -> Fri | C67: Seet | D67: Yiling | E67: Belle | F67: Boo
A68: ='Profit & Loss'!A68 -> 46158 | B68: ='Profit & Loss'!B68 -> Sat | C68: Seet | D68: Yiling | E68: Belle | F68: Boo
A69: ='Profit & Loss'!A69 -> 46160 | B69: ='Profit & Loss'!B69 -> Mon | C69: Belle | D69: Boo | E69: Seet | F69: Yiling
A70: ='Profit & Loss'!A70 -> 46166 | B70: ='Profit & Loss'!B70 -> Sun | C70: Belle | D70: Boo
A71: ='Profit & Loss'!A71 -> 46171 | B71: ='Profit & Loss'!B71 -> Fri | C71: Belle | D71: Boo
A72: ='Profit & Loss'!A72 -> 46172 | B72: ='Profit & Loss'!B72 -> Sat | C72: Seet | D72: Yiling
A73: ='Profit & Loss'!A73 -> 46180 | B73: ='Profit & Loss'!B73 -> Sun | C73: Belle | D73: Boo
A74: ='Profit & Loss'!A74 -> 0 | B74: ='Profit & Loss'!B74 -> 0
A75: ='Profit & Loss'!A75 -> 0 | B75: ='Profit & Loss'!B75 -> 0
A76: ='Profit & Loss'!A76 -> 0 | B76: ='Profit & Loss'!B76 -> 0
A77: ='Profit & Loss'!A77 -> 0 | B77: ='Profit & Loss'!B77 -> 0
A78: ='Profit & Loss'!A78 -> 0 | B78: ='Profit & Loss'!B78 -> 0
A79: ='Profit & Loss'!A79 -> 0 | B79: ='Profit & Loss'!B79 -> 0
A80: ='Profit & Loss'!A80 -> 0 | B80: ='Profit & Loss'!B80 -> 0
A81: ='Profit & Loss'!A81 -> 0 | B81: ='Profit & Loss'!B81 -> 0
A82: ='Profit & Loss'!A82 -> 0 | B82: ='Profit & Loss'!B82 -> 0
A83: ='Profit & Loss'!A83 -> 0 | B83: ='Profit & Loss'!B83 -> 0
A84: ='Profit & Loss'!A84 -> 0 | B84: ='Profit & Loss'!B84 -> 0
A85: ='Profit & Loss'!A85 -> 0 | B85: ='Profit & Loss'!B85 -> 0
... A999: ='Profit & Loss'!A999 -> 0 | B999: ='Profit & Loss'!B999 -> 0

Sheet Shuttle Purchase
A1: Shuttle Purchase
A4: Shuttle Type | B4: Shuttle Cost ($ per Tube) | C4: Shuttle Cost ($ per Shuttle) | D4: Purchased Date | E4: Belle & Boo (No. of Shuttles) | G4: Seet & Yiling (No. of Shuttles) | I4: Hui Min (No. of Shuttles) | K4: Wei Cong (No. of Shuttles)
A5: Ultimate (Sep 2025) | B5: 41.35 | C5: =B5/12 -> 3.4458333 | E5: 87 | F5: =QUOTIENT(E5,12) & " tubes and " & MOD(E5,12) & " shuttles" -> 7 tubes and 3 shuttles | G5: 144 | H5: =QUOTIENT(G5,12) & " tubes and " & MOD(G5,12) & " shuttles" -> 12 tubes and 0 shuttles | I5: 12 | J5: =QUOTIENT(I5,12) & " tubes and " & MOD(I5,12) & " shuttles" -> 1 tubes and 0 shuttles | K5: 29 | L5: =QUOTIENT(K5,12) & " tubes and " & MOD(K5,12) & " shuttles" -> 2 tubes and 5 shuttles
A6: Victor | B6: 29.33 | C6: =B6/12 -> 2.4441667 | E6: - | F6: - | G6: - | H6: - | I6: 17 | J6: =QUOTIENT(I6,12) & " tubes and " & MOD(I6,12) & " shuttles" -> 1 tubes and 5 shuttles | K6: - | L6: -
A7: Felet | B7: 33.36 | C7: =B7/12 -> 2.78 | E7: - | F7: - | G7: - | H7: - | I7: 5 | J7: =QUOTIENT(I7,12) & " tubes and " & MOD(I7,12) & " shuttles" -> 0 tubes and 5 shuttles | K7: - | L7: -
A8: Ultimate (Nov 2025) | B8: =428.58/10 -> 42.858 | C8: =B8/12 -> 3.5715 | D8: 45990 | E8: 53 | F8: =QUOTIENT(E8,12) & " tubes and " & MOD(E8,12) & " shuttles" -> 4 tubes and 5 shuttles | G8: 67 | H8: =QUOTIENT(G8,12) & " tubes and " & MOD(G8,12) & " shuttles" -> 5 tubes and 7 shuttles | I8: - | J8: - | K8: - | L8: -
A9: Supreme (Nov 2025) | B9: =415.97/10 -> 41.597 | C9: =B9/12 -> 3.4664167 | D9: 45990 | E9: 24 | F9: =QUOTIENT(E9,12) & " tubes and " & MOD(E9,12) & " shuttles" -> 2 tubes and 0 shuttles | G9: 96 | H9: =QUOTIENT(G9,12) & " tubes and " & MOD(G9,12) & " shuttles" -> 8 tubes and 0 shuttles | I9: - | J9: - | K9: - | L9: -
A10: Supreme (Joo Ching) | B10: 40 | C10: =B10/12 -> 3.3333333 | D10: 46033 | E10: 12 | F10: =QUOTIENT(E10,12) & " tubes and " & MOD(E10,12) & " shuttles" -> 1 tubes and 0 shuttles
A11: Ultimate (Mar 2026) | B11: =438.86/10 -> 43.886 | C11: =B11/12 -> 3.6571667 | D11: 46110 | E11: 0 | F11: =QUOTIENT(E11,12) & " tubes and " & MOD(E11,12) & " shuttles" -> 0 tubes and 0 shuttles | G11: 120 | H11: =QUOTIENT(G11,12) & " tubes and " & MOD(G11,12) & " shuttles" -> 10 tubes and 0 shuttles

Sheet Shuttle Count - Ultimate (Sep 2
A1: Shuttle Count - Ultimate (Sep 2025)
C4: No of Shuttles Used for Game | G4: Remaing No. of Shuttles | O4: Total Number of Remaining Shuttles
A5: Date | B5: Day | C5: Belle & Boo | D5: Seet & Yiling | E5: Hui Min | F5: Wei Cong | G5: Belle & Boo | I5: Seet & Yiling | K5: Hui Min | M5: Wei Cong
A6: ='Profit & Loss'!A6 -> 45955 | B6: ='Profit & Loss'!B6 -> Sat | F6: 11 | G6: =IF(C6=" ",'Shuttle Purchase'!E5,'Shuttle Purchase'!E5-C6) -> 87 | H6: =QUOTIENT(G6,12) & " tubes and " & MOD(G6,12) & " shuttles" -> 7 tubes and 3 shuttles | I6: =IF(D6=" ",'Shuttle Purchase'!G5,'Shuttle Purchase'!G5-D6) -> 144 | J6: =QUOTIENT(I6,12) & " tubes and " & MOD(I6,12) & " shuttles" -> 12 tubes and 0 shuttles | K6: =IF(E6=" ",'Shuttle Purchase'!I5,'Shuttle Purchase'!I5-E6) -> 12 | L6: =QUOTIENT(K6,12) & " tubes and " & MOD(K6,12) & " shuttles" -> 1 tubes and 0 shuttles | M6: =IF(F6=" ",'Shuttle Purchase'!K5,'Shuttle Purchase'!K5-F6) -> 18 | N6: =QUOTIENT(M6,12) & " tubes and " & MOD(M6,12) & " shuttles" -> 1 tubes and 6 shuttles | O6: =SUM(G6:M6) -> 261 | P6: =QUOTIENT(O6,12) & " tubes and " & MOD(O6,12) & " shuttles" -> 21 tubes and 9 shuttles
A7: ='Profit & Loss'!A7 -> 45960 | B7: ='Profit & Loss'!B7 -> Thurs | C7: 5 | G7: =IF(C7=" ",G6,G6-C7) -> 82 | H7: =QUOTIENT(G7,12) & " tubes and " & MOD(G7,12) & " shuttles" -> 6 tubes and 10 shuttles | I7: =IF(D7=" ",I6,I6-D7) -> 144 | J7: =QUOTIENT(I7,12) & " tubes and " & MOD(I7,12) & " shuttles" -> 12 tubes and 0 shuttles | K7: =IF(E7=" ",K6,K6-E7) -> 12 | L7: =QUOTIENT(K7,12) & " tubes and " & MOD(K7,12) & " shuttles" -> 1 tubes and 0 shuttles | M7: =IF(F7=" ",M6,M6-F7) -> 18 | N7: =QUOTIENT(M7,12) & " tubes and " & MOD(M7,12) & " shuttles" -> 1 tubes and 6 shuttles | O7: =SUM(G7:M7) -> 256 | P7: =QUOTIENT(O7,12) & " tubes and " & MOD(O7,12) & " shuttles" -> 21 tubes and 4 shuttles
A8: ='Profit & Loss'!A8 -> 45963 | B8: ='Profit & Loss'!B8 -> Sun | D8: 11 | G8: =IF(C8=" ",G7,G7-C8) -> 82 | H8: =QUOTIENT(G8,12) & " tubes and " & MOD(G8,12) & " shuttles" -> 6 tubes and 10 shuttles | I8: =IF(D8=" ",I7,I7-D8) -> 133 | J8: =QUOTIENT(I8,12) & " tubes and " & MOD(I8,12) & " shuttles" -> 11 tubes and 1 shuttles | K8: =IF(E8=" ",K7,K7-E8) -> 12 | L8: =QUOTIENT(K8,12) & " tubes and " & MOD(K8,12) & " shuttles" -> 1 tubes and 0 shuttles | M8: =IF(F8=" ",M7,M7-F8) -> 18 | N8: =QUOTIENT(M8,12) & " tubes and " & MOD(M8,12) & " shuttles" -> 1 tubes and 6 shuttles | O8: =SUM(G8:M8) -> 245 | P8: =QUOTIENT(O8,12) & " tubes and " & MOD(O8,12) & " shuttles" -> 20 tubes and 5 shuttles
A9: ='Profit & Loss'!A9 -> 45965 | B9: ='Profit & Loss'!B9 -> Tues | C9: 2 | D9: 1 | G9: =IF(C9=" ",G8,G8-C9) -> 80 | H9: =QUOTIENT(G9,12) & " tubes and " & MOD(G9,12) & " shuttles" -> 6 tubes and 8 shuttles | I9: =IF(D9=" ",I8,I8-D9) -> 132 | J9: =QUOTIENT(I9,12) & " tubes and " & MOD(I9,12) & " shuttles" -> 11 tubes and 0 shuttles | K9: =IF(E9=" ",K8,K8-E9) -> 12 | L9: =QUOTIENT(K9,12) & " tubes and " & MOD(K9,12) & " shuttles" -> 1 tubes and 0 shuttles | M9: =IF(F9=" ",M8,M8-F9) -> 18 | N9: =QUOTIENT(M9,12) & " tubes and " & MOD(M9,12) & " shuttles" -> 1 tubes and 6 shuttles | O9: =SUM(G9:M9) -> 242 | P9: =QUOTIENT(O9,12) & " tubes and " & MOD(O9,12) & " shuttles" -> 20 tubes and 2 shuttles
A10: ='Profit & Loss'!A10 -> 45969 | B10: ='Profit & Loss'!B10 -> Sat | D10: 9 | G10: =IF(C10=" ",G9,G9-C10) -> 80 | H10: =QUOTIENT(G10,12) & " tubes and " & MOD(G10,12) & " shuttles" -> 6 tubes and 8 shuttles | I10: =IF(D10=" ",I9,I9-D10) -> 123 | J10: =QUOTIENT(I10,12) & " tubes and " & MOD(I10,12) & " shuttles" -> 10 tubes and 3 shuttles | K10: =IF(E10=" ",K9,K9-E10) -> 12 | L10: =QUOTIENT(K10,12) & " tubes and " & MOD(K10,12) & " shuttles" -> 1 tubes and 0 shuttles | M10: =IF(F10=" ",M9,M9-F10) -> 18 | N10: =QUOTIENT(M10,12) & " tubes and " & MOD(M10,12) & " shuttles" -> 1 tubes and 6 shuttles | O10: =SUM(G10:M10) -> 233 | P10: =QUOTIENT(O10,12) & " tubes and " & MOD(O10,12) & " shuttles" -> 19 tubes and 5 shuttles
A11: ='Profit & Loss'!A11 -> 45973 | B11: ='Profit & Loss'!B11 -> Wed | D11: 3 | E11: 2 | G11: =IF(C11=" ",G10,G10-C11) -> 80 | H11: =QUOTIENT(G11,12) & " tubes and " & MOD(G11,12) & " shuttles" -> 6 tubes and 8 shuttles | I11: =IF(D11=" ",I10,I10-D11) -> 120 | J11: =QUOTIENT(I11,12) & " tubes and " & MOD(I11,12) & " shuttles" -> 10 tubes and 0 shuttles | K11: =IF(E11=" ",K10,K10-E11) -> 10 | L11: =QUOTIENT(K11,12) & " tubes and " & MOD(K11,12) & " shuttles" -> 0 tubes and 10 shuttles | M11: =IF(F11=" ",M10,M10-F11) -> 18 | N11: =QUOTIENT(M11,12) & " tubes and " & MOD(M11,12) & " shuttles" -> 1 tubes and 6 shuttles | O11: =SUM(G11:M11) -> 228 | P11: =QUOTIENT(O11,12) & " tubes and " & MOD(O11,12) & " shuttles" -> 19 tubes and 0 shuttles
A12: ='Profit & Loss'!A12 -> 45977 | B12: ='Profit & Loss'!B12 -> Sun | F12: 18 | G12: =IF(C12=" ",G11,G11-C12) -> 80 | H12: =QUOTIENT(G12,12) & " tubes and " & MOD(G12,12) & " shuttles" -> 6 tubes and 8 shuttles | I12: =IF(D12=" ",I11,I11-D12) -> 120 | J12: =QUOTIENT(I12,12) & " tubes and " & MOD(I12,12) & " shuttles" -> 10 tubes and 0 shuttles | K12: =IF(E12=" ",K11,K11-E12) -> 10 | L12: =QUOTIENT(K12,12) & " tubes and " & MOD(K12,12) & " shuttles" -> 0 tubes and 10 shuttles | M12: =IF(F12=" ",M11,M11-F12) -> 0 | N12: =QUOTIENT(M12,12) & " tubes and " & MOD(M12,12) & " shuttles" -> 0 tubes and 0 shuttles | O12: =SUM(G12:M12) -> 210 | P12: =QUOTIENT(O12,12) & " tubes and " & MOD(O12,12) & " shuttles" -> 17 tubes and 6 shuttles
A13: ='Profit & Loss'!A13 -> 45978 | B13: ='Profit & Loss'!B13 -> Mon | C13: 5 | G13: =IF(C13=" ",G12,G12-C13) -> 75 | H13: =QUOTIENT(G13,12) & " tubes and " & MOD(G13,12) & " shuttles" -> 6 tubes and 3 shuttles | I13: =IF(D13=" ",I12,I12-D13) -> 120 | J13: =QUOTIENT(I13,12) & " tubes and " & MOD(I13,12) & " shuttles" -> 10 tubes and 0 shuttles | K13: =IF(E13=" ",K12,K12-E13) -> 10 | L13: =QUOTIENT(K13,12) & " tubes and " & MOD(K13,12) & " shuttles" -> 0 tubes and 10 shuttles | M13: =IF(F13=" ",M12,M12-F13) -> 0 | N13: =QUOTIENT(M13,12) & " tubes and " & MOD(M13,12) & " shuttles" -> 0 tubes and 0 shuttles | O13: =SUM(G13:M13) -> 205 | P13: =QUOTIENT(O13,12) & " tubes and " & MOD(O13,12) & " shuttles" -> 17 tubes and 1 shuttles
A14: ='Profit & Loss'!A14 -> 45979 | B14: ='Profit & Loss'!B14 -> Tues | E14: 10 | G14: =IF(C14=" ",G13,G13-C14) -> 75 | H14: =QUOTIENT(G14,12) & " tubes and " & MOD(G14,12) & " shuttles" -> 6 tubes and 3 shuttles | I14: =IF(D14=" ",I13,I13-D14) -> 120 | J14: =QUOTIENT(I14,12) & " tubes and " & MOD(I14,12) & " shuttles" -> 10 tubes and 0 shuttles | K14: =IF(E14=" ",K13,K13-E14) -> 0 | L14: =QUOTIENT(K14,12) & " tubes and " & MOD(K14,12) & " shuttles" -> 0 tubes and 0 shuttles | M14: =IF(F14=" ",M13,M13-F14) -> 0 | N14: =QUOTIENT(M14,12) & " tubes and " & MOD(M14,12) & " shuttles" -> 0 tubes and 0 shuttles | O14: =SUM(G14:M14) -> 195 | P14: =QUOTIENT(O14,12) & " tubes and " & MOD(O14,12) & " shuttles" -> 16 tubes and 3 shuttles
A15: ='Profit & Loss'!A15 -> 45981 | B15: ='Profit & Loss'!B15 -> Thurs | D15: 4 | G15: =IF(C15=" ",G14,G14-C15) -> 75 | H15: =QUOTIENT(G15,12) & " tubes and " & MOD(G15,12) & " shuttles" -> 6 tubes and 3 shuttles | I15: =IF(D15=" ",I14,I14-D15) -> 116 | J15: =QUOTIENT(I15,12) & " tubes and " & MOD(I15,12) & " shuttles" -> 9 tubes and 8 shuttles | K15: =IF(E15=" ",K14,K14-E15) -> 0 | L15: =QUOTIENT(K15,12) & " tubes and " & MOD(K15,12) & " shuttles" -> 0 tubes and 0 shuttles | M15: =IF(F15=" ",M14,M14-F15) -> 0 | N15: =QUOTIENT(M15,12) & " tubes and " & MOD(M15,12) & " shuttles" -> 0 tubes and 0 shuttles | O15: =SUM(G15:M15) -> 191 | P15: =QUOTIENT(O15,12) & " tubes and " & MOD(O15,12) & " shuttles" -> 15 tubes and 11 shuttles
A16: ='Profit & Loss'!A16 -> 45984 | B16: ='Profit & Loss'!B16 -> Sun | C16: 3 | D16: 8 | G16: =IF(C16=" ",G15,G15-C16) -> 72 | H16: =QUOTIENT(G16,12) & " tubes and " & MOD(G16,12) & " shuttles" -> 6 tubes and 0 shuttles | I16: =IF(D16=" ",I15,I15-D16) -> 108 | J16: =QUOTIENT(I16,12) & " tubes and " & MOD(I16,12) & " shuttles" -> 9 tubes and 0 shuttles | K16: =IF(E16=" ",K15,K15-E16) -> 0 | L16: =QUOTIENT(K16,12) & " tubes and " & MOD(K16,12) & " shuttles" -> 0 tubes and 0 shuttles | M16: =IF(F16=" ",M15,M15-F16) -> 0 | N16: =QUOTIENT(M16,12) & " tubes and " & MOD(M16,12) & " shuttles" -> 0 tubes and 0 shuttles | O16: =SUM(G16:M16) -> 180 | P16: =QUOTIENT(O16,12) & " tubes and " & MOD(O16,12) & " shuttles" -> 15 tubes and 0 shuttles
A17: ='Profit & Loss'!A17 -> 45987 | B17: ='Profit & Loss'!B17 -> Wed | D17: 12 | G17: =IF(C17=" ",G16,G16-C17) -> 72 | H17: =QUOTIENT(G17,12) & " tubes and " & MOD(G17,12) & " shuttles" -> 6 tubes and 0 shuttles | I17: =IF(D17=" ",I16,I16-D17) -> 96 | J17: =QUOTIENT(I17,12) & " tubes and " & MOD(I17,12) & " shuttles" -> 8 tubes and 0 shuttles | K17: =IF(E17=" ",K16,K16-E17) -> 0 | L17: =QUOTIENT(K17,12) & " tubes and " & MOD(K17,12) & " shuttles" -> 0 tubes and 0 shuttles | M17: =IF(F17=" ",M16,M16-F17) -> 0 | N17: =QUOTIENT(M17,12) & " tubes and " & MOD(M17,12) & " shuttles" -> 0 tubes and 0 shuttles | O17: =SUM(G17:M17) -> 168 | P17: =QUOTIENT(O17,12) & " tubes and " & MOD(O17,12) & " shuttles" -> 14 tubes and 0 shuttles
A18: ='Profit & Loss'!A18 -> 45988 | B18: ='Profit & Loss'!B18 -> Thurs | C18: 3 | G18: =IF(C18=" ",G17,G17-C18) -> 69 | H18: =QUOTIENT(G18,12) & " tubes and " & MOD(G18,12) & " shuttles" -> 5 tubes and 9 shuttles | I18: =IF(D18=" ",I17,I17-D18) -> 96 | J18: =QUOTIENT(I18,12) & " tubes and " & MOD(I18,12) & " shuttles" -> 8 tubes and 0 shuttles | K18: =IF(E18=" ",K17,K17-E18) -> 0 | L18: =QUOTIENT(K18,12) & " tubes and " & MOD(K18,12) & " shuttles" -> 0 tubes and 0 shuttles | M18: =IF(F18=" ",M17,M17-F18) -> 0 | N18: =QUOTIENT(M18,12) & " tubes and " & MOD(M18,12) & " shuttles" -> 0 tubes and 0 shuttles | O18: =SUM(G18:M18) -> 165 | P18: =QUOTIENT(O18,12) & " tubes and " & MOD(O18,12) & " shuttles" -> 13 tubes and 9 shuttles
A19: ='Profit & Loss'!A19 -> 45991 | B19: ='Profit & Loss'!B19 -> Sun | C19: 6 | D19: 4 | G19: =IF(C19=" ",G18,G18-C19) -> 63 | H19: =QUOTIENT(G19,12) & " tubes and " & MOD(G19,12) & " shuttles" -> 5 tubes and 3 shuttles | I19: =IF(D19=" ",I18,I18-D19) -> 92 | J19: =QUOTIENT(I19,12) & " tubes and " & MOD(I19,12) & " shuttles" -> 7 tubes and 8 shuttles | K19: =IF(E19=" ",K18,K18-E19) -> 0 | L19: =QUOTIENT(K19,12) & " tubes and " & MOD(K19,12) & " shuttles" -> 0 tubes and 0 shuttles | M19: =IF(F19=" ",M18,M18-F19) -> 0 | N19: =QUOTIENT(M19,12) & " tubes and " & MOD(M19,12) & " shuttles" -> 0 tubes and 0 shuttles | O19: =SUM(G19:M19) -> 155 | P19: =QUOTIENT(O19,12) & " tubes and " & MOD(O19,12) & " shuttles" -> 12 tubes and 11 shuttles
A20: ='Profit & Loss'!A20 -> 45998 | B20: ='Profit & Loss'!B20 -> Sun | C20: 19 | G20: =IF(C20=" ",G19,G19-C20) -> 44 | H20: =QUOTIENT(G20,12) & " tubes and " & MOD(G20,12) & " shuttles" -> 3 tubes and 8 shuttles | I20: =IF(D20=" ",I19,I19-D20) -> 92 | J20: =QUOTIENT(I20,12) & " tubes and " & MOD(I20,12) & " shuttles" -> 7 tubes and 8 shuttles | K20: =IF(E20=" ",K19,K19-E20) -> 0 | L20: =QUOTIENT(K20,12) & " tubes and " & MOD(K20,12) & " shuttles" -> 0 tubes and 0 shuttles | M20: =IF(F20=" ",M19,M19-F20) -> 0 | N20: =QUOTIENT(M20,12) & " tubes and " & MOD(M20,12) & " shuttles" -> 0 tubes and 0 shuttles | O20: =SUM(G20:M20) -> 136 | P20: =QUOTIENT(O20,12) & " tubes and " & MOD(O20,12) & " shuttles" -> 11 tubes and 4 shuttles
A21: ='Profit & Loss'!A21 -> 45999 | B21: ='Profit & Loss'!B21 -> Mon | D21: 5 | G21: =IF(C21=" ",G20,G20-C21) -> 44 | H21: =QUOTIENT(G21,12) & " tubes and " & MOD(G21,12) & " shuttles" -> 3 tubes and 8 shuttles | I21: =IF(D21=" ",I20,I20-D21) -> 87 | J21: =QUOTIENT(I21,12) & " tubes and " & MOD(I21,12) & " shuttles" -> 7 tubes and 3 shuttles | K21: =IF(E21=" ",K20,K20-E21) -> 0 | L21: =QUOTIENT(K21,12) & " tubes and " & MOD(K21,12) & " shuttles" -> 0 tubes and 0 shuttles | M21: =IF(F21=" ",M20,M20-F21) -> 0 | N21: =QUOTIENT(M21,12) & " tubes and " & MOD(M21,12) & " shuttles" -> 0 tubes and 0 shuttles | O21: =SUM(G21:M21) -> 131 | P21: =QUOTIENT(O21,12) & " tubes and " & MOD(O21,12) & " shuttles" -> 10 tubes and 11 shuttles
A22: ='Profit & Loss'!A22 -> 46001 | B22: ='Profit & Loss'!B22 -> Wed | C22: 5 | G22: =IF(C22=" ",G21,G21-C22) -> 39 | H22: =QUOTIENT(G22,12) & " tubes and " & MOD(G22,12) & " shuttles" -> 3 tubes and 3 shuttles | I22: =IF(D22=" ",I21,I21-D22) -> 87 | J22: =QUOTIENT(I22,12) & " tubes and " & MOD(I22,12) & " shuttles" -> 7 tubes and 3 shuttles | K22: =IF(E22=" ",K21,K21-E22) -> 0 | L22: =QUOTIENT(K22,12) & " tubes and " & MOD(K22,12) & " shuttles" -> 0 tubes and 0 shuttles | M22: =IF(F22=" ",M21,M21-F22) -> 0 | N22: =QUOTIENT(M22,12) & " tubes and " & MOD(M22,12) & " shuttles" -> 0 tubes and 0 shuttles | O22: =SUM(G22:M22) -> 126 | P22: =QUOTIENT(O22,12) & " tubes and " & MOD(O22,12) & " shuttles" -> 10 tubes and 6 shuttles
A23: ='Profit & Loss'!A23 -> 46004 | B23: ='Profit & Loss'!B23 -> Sat | C23: 9 | D23: 3 | G23: =IF(C23=" ",G22,G22-C23) -> 30 | H23: =QUOTIENT(G23,12) & " tubes and " & MOD(G23,12) & " shuttles" -> 2 tubes and 6 shuttles | I23: =IF(D23=" ",I22,I22-D23) -> 84 | J23: =QUOTIENT(I23,12) & " tubes and " & MOD(I23,12) & " shuttles" -> 7 tubes and 0 shuttles | K23: =IF(E23=" ",K22,K22-E23) -> 0 | L23: =QUOTIENT(K23,12) & " tubes and " & MOD(K23,12) & " shuttles" -> 0 tubes and 0 shuttles | M23: =IF(F23=" ",M22,M22-F23) -> 0 | N23: =QUOTIENT(M23,12) & " tubes and " & MOD(M23,12) & " shuttles" -> 0 tubes and 0 shuttles | O23: =SUM(G23:M23) -> 114 | P23: =QUOTIENT(O23,12) & " tubes and " & MOD(O23,12) & " shuttles" -> 9 tubes and 6 shuttles
A24: ='Profit & Loss'!A24 -> 46006 | B24: ='Profit & Loss'!B24 -> Mon | C24: 5 | G24: =IF(C24=" ",G23,G23-C24) -> 25 | H24: =QUOTIENT(G24,12) & " tubes and " & MOD(G24,12) & " shuttles" -> 2 tubes and 1 shuttles | I24: =IF(D24=" ",I23,I23-D24) -> 84 | J24: =QUOTIENT(I24,12) & " tubes and " & MOD(I24,12) & " shuttles" -> 7 tubes and 0 shuttles | K24: =IF(E24=" ",K23,K23-E24) -> 0 | L24: =QUOTIENT(K24,12) & " tubes and " & MOD(K24,12) & " shuttles" -> 0 tubes and 0 shuttles | M24: =IF(F24=" ",M23,M23-F24) -> 0 | N24: =QUOTIENT(M24,12) & " tubes and " & MOD(M24,12) & " shuttles" -> 0 tubes and 0 shuttles | O24: =SUM(G24:M24) -> 109 | P24: =QUOTIENT(O24,12) & " tubes and " & MOD(O24,12) & " shuttles" -> 9 tubes and 1 shuttles
A25: ='Profit & Loss'!A25 -> 46011 | B25: ='Profit & Loss'!B25 -> Sat | D25: 10 | G25: =IF(C25=" ",G24,G24-C25) -> 25 | H25: =QUOTIENT(G25,12) & " tubes and " & MOD(G25,12) & " shuttles" -> 2 tubes and 1 shuttles | I25: =IF(D25=" ",I24,I24-D25) -> 74 | J25: =QUOTIENT(I25,12) & " tubes and " & MOD(I25,12) & " shuttles" -> 6 tubes and 2 shuttles | K25: =IF(E25=" ",K24,K24-E25) -> 0 | L25: =QUOTIENT(K25,12) & " tubes and " & MOD(K25,12) & " shuttles" -> 0 tubes and 0 shuttles | M25: =IF(F25=" ",M24,M24-F25) -> 0 | N25: =QUOTIENT(M25,12) & " tubes and " & MOD(M25,12) & " shuttles" -> 0 tubes and 0 shuttles | O25: =SUM(G25:M25) -> 99 | P25: =QUOTIENT(O25,12) & " tubes and " & MOD(O25,12) & " shuttles" -> 8 tubes and 3 shuttles
A26: ='Profit & Loss'!A26 -> 46017 | B26: ='Profit & Loss'!B26 -> Fri | C26: 6 | D26: 5 | G26: =IF(C26=" ",G25,G25-C26) -> 19 | H26: =QUOTIENT(G26,12) & " tubes and " & MOD(G26,12) & " shuttles" -> 1 tubes and 7 shuttles | I26: =IF(D26=" ",I25,I25-D26) -> 69 | J26: =QUOTIENT(I26,12) & " tubes and " & MOD(I26,12) & " shuttles" -> 5 tubes and 9 shuttles | K26: =IF(E26=" ",K25,K25-E26) -> 0 | L26: =QUOTIENT(K26,12) & " tubes and " & MOD(K26,12) & " shuttles" -> 0 tubes and 0 shuttles | M26: =IF(F26=" ",M25,M25-F26) -> 0 | N26: =QUOTIENT(M26,12) & " tubes and " & MOD(M26,12) & " shuttles" -> 0 tubes and 0 shuttles | O26: =SUM(G26:M26) -> 88 | P26: =QUOTIENT(O26,12) & " tubes and " & MOD(O26,12) & " shuttles" -> 7 tubes and 4 shuttles
A27: ='Profit & Loss'!A27 -> 46019 | B27: ='Profit & Loss'!B27 -> Sun | D27: 6 | G27: =IF(C27=" ",G26,G26-C27) -> 19 | H27: =QUOTIENT(G27,12) & " tubes and " & MOD(G27,12) & " shuttles" -> 1 tubes and 7 shuttles | I27: =IF(D27=" ",I26,I26-D27) -> 63 | J27: =QUOTIENT(I27,12) & " tubes and " & MOD(I27,12) & " shuttles" -> 5 tubes and 3 shuttles | K27: =IF(E27=" ",K26,K26-E27) -> 0 | L27: =QUOTIENT(K27,12) & " tubes and " & MOD(K27,12) & " shuttles" -> 0 tubes and 0 shuttles | M27: =IF(F27=" ",M26,M26-F27) -> 0 | N27: =QUOTIENT(M27,12) & " tubes and " & MOD(M27,12) & " shuttles" -> 0 tubes and 0 shuttles | O27: =SUM(G27:M27) -> 82 | P27: =QUOTIENT(O27,12) & " tubes and " & MOD(O27,12) & " shuttles" -> 6 tubes and 10 shuttles
A28: ='Profit & Loss'!A28 -> 46020 | B28: ='Profit & Loss'!B28 -> Mon | C28: 2 | D28: 3 | G28: =IF(C28=" ",G27,G27-C28) -> 17 | H28: =QUOTIENT(G28,12) & " tubes and " & MOD(G28,12) & " shuttles" -> 1 tubes and 5 shuttles | I28: =IF(D28=" ",I27,I27-D28) -> 60 | J28: =QUOTIENT(I28,12) & " tubes and " & MOD(I28,12) & " shuttles" -> 5 tubes and 0 shuttles | K28: =IF(E28=" ",K27,K27-E28) -> 0 | L28: =QUOTIENT(K28,12) & " tubes and " & MOD(K28,12) & " shuttles" -> 0 tubes and 0 shuttles | M28: =IF(F28=" ",M27,M27-F28) -> 0 | N28: =QUOTIENT(M28,12) & " tubes and " & MOD(M28,12) & " shuttles" -> 0 tubes and 0 shuttles | O28: =SUM(G28:M28) -> 77 | P28: =QUOTIENT(O28,12) & " tubes and " & MOD(O28,12) & " shuttles" -> 6 tubes and 5 shuttles
A29: ='Profit & Loss'!A29 -> 46024 | B29: ='Profit & Loss'!B29 -> Fri | C29: 3 | D29: 12 | G29: =IF(C29=" ",G28,G28-C29) -> 14 | H29: =QUOTIENT(G29,12) & " tubes and " & MOD(G29,12) & " shuttles" -> 1 tubes and 2 shuttles | I29: =IF(D29=" ",I28,I28-D29) -> 48 | J29: =QUOTIENT(I29,12) & " tubes and " & MOD(I29,12) & " shuttles" -> 4 tubes and 0 shuttles | K29: =IF(E29=" ",K28,K28-E29) -> 0 | L29: =QUOTIENT(K29,12) & " tubes and " & MOD(K29,12) & " shuttles" -> 0 tubes and 0 shuttles | M29: =IF(F29=" ",M28,M28-F29) -> 0 | N29: =QUOTIENT(M29,12) & " tubes and " & MOD(M29,12) & " shuttles" -> 0 tubes and 0 shuttles | O29: =SUM(G29:M29) -> 62 | P29: =QUOTIENT(O29,12) & " tubes and " & MOD(O29,12) & " shuttles" -> 5 tubes and 2 shuttles
A30: ='Profit & Loss'!A30 -> 46026 | B30: ='Profit & Loss'!B30 -> Sun | G30: =IF(C30=" ",G29,G29-C30) -> 14 | H30: =QUOTIENT(G30,12) & " tubes and " & MOD(G30,12) & " shuttles" -> 1 tubes and 2 shuttles | I30: =IF(D30=" ",I29,I29-D30) -> 48 | J30: =QUOTIENT(I30,12) & " tubes and " & MOD(I30,12) & " shuttles" -> 4 tubes and 0 shuttles | K30: =IF(E30=" ",K29,K29-E30) -> 0 | L30: =QUOTIENT(K30,12) & " tubes and " & MOD(K30,12) & " shuttles" -> 0 tubes and 0 shuttles | M30: =IF(F30=" ",M29,M29-F30) -> 0 | N30: =QUOTIENT(M30,12) & " tubes and " & MOD(M30,12) & " shuttles" -> 0 tubes and 0 shuttles | O30: =SUM(G30:M30) -> 62 | P30: =QUOTIENT(O30,12) & " tubes and " & MOD(O30,12) & " shuttles" -> 5 tubes and 2 shuttles
A31: ='Profit & Loss'!A31 -> 46033 | B31: ='Profit & Loss'!B31 -> Sun | D31: 10 | G31: =IF(C31=" ",G30,G30-C31) -> 14 | H31: =QUOTIENT(G31,12) & " tubes and " & MOD(G31,12) & " shuttles" -> 1 tubes and 2 shuttles | I31: =IF(D31=" ",I30,I30-D31) -> 38 | J31: =QUOTIENT(I31,12) & " tubes and " & MOD(I31,12) & " shuttles" -> 3 tubes and 2 shuttles | K31: =IF(E31=" ",K30,K30-E31) -> 0 | L31: =QUOTIENT(K31,12) & " tubes and " & MOD(K31,12) & " shuttles" -> 0 tubes and 0 shuttles | M31: =IF(F31=" ",M30,M30-F31) -> 0 | N31: =QUOTIENT(M31,12) & " tubes and " & MOD(M31,12) & " shuttles" -> 0 tubes and 0 shuttles | O31: =SUM(G31:M31) -> 52 | P31: =QUOTIENT(O31,12) & " tubes and " & MOD(O31,12) & " shuttles" -> 4 tubes and 4 shuttles
A32: ='Profit & Loss'!A32 -> 46036 | B32: ='Profit & Loss'!B32 -> Wed | D32: 2 | G32: =IF(C32=" ",G31,G31-C32) -> 14 | H32: =QUOTIENT(G32,12) & " tubes and " & MOD(G32,12) & " shuttles" -> 1 tubes and 2 shuttles | I32: =IF(D32=" ",I31,I31-D32) -> 36 | J32: =QUOTIENT(I32,12) & " tubes and " & MOD(I32,12) & " shuttles" -> 3 tubes and 0 shuttles | K32: =IF(E32=" ",K31,K31-E32) -> 0 | L32: =QUOTIENT(K32,12) & " tubes and " & MOD(K32,12) & " shuttles" -> 0 tubes and 0 shuttles | M32: =IF(F32=" ",M31,M31-F32) -> 0 | N32: =QUOTIENT(M32,12) & " tubes and " & MOD(M32,12) & " shuttles" -> 0 tubes and 0 shuttles | O32: =SUM(G32:M32) -> 50 | P32: =QUOTIENT(O32,12) & " tubes and " & MOD(O32,12) & " shuttles" -> 4 tubes and 2 shuttles
A33: ='Profit & Loss'!A33 -> 46038 | B33: ='Profit & Loss'!B33 -> Fri | D33: 7 | G33: =IF(C33=" ",G32,G32-C33) -> 14 | H33: =QUOTIENT(G33,12) & " tubes and " & MOD(G33,12) & " shuttles" -> 1 tubes and 2 shuttles | I33: =IF(D33=" ",I32,I32-D33) -> 29 | J33: =QUOTIENT(I33,12) & " tubes and " & MOD(I33,12) & " shuttles" -> 2 tubes and 5 shuttles | K33: =IF(E33=" ",K32,K32-E33) -> 0 | L33: =QUOTIENT(K33,12) & " tubes and " & MOD(K33,12) & " shuttles" -> 0 tubes and 0 shuttles | M33: =IF(F33=" ",M32,M32-F33) -> 0 | N33: =QUOTIENT(M33,12) & " tubes and " & MOD(M33,12) & " shuttles" -> 0 tubes and 0 shuttles | O33: =SUM(G33:M33) -> 43 | P33: =QUOTIENT(O33,12) & " tubes and " & MOD(O33,12) & " shuttles" -> 3 tubes and 7 shuttles
A34: ='Profit & Loss'!A34 -> 46040 | B34: ='Profit & Loss'!B34 -> Sun | C34: 8 | D34: 5 | G34: =IF(C34=" ",G33,G33-C34) -> 6 | H34: =QUOTIENT(G34,12) & " tubes and " & MOD(G34,12) & " shuttles" -> 0 tubes and 6 shuttles | I34: =IF(D34=" ",I33,I33-D34) -> 24 | J34: =QUOTIENT(I34,12) & " tubes and " & MOD(I34,12) & " shuttles" -> 2 tubes and 0 shuttles | K34: =IF(E34=" ",K33,K33-E34) -> 0 | L34: =QUOTIENT(K34,12) & " tubes and " & MOD(K34,12) & " shuttles" -> 0 tubes and 0 shuttles | M34: =IF(F34=" ",M33,M33-F34) -> 0 | N34: =QUOTIENT(M34,12) & " tubes and " & MOD(M34,12) & " shuttles" -> 0 tubes and 0 shuttles | O34: =SUM(G34:M34) -> 30 | P34: =QUOTIENT(O34,12) & " tubes and " & MOD(O34,12) & " shuttles" -> 2 tubes and 6 shuttles
A35: ='Profit & Loss'!A35 -> 46044 | B35: ='Profit & Loss'!B35 -> Thurs | D35: 5 | G35: =IF(C35=" ",G34,G34-C35) -> 6 | H35: =QUOTIENT(G35,12) & " tubes and " & MOD(G35,12) & " shuttles" -> 0 tubes and 6 shuttles | I35: =IF(D35=" ",I34,I34-D35) -> 19 | J35: =QUOTIENT(I35,12) & " tubes and " & MOD(I35,12) & " shuttles" -> 1 tubes and 7 shuttles | K35: =IF(E35=" ",K34,K34-E35) -> 0 | L35: =QUOTIENT(K35,12) & " tubes and " & MOD(K35,12) & " shuttles" -> 0 tubes and 0 shuttles | M35: =IF(F35=" ",M34,M34-F35) -> 0 | N35: =QUOTIENT(M35,12) & " tubes and " & MOD(M35,12) & " shuttles" -> 0 tubes and 0 shuttles | O35: =SUM(G35:M35) -> 25 | P35: =QUOTIENT(O35,12) & " tubes and " & MOD(O35,12) & " shuttles" -> 2 tubes and 1 shuttles
A36: ='Profit & Loss'!A36 -> 46047 | B36: ='Profit & Loss'!B36 -> Sun | C36: 4 | G36: =IF(C36=" ",G37,G37-C36) -> 2 | H36: =QUOTIENT(G36,12) & " tubes and " & MOD(G36,12) & " shuttles" -> 0 tubes and 2 shuttles | I36: =IF(D36=" ",I37,I37-D36) -> 14 | J36: =QUOTIENT(I36,12) & " tubes and " & MOD(I36,12) & " shuttles" -> 1 tubes and 2 shuttles | K36: =IF(E36=" ",K37,K37-E36) -> 0 | L36: =QUOTIENT(K36,12) & " tubes and " & MOD(K36,12) & " shuttles" -> 0 tubes and 0 shuttles | M36: =IF(F36=" ",M37,M37-F36) -> 0 | N36: =QUOTIENT(M36,12) & " tubes and " & MOD(M36,12) & " shuttles" -> 0 tubes and 0 shuttles | O36: =SUM(G36:M36) -> 16 | P36: =QUOTIENT(O36,12) & " tubes and " & MOD(O36,12) & " shuttles" -> 1 tubes and 4 shuttles
A37: ='Profit & Loss'!A37 -> 46050 | B37: ='Profit & Loss'!B37 -> Wed | D37: 5 | G37: =IF(C37=" ",G35,G35-C37) -> 6 | H37: =QUOTIENT(G37,12) & " tubes and " & MOD(G37,12) & " shuttles" -> 0 tubes and 6 shuttles | I37: =IF(D37=" ",I35,I35-D37) -> 14 | J37: =QUOTIENT(I37,12) & " tubes and " & MOD(I37,12) & " shuttles" -> 1 tubes and 2 shuttles | K37: =IF(E37=" ",K35,K35-E37) -> 0 | L37: =QUOTIENT(K37,12) & " tubes and " & MOD(K37,12) & " shuttles" -> 0 tubes and 0 shuttles | M37: =IF(F37=" ",M35,M35-F37) -> 0 | N37: =QUOTIENT(M37,12) & " tubes and " & MOD(M37,12) & " shuttles" -> 0 tubes and 0 shuttles | O37: =SUM(G37:M37) -> 20 | P37: =QUOTIENT(O37,12) & " tubes and " & MOD(O37,12) & " shuttles" -> 1 tubes and 8 shuttles
A38: ='Profit & Loss'!A38 -> 46054 | B38: ='Profit & Loss'!B38 -> Sun | D38: 10 | G38: =IF(C38=" ",G36,G36-C38) -> 2 | H38: =QUOTIENT(G38,12) & " tubes and " & MOD(G38,12) & " shuttles" -> 0 tubes and 2 shuttles | I38: =IF(D38=" ",I36,I36-D38) -> 4 | J38: =QUOTIENT(I38,12) & " tubes and " & MOD(I38,12) & " shuttles" -> 0 tubes and 4 shuttles | K38: =IF(E38=" ",K36,K36-E38) -> 0 | L38: =QUOTIENT(K38,12) & " tubes and " & MOD(K38,12) & " shuttles" -> 0 tubes and 0 shuttles | M38: =IF(F38=" ",M36,M36-F38) -> 0 | N38: =QUOTIENT(M38,12) & " tubes and " & MOD(M38,12) & " shuttles" -> 0 tubes and 0 shuttles | O38: =SUM(G38:M38) -> 6 | P38: =QUOTIENT(O38,12) & " tubes and " & MOD(O38,12) & " shuttles" -> 0 tubes and 6 shuttles
A39: ='Profit & Loss'!A39 -> 46060 | B39: ='Profit & Loss'!B39 -> Sat | D39: 4 | G39: =IF(C39=" ",G38,G38-C39) -> 2 | H39: =QUOTIENT(G39,12) & " tubes and " & MOD(G39,12) & " shuttles" -> 0 tubes and 2 shuttles | I39: =IF(D39=" ",I38,I38-D39) -> 0 | J39: =QUOTIENT(I39,12) & " tubes and " & MOD(I39,12) & " shuttles" -> 0 tubes and 0 shuttles | K39: =IF(E39=" ",K38,K38-E39) -> 0 | L39: =QUOTIENT(K39,12) & " tubes and " & MOD(K39,12) & " shuttles" -> 0 tubes and 0 shuttles | M39: =IF(F39=" ",M38,M38-F39) -> 0 | N39: =QUOTIENT(M39,12) & " tubes and " & MOD(M39,12) & " shuttles" -> 0 tubes and 0 shuttles | O39: =SUM(G39:M39) -> 2 | P39: =QUOTIENT(O39,12) & " tubes and " & MOD(O39,12) & " shuttles" -> 0 tubes and 2 shuttles
A40: ='Profit & Loss'!A40 -> 46061 | B40: ='Profit & Loss'!B40 -> Sun | G40: =IF(C40=" ",G39,G39-C40) -> 2 | H40: =QUOTIENT(G40,12) & " tubes and " & MOD(G40,12) & " shuttles" -> 0 tubes and 2 shuttles | I40: =IF(D40=" ",I39,I39-D40) -> 0 | J40: =QUOTIENT(I40,12) & " tubes and " & MOD(I40,12) & " shuttles" -> 0 tubes and 0 shuttles | K40: =IF(E40=" ",K39,K39-E40) -> 0 | L40: =QUOTIENT(K40,12) & " tubes and " & MOD(K40,12) & " shuttles" -> 0 tubes and 0 shuttles | M40: =IF(F40=" ",M39,M39-F40) -> 0 | N40: =QUOTIENT(M40,12) & " tubes and " & MOD(M40,12) & " shuttles" -> 0 tubes and 0 shuttles | O40: =SUM(G40:M40) -> 2 | P40: =QUOTIENT(O40,12) & " tubes and " & MOD(O40,12) & " shuttles" -> 0 tubes and 2 shuttles
A41: ='Profit & Loss'!A41 -> 46065 | B41: ='Profit & Loss'!B41 -> Thurs | G41: =IF(C41=" ",G40,G40-C41) -> 2 | H41: =QUOTIENT(G41,12) & " tubes and " & MOD(G41,12) & " shuttles" -> 0 tubes and 2 shuttles | I41: =IF(D41=" ",I40,I40-D41) -> 0 | J41: =QUOTIENT(I41,12) & " tubes and " & MOD(I41,12) & " shuttles" -> 0 tubes and 0 shuttles | K41: =IF(E41=" ",K40,K40-E41) -> 0 | L41: =QUOTIENT(K41,12) & " tubes and " & MOD(K41,12) & " shuttles" -> 0 tubes and 0 shuttles | M41: =IF(F41=" ",M40,M40-F41) -> 0 | N41: =QUOTIENT(M41,12) & " tubes and " & MOD(M41,12) & " shuttles" -> 0 tubes and 0 shuttles | O41: =SUM(G41:M41) -> 2 | P41: =QUOTIENT(O41,12) & " tubes and " & MOD(O41,12) & " shuttles" -> 0 tubes and 2 shuttles
